Workbook

Sheet Top Targets
A1: Wholesale non-QM prospects: banks and credit unions headquartered in LA, Orange, Riverside and San Bernardino counties
A2: Data as of June 30, 2026 (FDIC/NCUA call reports) and calendar 2025 (HMDA). Tier 1 and Tier 2 only, sorted by capacity score. Scores and tiers pull live from the Banks / Credit Unions tabs.
A4: Rank | B4: Type | C4: Institution | D4: City | E4: County | F4: Total assets ($M) | G4: Loan-to-deposit / share | H4: Liquidity | I4: Capital ratio | J4: % kept in portfolio (HMDA) | K4: Wholesale status | L4: Capacity score | M4: Tier | N4: Why they might say yes
A5: 1 | B5: Credit Union | C5: ='Credit Unions'!B40 | D5: ='Credit Unions'!C40 | E5: ='Credit Unions'!D40 | F5: ='Credit Unions'!E40 | G5: ='Credit Unions'!I40 | H5: ='Credit Unions'!J40 | I5: ='Credit Unions'!K40 | J5: =IF('Credit Unions'!U40="","n/a",'Credit Unions'!U40) | K5: ='Credit Unions'!Y40 | L5: ='Credit Unions'!Z40 | M5: ='Credit Unions'!AA40 | N5: Lends out only 35% of deposits; 69% of assets in cash/securities; strong capital (13.1%); little or no mortgage lending today, so you'd be pitching a new business line
A6: 2 | B6: Credit Union | C6: ='Credit Unions'!B39 | D6: ='Credit Unions'!C39 | E6: ='Credit Unions'!D39 | F6: ='Credit Unions'!E39 | G6: ='Credit Unions'!I39 | H6: ='Credit Unions'!J39 | I6: ='Credit Unions'!K39 | J6: =IF('Credit Unions'!U39="","n/a",'Credit Unions'!U39) | K6: ='Credit Unions'!Y39 | L6: ='Credit Unions'!Z39 | M6: ='Credit Unions'!AA39 | N6: Lends out only 47% of deposits; 61% of assets in cash/securities; little or no mortgage lending today, so you'd be pitching a new business line
A7: 3 | B7: Bank | C7: ='Banks'!B4 | D7: ='Banks'!C4 | E7: ='Banks'!D4 | F7: ='Banks'!F4 | G7: ='Banks'!J4 | H7: ='Banks'!K4 | I7: ='Banks'!L4 | J7: =IF('Banks'!T4="","n/a",'Banks'!T4) | K7: ='Banks'!X4 | L7: ='Banks'!Y4 | M7: ='Banks'!Z4 | N7: Lends out only 48% of deposits; 55% of assets in cash/securities; deposits outgrowing loans; little or no mortgage lending today, so you'd be pitching a new business line
A8: 4 | B8: Bank | C8: ='Banks'!B8 | D8: ='Banks'!C8 | E8: ='Banks'!D8 | F8: ='Banks'!F8 | G8: ='Banks'!J8 | H8: ='Banks'!K8 | I8: ='Banks'!L8 | J8: =IF('Banks'!T8="","n/a",'Banks'!T8) | K8: ='Banks'!X8 | L8: ='Banks'!Y8 | M8: ='Banks'!Z8 | N8: CRE at 470% of capital (above the 300% regulatory guide) so resi would diversify; deposits outgrowing loans; little or no mortgage lending today, so you'd be pitching a new business line
A9: 5 | B9: Bank | C9: ='Banks'!B34 | D9: ='Banks'!C34 | E9: ='Banks'!D34 | F9: ='Banks'!F34 | G9: ='Banks'!J34 | H9: ='Banks'!K34 | I9: ='Banks'!L34 | J9: =IF('Banks'!T34="","n/a",'Banks'!T34) | K9: ='Banks'!X34 | L9: ='Banks'!Y34 | M9: ='Banks'!Z34 | N9: CRE at 347% of capital (above the 300% regulatory guide) so resi would diversify; deposits outgrowing loans; strong capital (17.8%); little or no mortgage lending today, so you'd be pitching a new business line
A10: 6 | B10: Bank | C10: ='Banks'!B24 | D10: ='Banks'!C24 | E10: ='Banks'!D24 | F10: ='Banks'!F24 | G10: ='Banks'!J24 | H10: ='Banks'!K24 | I10: ='Banks'!L24 | J10: =IF('Banks'!T24="","n/a",'Banks'!T24) | K10: ='Banks'!X24 | L10: ='Banks'!Y24 | M10: ='Banks'!Z24 | N10: Strong capital (15.9%); little or no mortgage lending today, so you'd be pitching a new business line
A11: 7 | B11: Credit Union | C11: ='Credit Unions'!B19 | D11: ='Credit Unions'!C19 | E11: ='Credit Unions'!D19 | F11: ='Credit Unions'!E19 | G11: ='Credit Unions'!I19 | H11: ='Credit Unions'!J19 | I11: ='Credit Unions'!K19 | J11: =IF('Credit Unions'!U19="","n/a",'Credit Unions'!U19) | K11: ='Credit Unions'!Y19 | L11: ='Credit Unions'!Z19 | M11: ='Credit Unions'!AA19 | N11: Lends out only 56% of deposits; 45% of assets in cash/securities; keeps 100% of its mortgages (portfolio lender)
A12: 8 | B12: Bank | C12: ='Banks'!B27 | D12: ='Banks'!C27 | E12: ='Banks'!D27 | F12: ='Banks'!F27 | G12: ='Banks'!J27 | H12: ='Banks'!K27 | I12: ='Banks'!L27 | J12: =IF('Banks'!T27="","n/a",'Banks'!T27) | K12: ='Banks'!X27 | L12: ='Banks'!Y27 | M12: ='Banks'!Z27 | N12: Lends out only 60% of deposits; 50% of assets in cash/securities; strong capital (12.5%); little or no mortgage lending today, so you'd be pitching a new business line
A13: 9 | B13: Credit Union | C13: ='Credit Unions'!B15 | D13: ='Credit Unions'!C15 | E13: ='Credit Unions'!D15 | F13: ='Credit Unions'!E15 | G13: ='Credit Unions'!I15 | H13: ='Credit Unions'!J15 | I13: ='Credit Unions'!K15 | J13: =IF('Credit Unions'!U15="","n/a",'Credit Unions'!U15) | K13: ='Credit Unions'!Y15 | L13: ='Credit Unions'!Z15 | M13: ='Credit Unions'!AA15 | N13: Lends out only 62% of deposits; 42% of assets in cash/securities; strong capital (13.1%); keeps 93% of its mortgages (portfolio lender)
A14: 10 | B14: Credit Union | C14: ='Credit Unions'!B21 | D14: ='Credit Unions'!C21 | E14: ='Credit Unions'!D21 | F14: ='Credit Unions'!E21 | G14: ='Credit Unions'!I21 | H14: ='Credit Unions'!J21 | I14: ='Credit Unions'!K21 | J14: =IF('Credit Unions'!U21="","n/a",'Credit Unions'!U21) | K14: ='Credit Unions'!Y21 | L14: ='Credit Unions'!Z21 | M14: ='Credit Unions'!AA21 | N14: Lends out only 61% of deposits; 42% of assets in cash/securities; keeps 93% of its mortgages (portfolio lender)
A15: 11 | B15: Credit Union | C15: ='Credit Unions'!B35 | D15: ='Credit Unions'!C35 | E15: ='Credit Unions'!D35 | F15: ='Credit Unions'!E35 | G15: ='Credit Unions'!I35 | H15: ='Credit Unions'!J35 | I15: ='Credit Unions'!K35 | J15: =IF('Credit Unions'!U35="","n/a",'Credit Unions'!U35) | K15: ='Credit Unions'!Y35 | L15: ='Credit Unions'!Z35 | M15: ='Credit Unions'!AA35 | N15: Lends out only 55% of deposits; 34% of assets in cash/securities; keeps 100% of its mortgages (portfolio lender)
A16: 12 | B16: Bank | C16: ='Banks'!B16 | D16: ='Banks'!C16 | E16: ='Banks'!D16 | F16: ='Banks'!F16 | G16: ='Banks'!J16 | H16: ='Banks'!K16 | I16: ='Banks'!L16 | J16: =IF('Banks'!T16="","n/a",'Banks'!T16) | K16: ='Banks'!X16 | L16: ='Banks'!Y16 | M16: ='Banks'!Z16 | N16: Lends out only 74% of deposits; 33% of assets in cash/securities; deposits outgrowing loans; little or no mortgage lending today, so you'd be pitching a new business line
A17: 13 | B17: Credit Union | C17: ='Credit Unions'!B9 | D17: ='Credit Unions'!C9 | E17: ='Credit Unions'!D9 | F17: ='Credit Unions'!E9 | G17: ='Credit Unions'!I9 | H17: ='Credit Unions'!J9 | I17: ='Credit Unions'!K9 | J17: =IF('Credit Unions'!U9="","n/a",'Credit Unions'!U9) | K17: ='Credit Unions'!Y9 | L17: ='Credit Unions'!Z9 | M17: ='Credit Unions'!AA9 | N17: Lends out only 60% of deposits; 58% of assets in cash/securities; strong capital (12.6%); keeps 100% of its mortgages (portfolio lender); already made 8 IO/balloon/non-amortizing loans
A18: 14 | B18: Credit Union | C18: ='Credit Unions'!B45 | D18: ='Credit Unions'!C45 | E18: ='Credit Unions'!D45 | F18: ='Credit Unions'!E45 | G18: ='Credit Unions'!I45 | H18: ='Credit Unions'!J45 | I18: ='Credit Unions'!K45 | J18: =IF('Credit Unions'!U45="","n/a",'Credit Unions'!U45) | K18: ='Credit Unions'!Y45 | L18: ='Credit Unions'!Z45 | M18: ='Credit Unions'!AA45 | N18: Lends out only 57% of deposits; 45% of assets in cash/securities; strong capital (13.1%); little or no mortgage lending today, so you'd be pitching a new business line
A19: 15 | B19: Bank | C19: ='Banks'!B5 | D19: ='Banks'!C5 | E19: ='Banks'!D5 | F19: ='Banks'!F5 | G19: ='Banks'!J5 | H19: ='Banks'!K5 | I19: ='Banks'!L5 | J19: =IF('Banks'!T5="","n/a",'Banks'!T5) | K19: ='Banks'!X5 | L19: ='Banks'!Y5 | M19: ='Banks'!Z5 | N19: Deposits outgrowing loans; strong capital (14.7%); keeps 100% of its mortgages (portfolio lender); already made 2 IO/balloon/non-amortizing loans
A20: 16 | B20: Credit Union | C20: ='Credit Unions'!B42 | D20: ='Credit Unions'!C42 | E20: ='Credit Unions'!D42 | F20: ='Credit Unions'!E42 | G20: ='Credit Unions'!I42 | H20: ='Credit Unions'!J42 | I20: ='Credit Unions'!K42 | J20: =IF('Credit Unions'!U42="","n/a",'Credit Unions'!U42) | K20: ='Credit Unions'!Y42 | L20: ='Credit Unions'!Z42 | M20: ='Credit Unions'!AA42 | N20: Lends out only 69% of deposits; 36% of assets in cash/securities; keeps 100% of its mortgages (portfolio lender)
A21: 17 | B21: Bank | C21: ='Banks'!B11 | D21: ='Banks'!C11 | E21: ='Banks'!D11 | F21: ='Banks'!F11 | G21: ='Banks'!J11 | H21: ='Banks'!K11 | I21: ='Banks'!L11 | J21: =IF('Banks'!T11="","n/a",'Banks'!T11) | K21: ='Banks'!X11 | L21: ='Banks'!Y11 | M21: ='Banks'!Z11 | N21: Strong capital (13.9%); little or no mortgage lending today, so you'd be pitching a new business line
A22: 18 | B22: Bank | C22: ='Banks'!B20 | D22: ='Banks'!C20 | E22: ='Banks'!D20 | F22: ='Banks'!F20 | G22: ='Banks'!J20 | H22: ='Banks'!K20 | I22: ='Banks'!L20 | J22: =IF('Banks'!T20="","n/a",'Banks'!T20) | K22: ='Banks'!X20 | L22: ='Banks'!Y20 | M22: ='Banks'!Z20 | N22: CRE at 611% of capital (above the 300% regulatory guide) so resi would diversify; little or no mortgage lending today, so you'd be pitching a new business line
A23: 19 | B23: Credit Union | C23: ='Credit Unions'!B46 | D23: ='Credit Unions'!C46 | E23: ='Credit Unions'!D46 | F23: ='Credit Unions'!E46 | G23: ='Credit Unions'!I46 | H23: ='Credit Unions'!J46 | I23: ='Credit Unions'!K46 | J23: =IF('Credit Unions'!U46="","n/a",'Credit Unions'!U46) | K23: ='Credit Unions'!Y46 | L23: ='Credit Unions'!Z46 | M23: ='Credit Unions'!AA46 | N23: Lends out only 65% of deposits; 39% of assets in cash/securities; deposits outgrowing loans
A24: 20 | B24: Credit Union | C24: ='Credit Unions'!B6 | D24: ='Credit Unions'!C6 | E24: ='Credit Unions'!D6 | F24: ='Credit Unions'!E6 | G24: ='Credit Unions'!I6 | H24: ='Credit Unions'!J6 | I24: ='Credit Unions'!K6 | J24: =IF('Credit Unions'!U6="","n/a",'Credit Unions'!U6) | K24: ='Credit Unions'!Y6 | L24: ='Credit Unions'!Z6 | M24: ='Credit Unions'!AA6 | N24: Lends out only 70% of deposits; 43% of assets in cash/securities; keeps 100% of its mortgages (portfolio lender); already made 97 IO/balloon/non-amortizing loans
A25: 21 | B25: Credit Union | C25: ='Credit Unions'!B30 | D25: ='Credit Unions'!C30 | E25: ='Credit Unions'!D30 | F25: ='Credit Unions'!E30 | G25: ='Credit Unions'!I30 | H25: ='Credit Unions'!J30 | I25: ='Credit Unions'!K30 | J25: =IF('Credit Unions'!U30="","n/a",'Credit Unions'!U30) | K25: ='Credit Unions'!Y30 | L25: ='Credit Unions'!Z30 | M25: ='Credit Unions'!AA30 | N25: Lends out only 57% of deposits; 45% of assets in cash/securities; strong capital (13.5%); keeps 100% of its mortgages (portfolio lender)
A26: 22 | B26: Credit Union | C26: ='Credit Unions'!B63 | D26: ='Credit Unions'!C63 | E26: ='Credit Unions'!D63 | F26: ='Credit Unions'!E63 | G26: ='Credit Unions'!I63 | H26: ='Credit Unions'!J63 | I26: ='Credit Unions'!K63 | J26: =IF('Credit Unions'!U63="","n/a",'Credit Unions'!U63) | K26: ='Credit Unions'!Y63 | L26: ='Credit Unions'!Z63 | M26: ='Credit Unions'!AA63 | N26: Lends out only 50% of deposits; 53% of assets in cash/securities; deposits outgrowing loans; strong capital (23.4%); little or no mortgage lending today, so you'd be pitching a new business line
A27: 23 | B27: Credit Union | C27: ='Credit Unions'!B52 | D27: ='Credit Unions'!C52 | E27: ='Credit Unions'!D52 | F27: ='Credit Unions'!E52 | G27: ='Credit Unions'!I52 | H27: ='Credit Unions'!J52 | I27: ='Credit Unions'!K52 | J27: =IF('Credit Unions'!U52="","n/a",'Credit Unions'!U52) | K27: ='Credit Unions'!Y52 | L27: ='Credit Unions'!Z52 | M27: ='Credit Unions'!AA52 | N27: Lends out only 54% of deposits; 48% of assets in cash/securities; strong capital (14.0%); already made 1 IO/balloon/non-amortizing loans
A28: 24 | B28: Credit Union | C28: ='Credit Unions'!B59 | D28: ='Credit Unions'!C59 | E28: ='Credit Unions'!D59 | F28: ='Credit Unions'!E59 | G28: ='Credit Unions'!I59 | H28: ='Credit Unions'!J59 | I28: ='Credit Unions'!K59 | J28: =IF('Credit Unions'!U59="","n/a",'Credit Unions'!U59) | K28: ='Credit Unions'!Y59 | L28: ='Credit Unions'!Z59 | M28: ='Credit Unions'!AA59 | N28: Lends out only 46% of deposits; 52% of assets in cash/securities; little or no mortgage lending today, so you'd be pitching a new business line
A29: 25 | B29: Credit Union | C29: ='Credit Unions'!B11 | D29: ='Credit Unions'!C11 | E29: ='Credit Unions'!D11 | F29: ='Credit Unions'!E11 | G29: ='Credit Unions'!I11 | H29: ='Credit Unions'!J11 | I29: ='Credit Unions'!K11 | J29: =IF('Credit Unions'!U11="","n/a",'Credit Unions'!U11) | K29: ='Credit Unions'!Y11 | L29: ='Credit Unions'!Z11 | M29: ='Credit Unions'!AA11 | N29: Lends out only 60% of deposits; 46% of assets in cash/securities; deposits outgrowing loans; already made 1 IO/balloon/non-amortizing loans
A30: 26 | B30: Credit Union | C30: ='Credit Unions'!B54 | D30: ='Credit Unions'!C54 | E30: ='Credit Unions'!D54 | F30: ='Credit Unions'!E54 | G30: ='Credit Unions'!I54 | H30: ='Credit Unions'!J54 | I30: ='Credit Unions'!K54 | J30: =IF('Credit Unions'!U54="","n/a",'Credit Unions'!U54) | K30: ='Credit Unions'!Y54 | L30: ='Credit Unions'!Z54 | M30: ='Credit Unions'!AA54 | N30: Lends out only 55% of deposits; 49% of assets in cash/securities; little or no mortgage lending today, so you'd be pitching a new business line
A31: 27 | B31: Credit Union | C31: ='Credit Unions'!B62 | D31: ='Credit Unions'!C62 | E31: ='Credit Unions'!D62 | F31: ='Credit Unions'!E62 | G31: ='Credit Unions'!I62 | H31: ='Credit Unions'!J62 | I31: ='Credit Unions'!K62 | J31: =IF('Credit Unions'!U62="","n/a",'Credit Unions'!U62) | K31: ='Credit Unions'!Y62 | L31: ='Credit Unions'!Z62 | M31: ='Credit Unions'!AA62 | N31: Lends out only 51% of deposits; 41% of assets in cash/securities; little or no mortgage lending today, so you'd be pitching a new business line
A32: 28 | B32: Bank | C32: ='Banks'!B45 | D32: ='Banks'!C45 | E32: ='Banks'!D45 | F32: ='Banks'!F45 | G32: ='Banks'!J45 | H32: ='Banks'!K45 | I32: ='Banks'!L45 | J32: =IF('Banks'!T45="","n/a",'Banks'!T45) | K32: ='Banks'!X45 | L32: ='Banks'!Y45 | M32: ='Banks'!Z45 | N32: Lends out only 79% of deposits; deposits outgrowing loans; strong capital (13.5%); little or no mortgage lending today, so you'd be pitching a new business line
A33: 29 | B33: Credit Union | C33: ='Credit Unions'!B58 | D33: ='Credit Unions'!C58 | E33: ='Credit Unions'!D58 | F33: ='Credit Unions'!E58 | G33: ='Credit Unions'!I58 | H33: ='Credit Unions'!J58 | I33: ='Credit Unions'!K58 | J33: =IF('Credit Unions'!U58="","n/a",'Credit Unions'!U58) | K33: ='Credit Unions'!Y58 | L33: ='Credit Unions'!Z58 | M33: ='Credit Unions'!AA58 | N33: 31% of assets in cash/securities; strong capital (23.4%); little or no mortgage lending today, so you'd be pitching a new business line
A34: 30 | B34: Credit Union | C34: ='Credit Unions'!B49 | D34: ='Credit Unions'!C49 | E34: ='Credit Unions'!D49 | F34: ='Credit Unions'!E49 | G34: ='Credit Unions'!I49 | H34: ='Credit Unions'!J49 | I34: ='Credit Unions'!K49 | J34: =IF('Credit Unions'!U49="","n/a",'Credit Unions'!U49) | K34: ='Credit Unions'!Y49 | L34: ='Credit Unions'!Z49 | M34: ='Credit Unions'!AA49 | N34: Lends out only 59% of deposits; 44% of assets in cash/securities; little or no mortgage lending today, so you'd be pitching a new business line
A35: 31 | B35: Credit Union | C35: ='Credit Unions'!B61 | D35: ='Credit Unions'!C61 | E35: ='Credit Unions'!D61 | F35: ='Credit Unions'!E61 | G35: ='Credit Unions'!I61 | H35: ='Credit Unions'!J61 | I35: ='Credit Unions'!K61 | J35: =IF('Credit Unions'!U61="","n/a",'Credit Unions'!U61) | K35: ='Credit Unions'!Y61 | L35: ='Credit Unions'!Z61 | M35: ='Credit Unions'!AA61 | N35: Lends out only 61% of deposits; 43% of assets in cash/securities; little or no mortgage lending today, so you'd be pitching a new business line
A36: 32 | B36: Credit Union | C36: ='Credit Unions'!B57 | D36: ='Credit Unions'!C57 | E36: ='Credit Unions'!D57 | F36: ='Credit Unions'!E57 | G36: ='Credit Unions'!I57 | H36: ='Credit Unions'!J57 | I36: ='Credit Unions'!K57 | J36: =IF('Credit Unions'!U57="","n/a",'Credit Unions'!U57) | K36: ='Credit Unions'!Y57 | L36: ='Credit Unions'!Z57 | M36: ='Credit Unions'!AA57 | N36: Lends out only 59% of deposits; 46% of assets in cash/securities; strong capital (13.8%); little or no mortgage lending today, so you'd be pitching a new business line
A37: 33 | B37: Bank | C37: ='Banks'!B42 | D37: ='Banks'!C42 | E37: ='Banks'!D42 | F37: ='Banks'!F42 | G37: ='Banks'!J42 | H37: ='Banks'!K42 | I37: ='Banks'!L42 | J37: =IF('Banks'!T42="","n/a",'Banks'!T42) | K37: ='Banks'!X42 | L37: ='Banks'!Y42 | M37: ='Banks'!Z42 | N37: Lends out only 69% of deposits; 41% of assets in cash/securities; strong capital (16.4%)
A38: 34 | B38: Credit Union | C38: ='Credit Unions'!B48 | D38: ='Credit Unions'!C48 | E38: ='Credit Unions'!D48 | F38: ='Credit Unions'!E48 | G38: ='Credit Unions'!I48 | H38: ='Credit Unions'!J48 | I38: ='Credit Unions'!K48 | J38: =IF('Credit Unions'!U48="","n/a",'Credit Unions'!U48) | K38: ='Credit Unions'!Y48 | L38: ='Credit Unions'!Z48 | M38: ='Credit Unions'!AA48 | N38: Lends out only 52% of deposits; 45% of assets in cash/securities; strong capital (13.9%)
A39: 35 | B39: Credit Union | C39: ='Credit Unions'!B65 | D39: ='Credit Unions'!C65 | E39: ='Credit Unions'!D65 | F39: ='Credit Unions'!E65 | G39: ='Credit Unions'!I65 | H39: ='Credit Unions'!J65 | I39: ='Credit Unions'!K65 | J39: =IF('Credit Unions'!U65="","n/a",'Credit Unions'!U65) | K39: ='Credit Unions'!Y65 | L39: ='Credit Unions'!Z65 | M39: ='Credit Unions'!AA65 | N39: Lends out only 71% of deposits; 34% of assets in cash/securities; strong capital (13.5%); little or no mortgage lending today, so you'd be pitching a new business line
A40: 36 | B40: Bank | C40: ='Banks'!B46 | D40: ='Banks'!C46 | E40: ='Banks'!D46 | F40: ='Banks'!F46 | G40: ='Banks'!J46 | H40: ='Banks'!K46 | I40: ='Banks'!L46 | J40: =IF('Banks'!T46="","n/a",'Banks'!T46) | K40: ='Banks'!X46 | L40: ='Banks'!Y46 | M40: ='Banks'!Z46 | N40: Lends out only 76% of deposits; deposits outgrowing loans; little or no mortgage lending today, so you'd be pitching a new business line
A41: 37 | B41: Bank | C41: ='Banks'!B6 | D41: ='Banks'!C6 | E41: ='Banks'!D6 | F41: ='Banks'!F6 | G41: ='Banks'!J6 | H41: ='Banks'!K6 | I41: ='Banks'!L6 | J41: =IF('Banks'!T6="","n/a",'Banks'!T6) | K41: ='Banks'!X6 | L41: ='Banks'!Y6 | M41: ='Banks'!Z6 | N41: Lends out only 79% of deposits; little or no mortgage lending today, so you'd be pitching a new business line
A42: 38 | B42: Bank | C42: ='Banks'!B31 | D42: ='Banks'!C31 | E42: ='Banks'!D31 | F42: ='Banks'!F31 | G42: ='Banks'!J31 | H42: ='Banks'!K31 | I42: ='Banks'!L31 | J42: =IF('Banks'!T31="","n/a",'Banks'!T31) | K42: ='Banks'!X31 | L42: ='Banks'!Y31 | M42: ='Banks'!Z31 | N42: CRE at 407% of capital (above the 300% regulatory guide) so resi would diversify; deposits outgrowing loans; strong capital (13.4%); little or no mortgage lending today, so you'd be pitching a new business line
A43: 39 | B43: Bank | C43: ='Banks'!B35 | D43: ='Banks'!C35 | E43: ='Banks'!D35 | F43: ='Banks'!F35 | G43: ='Banks'!J35 | H43: ='Banks'!K35 | I43: ='Banks'!L35 | J43: =IF('Banks'!T35="","n/a",'Banks'!T35) | K43: ='Banks'!X35 | L43: ='Banks'!Y35 | M43: ='Banks'!Z35 | N43: Deposits outgrowing loans; strong capital (16.2%); keeps 100% of its mortgages (portfolio lender)
A44: 40 | B44: Bank | C44: ='Banks'!B43 | D44: ='Banks'!C43 | E44: ='Banks'!D43 | F44: ='Banks'!F43 | G44: ='Banks'!J43 | H44: ='Banks'!K43 | I44: ='Banks'!L43 | J44: =IF('Banks'!T43="","n/a",'Banks'!T43) | K44: ='Banks'!X43 | L44: ='Banks'!Y43 | M44: ='Banks'!Z43 | N44: Deposits outgrowing loans; strong capital (14.5%); little or no mortgage lending today, so you'd be pitching a new business line
A45: 41 | B45: Bank | C45: ='Banks'!B18 | D45: ='Banks'!C18 | E45: ='Banks'!D18 | F45: ='Banks'!F18 | G45: ='Banks'!J18 | H45: ='Banks'!K18 | I45: ='Banks'!L18 | J45: =IF('Banks'!T18="","n/a",'Banks'!T18) | K45: ='Banks'!X18 | L45: ='Banks'!Y18 | M45: ='Banks'!Z18 | N45: Deposits outgrowing loans; strong capital (21.7%); little or no mortgage lending today, so you'd be pitching a new business line
A46: 42 | B46: Credit Union | C46: ='Credit Unions'!B18 | D46: ='Credit Unions'!C18 | E46: ='Credit Unions'!D18 | F46: ='Credit Unions'!E18 | G46: ='Credit Unions'!I18 | H46: ='Credit Unions'!J18 | I46: ='Credit Unions'!K18 | J46: =IF('Credit Unions'!U18="","n/a",'Credit Unions'!U18) | K46: ='Credit Unions'!Y18 | L46: ='Credit Unions'!Z18 | M46: ='Credit Unions'!AA18 | N46: Lends out only 45% of deposits; 65% of assets in cash/securities; keeps 100% of its mortgages (portfolio lender)
A47: 43 | B47: Credit Union | C47: ='Credit Unions'!B20 | D47: ='Credit Unions'!C20 | E47: ='Credit Unions'!D20 | F47: ='Credit Unions'!E20 | G47: ='Credit Unions'!I20 | H47: ='Credit Unions'!J20 | I47: ='Credit Unions'!K20 | J47: =IF('Credit Unions'!U20="","n/a",'Credit Unions'!U20) | K47: ='Credit Unions'!Y20 | L47: ='Credit Unions'!Z20 | M47: ='Credit Unions'!AA20 | N47: Deposits outgrowing loans; strong capital (12.8%); little or no mortgage lending today, so you'd be pitching a new business line
A48: 44 | B48: Credit Union | C48: ='Credit Unions'!B66 | D48: ='Credit Unions'!C66 | E48: ='Credit Unions'!D66 | F48: ='Credit Unions'!E66 | G48: ='Credit Unions'!I66 | H48: ='Credit Unions'!J66 | I48: ='Credit Unions'!K66 | J48: =IF('Credit Unions'!U66="","n/a",'Credit Unions'!U66) | K48: ='Credit Unions'!Y66 | L48: ='Credit Unions'!Z66 | M48: ='Credit Unions'!AA66 | N48: Lends out only 61% of deposits; 42% of assets in cash/securities; little or no mortgage lending today, so you'd be pitching a new business line
A49: 45 | B49: Bank | C49: ='Banks'!B33 | D49: ='Banks'!C33 | E49: ='Banks'!D33 | F49: ='Banks'!F33 | G49: ='Banks'!J33 | H49: ='Banks'!K33 | I49: ='Banks'!L33 | J49: =IF('Banks'!T33="","n/a",'Banks'!T33) | K49: ='Banks'!X33 | L49: ='Banks'!Y33 | M49: ='Banks'!Z33 | N49: CRE at 480% of capital (above the 300% regulatory guide) so resi would diversify; deposits outgrowing loans; strong capital (14.4%); little or no mortgage lending today, so you'd be pitching a new business line
A50: 46 | B50: Bank | C50: ='Banks'!B37 | D50: ='Banks'!C37 | E50: ='Banks'!D37 | F50: ='Banks'!F37 | G50: ='Banks'!J37 | H50: ='Banks'!K37 | I50: ='Banks'!L37 | J50: =IF('Banks'!T37="","n/a",'Banks'!T37) | K50: ='Banks'!X37 | L50: ='Banks'!Y37 | M50: ='Banks'!Z37 | N50: CRE at 442% of capital (above the 300% regulatory guide) so resi would diversify; little or no mortgage lending today, so you'd be pitching a new business line
A51: 47 | B51: Bank | C51: ='Banks'!B39 | D51: ='Banks'!C39 | E51: ='Banks'!D39 | F51: ='Banks'!F39 | G51: ='Banks'!J39 | H51: ='Banks'!K39 | I51: ='Banks'!L39 | J51: =IF('Banks'!T39="","n/a",'Banks'!T39) | K51: ='Banks'!X39 | L51: ='Banks'!Y39 | M51: ='Banks'!Z39 | N51: CRE at 375% of capital (above the 300% regulatory guide) so resi would diversify; strong capital (17.4%); little or no mortgage lending today, so you'd be pitching a new business line
A52: 48 | B52: Credit Union | C52: ='Credit Unions'!B38 | D52: ='Credit Unions'!C38 | E52: ='Credit Unions'!D38 | F52: ='Credit Unions'!E38 | G52: ='Credit Unions'!I38 | H52: ='Credit Unions'!J38 | I52: ='Credit Unions'!K38 | J52: =IF('Credit Unions'!U38="","n/a",'Credit Unions'!U38) | K52: ='Credit Unions'!Y38 | L52: ='Credit Unions'!Z38 | M52: ='Credit Unions'!AA38 | N52: Lends out only 57% of deposits; 42% of assets in cash/securities
A53: 49 | B53: Credit Union | C53: ='Credit Unions'!B37 | D53: ='Credit Unions'!C37 | E53: ='Credit Unions'!D37 | F53: ='Credit Unions'!E37 | G53: ='Credit Unions'!I37 | H53: ='Credit Unions'!J37 | I53: ='Credit Unions'!K37 | J53: =IF('Credit Unions'!U37="","n/a",'Credit Unions'!U37) | K53: ='Credit Unions'!Y37 | L53: ='Credit Unions'!Z37 | M53: ='Credit Unions'!AA37 | N53: Lends out only 74% of deposits; keeps 100% of its mortgages (portfolio lender); already made 1 IO/balloon/non-amortizing loans
A54: 50 | B54: Bank | C54: ='Banks'!B36 | D54: ='Banks'!C36 | E54: ='Banks'!D36 | F54: ='Banks'!F36 | G54: ='Banks'!J36 | H54: ='Banks'!K36 | I54: ='Banks'!L36 | J54: =IF('Banks'!T36="","n/a",'Banks'!T36) | K54: ='Banks'!X36 | L54: ='Banks'!Y36 | M54: ='Banks'!Z36 | N54: Strong capital (13.0%); little or no mortgage lending today, so you'd be pitching a new business line
A55: 51 | B55: Credit Union | C55: ='Credit Unions'!B26 | D55: ='Credit Unions'!C26 | E55: ='Credit Unions'!D26 | F55: ='Credit Unions'!E26 | G55: ='Credit Unions'!I26 | H55: ='Credit Unions'!J26 | I55: ='Credit Unions'!K26 | J55: =IF('Credit Unions'!U26="","n/a",'Credit Unions'!U26) | K55: ='Credit Unions'!Y26 | L55: ='Credit Unions'!Z26 | M55: ='Credit Unions'!AA26 | N55: Lends out only 79% of deposits; keeps 100% of its mortgages (portfolio lender)
A56: 52 | B56: Credit Union | C56: ='Credit Unions'!B31 | D56: ='Credit Unions'!C31 | E56: ='Credit Unions'!D31 | F56: ='Credit Unions'!E31 | G56: ='Credit Unions'!I31 | H56: ='Credit Unions'!J31 | I56: ='Credit Unions'!K31 | J56: =IF('Credit Unions'!U31="","n/a",'Credit Unions'!U31) | K56: ='Credit Unions'!Y31 | L56: ='Credit Unions'!Z31 | M56: ='Credit Unions'!AA31 | N56: 34% of assets in cash/securities; strong capital (20.7%); keeps 100% of its mortgages (portfolio lender)
A57: 53 | B57: Credit Union | C57: ='Credit Unions'!B47 | D57: ='Credit Unions'!C47 | E57: ='Credit Unions'!D47 | F57: ='Credit Unions'!E47 | G57: ='Credit Unions'!I47 | H57: ='Credit Unions'!J47 | I57: ='Credit Unions'!K47 | J57: =IF('Credit Unions'!U47="","n/a",'Credit Unions'!U47) | K57: ='Credit Unions'!Y47 | L57: ='Credit Unions'!Z47 | M57: ='Credit Unions'!AA47 | N57: Lends out only 57% of deposits; 45% of assets in cash/securities
A58: 54 | B58: Credit Union | C58: ='Credit Unions'!B64 | D58: ='Credit Unions'!C64 | E58: ='Credit Unions'!D64 | F58: ='Credit Unions'!E64 | G58: ='Credit Unions'!I64 | H58: ='Credit Unions'!J64 | I58: ='Credit Unions'!K64 | J58: =IF('Credit Unions'!U64="","n/a",'Credit Unions'!U64) | K58: ='Credit Unions'!Y64 | L58: ='Credit Unions'!Z64 | M58: ='Credit Unions'!AA64 | N58: Lends out only 67% of deposits; little or no mortgage lending today, so you'd be pitching a new business line
A59: 55 | B59: Bank | C59: ='Banks'!B44 | D59: ='Banks'!C44 | E59: ='Banks'!D44 | F59: ='Banks'!F44 | G59: ='Banks'!J44 | H59: ='Banks'!K44 | I59: ='Banks'!L44 | J59: =IF('Banks'!T44="","n/a",'Banks'!T44) | K59: ='Banks'!X44 | L59: ='Banks'!Y44 | M59: ='Banks'!Z44 | N59: CRE at 365% of capital (above the 300% regulatory guide) so resi would diversify; strong capital (18.3%); little or no mortgage lending today, so you'd be pitching a new business line
A60: 56 | B60: Bank | C60: ='Banks'!B29 | D60: ='Banks'!C29 | E60: ='Banks'!D29 | F60: ='Banks'!F29 | G60: ='Banks'!J29 | H60: ='Banks'!K29 | I60: ='Banks'!L29 | J60: =IF('Banks'!T29="","n/a",'Banks'!T29) | K60: ='Banks'!X29 | L60: ='Banks'!Y29 | M60: ='Banks'!Z29 | N60: Little or no mortgage lending today, so you'd be pitching a new business line
A61: 57 | B61: Credit Union | C61: ='Credit Unions'!B53 | D61: ='Credit Unions'!C53 | E61: ='Credit Unions'!D53 | F61: ='Credit Unions'!E53 | G61: ='Credit Unions'!I53 | H61: ='Credit Unions'!J53 | I61: ='Credit Unions'!K53 | J61: =IF('Credit Unions'!U53="","n/a",'Credit Unions'!U53) | K61: ='Credit Unions'!Y53 | L61: ='Credit Unions'!Z53 | M61: ='Credit Unions'!AA53 | N61: 33% of assets in cash/securities; strong capital (29.4%); little or no mortgage lending today, so you'd be pitching a new business line
A62: 58 | B62: Bank | C62: ='Banks'!B2 | D62: ='Banks'!C2 | E62: ='Banks'!D2 | F62: ='Banks'!F2 | G62: ='Banks'!J2 | H62: ='Banks'!K2 | I62: ='Banks'!L2 | J62: =IF('Banks'!T2="","n/a",'Banks'!T2) | K62: ='Banks'!X2 | L62: ='Banks'!Y2 | M62: ='Banks'!Z2 | N62: CRE at 315% of capital (above the 300% regulatory guide) so resi would diversify; keeps 95% of its mortgages (portfolio lender)
A63: 59 | B63: Credit Union | C63: ='Credit Unions'!B13 | D63: ='Credit Unions'!C13 | E63: ='Credit Unions'!D13 | F63: ='Credit Unions'!E13 | G63: ='Credit Unions'!I13 | H63: ='Credit Unions'!J13 | I63: ='Credit Unions'!K13 | J63: =IF('Credit Unions'!U13="","n/a",'Credit Unions'!U13) | K63: ='Credit Unions'!Y13 | L63: ='Credit Unions'!Z13 | M63: ='Credit Unions'!AA13 | N63: Lends out only 75% of deposits; keeps 100% of its mortgages (portfolio lender); already made 3 IO/balloon/non-amortizing loans
A64: 60 | B64: Bank | C64: ='Banks'!B14 | D64: ='Banks'!C14 | E64: ='Banks'!D14 | F64: ='Banks'!F14 | G64: ='Banks'!J14 | H64: ='Banks'!K14 | I64: ='Banks'!L14 | J64: =IF('Banks'!T14="","n/a",'Banks'!T14) | K64: ='Banks'!X14 | L64: ='Banks'!Y14 | M64: ='Banks'!Z14 | N64: Strong capital (14.0%); little or no mortgage lending today, so you'd be pitching a new business line
A65: 61 | B65: Bank | C65: ='Banks'!B38 | D65: ='Banks'!C38 | E65: ='Banks'!D38 | F65: ='Banks'!F38 | G65: ='Banks'!J38 | H65: ='Banks'!K38 | I65: ='Banks'!L38 | J65: =IF('Banks'!T38="","n/a",'Banks'!T38) | K65: ='Banks'!X38 | L65: ='Banks'!Y38 | M65: ='Banks'!Z38 | N65: Deposits outgrowing loans; strong capital (22.8%); little or no mortgage lending today, so you'd be pitching a new business line
A66: 62 | B66: Credit Union | C66: ='Credit Unions'!B33 | D66: ='Credit Unions'!C33 | E66: ='Credit Unions'!D33 | F66: ='Credit Unions'!E33 | G66: ='Credit Unions'!I33 | H66: ='Credit Unions'!J33 | I66: ='Credit Unions'!K33 | J66: =IF('Credit Unions'!U33="","n/a",'Credit Unions'!U33) | K66: ='Credit Unions'!Y33 | L66: ='Credit Unions'!Z33 | M66: ='Credit Unions'!AA33 | N66: Little or no mortgage lending today, so you'd be pitching a new business line
A67: 63 | B67: Credit Union | C67: ='Credit Unions'!B51 | D67: ='Credit Unions'!C51 | E67: ='Credit Unions'!D51 | F67: ='Credit Unions'!E51 | G67: ='Credit Unions'!I51 | H67: ='Credit Unions'!J51 | I67: ='Credit Unions'!K51 | J67: =IF('Credit Unions'!U51="","n/a",'Credit Unions'!U51) | K67: ='Credit Unions'!Y51 | L67: ='Credit Unions'!Z51 | M67: ='Credit Unions'!AA51 | N67: Lends out only 69% of deposits; already made 21 IO/balloon/non-amortizing loans

Sheet Read Me
A1: How to use this workbook
A2: Top Targets: the short list. Tier 1 = strongest balance-sheet capacity and NOT already taking broker loans. Start there.
A3: Banks / Credit Unions: full detail on every institution in scope. Filter by County, Tier or Wholesale status. Fill in the yellow CEO / contact and Notes columns as you research.
A4: Scoring: the weights behind the capacity score. Change the blue numbers to re-rank everything.
A6: What the columns mean
A7: Loan-to-deposit (banks) / Loan-to-share (CUs): total loans divided by deposits. Under ~80% means deposits are sitting idle and earning less than a loan would.
A8: Liquidity: cash plus investment securities as a share of assets. A high number = money available to redeploy into loans.
A9: Capital ratio: Tier 1 leverage ratio (banks) or net worth ratio (CUs). 10%+ is comfortable; portfolio non-QM uses capital, so they need room.
A10: CRE concentration: non-owner-occupied CRE + multifamily + construction loans divided by total risk-based capital. Regulators scrutinize banks above 300%; 1-4 family loans help them diversify.
A11: % kept in portfolio: share of 2025 HMDA originations NOT sold the same year. High = they already hold mortgages on their books, which non-QM requires (or they sell to a non-QM investor).
A12: Non-QM-feature loans: 2025 originations with interest-only, balloon, negative-amortization or other non-amortizing terms. These loans cannot be QM, so a count above zero means they already do some non-QM.
A13: Broker-channel share: share of 2025 applications NOT submitted directly to the institution (HMDA "submission of application" = 2). This is the best public signal of an existing wholesale/broker channel.
... A83: Los Angeles Lee CU (Credit Union, $1M): Under $100M in assets (too small to fund a wholesale channel)

Sheet Scoring
A1: Capacity score settings (edit the blue numbers; every score recalculates)
A3: Bank weights | C3: Total | D3: =SUM(B4:B9)
A4: Low loan-to-deposit ratio | B4: 0.3
A5: High liquidity (cash + securities / assets) | B5: 0.2
A6: Strong capital (leverage ratio) | B6: 0.15
A7: Deposits growing faster than loans | B7: 0.1
A8: High CRE concentration (needs to diversify) | B8: 0.15
A9: Low 1-4 family share of loans (room to add) | B9: 0.1
A10: Credit union weights | C10: Total | D10: =SUM(B11:B16)
A11: Low loan-to-share ratio | B11: 0.3
A12: High liquidity (cash + investments / assets) | B12: 0.2
A13: Strong net worth ratio | B13: 0.15
A14: Shares growing faster than loans | B14: 0.1
A15: Low mortgage originations vs. assets | B15: 0.15
A16: Low 1st-mortgage share of loans (room to add) | B16: 0.1
A17: Tier cutoffs
A18: Tier 1 minimum score | B18: 60
A19: Tier 2 minimum score | B19: 45
A20: Tier 1 minimum total assets ($M) | B20: 300
A22: How the score works
A23: Each institution is ranked against its peers on each factor (0% = worst in group, 100% = best), banks against banks, credit unions against credit unions.
A24: The score is the weighted average of those ranks, times 100. Higher means more balance-sheet room to add mortgages.
A25: Tier 1 = score at or above the Tier 1 cutoff AND assets at or above the Tier 1 size floor AND not already taking broker loans. The size floor exists because a very small institution rarely has the staff or balance sheet to support a wholesale channel. Tier 2 = score at or above the Tier 2 cutoff. Everything else is Tier 3.
A26: A blank input (e.g., missing prior-year data after a merger) is treated as middle-of-the-pack (50%).

Sheet Banks
A1: Key | B1: Institution | C1: City | D1: County | E1: Website | F1: Total assets ($M) | G1: Deposits ($M) | H1: Total loans ($M) | I1: 1-4 family resi loans ($M) | J1: Loan-to-deposit | K1: Liquidity (cash+sec / assets) | L1: Leverage capital ratio | M1: Resi % of loans | N1: CRE concentration (% of capital) | O1: Deposit growth YoY | P1: Loan growth YoY | Q1: Funding gap (dep g - loan g) | R1: HMDA 2025 originations (#) | S1: HMDA 2025 volume ($M) | T1: % kept in portfolio | U1: Non-QM-feature loans (IO/balloon/non-amort.) | V1: Investor / business-purpose loans | W1: Broker-channel share | X1: Wholesale status | Y1: Capacity score | Z1: Tier | AA1: CEO / contact (fill in) | AB1: Notes (fill in)
A2: bank:24170 | B2: Hanmi Bank | C2: Los Angeles | D2: Los Angeles | E2: www.hanmi.com | F2: 7954.215 | G2: 6963.809 | H2: 6552.281 | I2: 1006.667 | J2: =IF(G2=0,"",H2/G2) | K2: 0.14852578 | L2: 0.11707843 | M2: =IF(H2=0,"",I2/H2) | N2: 3.1541174 | O2: 0.033505094 | P2: 0.030951448 | Q2: =IF(OR(O2="",P2=""),"",O2-P2) | R2: 73 | S2: 56.465 | T2: 0.94520548 | V2: 39 | X2: Unknown (small filer, channel not reported) | Y2: =ROUND(100*(Scoring!$B$4*(1-IFERROR(PERCENTRANK($J$2:$J$46,J2),0.5))+Scoring!$B$5*IFERROR(PERCENTRANK($K$2:$K$46,K2),0.5)+Scoring!$B$6*IFERROR(PERCENTRANK($L$2:$L$46,L2),0.5)+Scoring!$B$7*IFERROR(PERCENTRANK($Q$2:$Q$46,Q2),0.5)+Scoring!$B$8*IFERROR(PERCENTRANK($N$2:$N$46,N2),0.5)+Scoring!$B$9*(1-IFERROR(PERCENTRANK($M$2:$M$46,M2),0.5))),0) | Z2: =IF(AND(Y2>=Scoring!$B$18,F2>=Scoring!$B$20,X2<>"Already takes broker loans"),"Tier 1",IF(Y2>=Scoring!$B$19,"Tier 2","Tier 3"))
A3: bank:33539 | B3: Preferred Bank | C3: Los Angeles | D3: Los Angeles | E3: www.preferredbank.com | F3: 7731.004 | G3: 6476.766 | H3: 6279.342 | I3: 736.088 | J3: =IF(G3=0,"",H3/G3) | K3: 0.16741396 | L3: 0.10554007 | M3: =IF(H3=0,"",I3/H3) | N3: 3.5726449 | O3: 0.064644695 | P3: 0.092501989 | Q3: =IF(OR(O3="",P3=""),"",O3-P3) | R3: 166 | S3: 139.85 | T3: 1 | V3: 37 | X3: Unknown (small filer, channel not reported) | Y3: =ROUND(100*(Scoring!$B$4*(1-IFERROR(PERCENTRANK($J$2:$J$46,J3),0.5))+Scoring!$B$5*IFERROR(PERCENTRANK($K$2:$K$46,K3),0.5)+Scoring!$B$6*IFERROR(PERCENTRANK($L$2:$L$46,L3),0.5)+Scoring!$B$7*IFERROR(PERCENTRANK($Q$2:$Q$46,Q3),0.5)+Scoring!$B$8*IFERROR(PERCENTRANK($N$2:$N$46,N3),0.5)+Scoring!$B$9*(1-IFERROR(PERCENTRANK($M$2:$M$46,M3),0.5))),0) | Z3: =IF(AND(Y3>=Scoring!$B$18,F3>=Scoring!$B$20,X3<>"Already takes broker loans"),"Tier 1",IF(Y3>=Scoring!$B$19,"Tier 2","Tier 3"))
A4: bank:18618 | B4: SMBC MANUBANK | C4: Los Angeles | D4: Los Angeles | E4: www.smbcmanubank.com | F4: 6596.628 | G4: 5564.446 | H4: 2683.716 | I4: 5.187 | J4: =IF(G4=0,"",H4/G4) | K4: 0.55362755 | L4: 0.096265967 | M4: =IF(H4=0,"",I4/H4) | N4: 1.5473777 | O4: -0.00081038485 | P4: -0.40229641 | Q4: =IF(OR(O4="",P4=""),"",O4-P4) | X4: No HMDA mortgage reporting | Y4: =ROUND(100*(Scoring!$B$4*(1-IFERROR(PERCENTRANK($J$2:$J$46,J4),0.5))+Scoring!$B$5*IFERROR(PERCENTRANK($K$2:$K$46,K4),0.5)+Scoring!$B$6*IFERROR(PERCENTRANK($L$2:$L$46,L4),0.5)+Scoring!$B$7*IFERROR(PERCENTRANK($Q$2:$Q$46,Q4),0.5)+Scoring!$B$8*IFERROR(PERCENTRANK($N$2:$N$46,N4),0.5)+Scoring!$B$9*(1-IFERROR(PERCENTRANK($M$2:$M$46,M4),0.5))),0) | Z4: =IF(AND(Y4>=Scoring!$B$18,F4>=Scoring!$B$20,X4<>"Already takes broker loans"),"Tier 1",IF(Y4>=Scoring!$B$19,"Tier 2","Tier 3"))
A5: bank:19416 | B5: CTBC Bank Corp. (USA) | C5: Los Angeles | D5: Los Angeles | E5: http://www.ctbcbankusa.com | F5: 5872.649 | G5: 5018.563 | H5: 4418.792 | I5: 1497.789 | J5: =IF(G5=0,"",H5/G5) | K5: 0.2135011 | L5: 0.14667221 | M5: =IF(H5=0,"",I5/H5) | N5: 2.1363458 | O5: 0.10585099 | P5: 0.022499283 | Q5: =IF(OR(O5="",P5=""),"",O5-P5) | R5: 339 | S5: 322.475 | T5: 1 | U5: 2 | V5: 110 | W5: 0 | X5: Retail only | Y5: =ROUND(100*(Scoring!$B$4*(1-IFERROR(PERCENTRANK($J$2:$J$46,J5),0.5))+Scoring!$B$5*IFERROR(PERCENTRANK($K$2:$K$46,K5),0.5)+Scoring!$B$6*IFERROR(PERCENTRANK($L$2:$L$46,L5),0.5)+Scoring!$B$7*IFERROR(PERCENTRANK($Q$2:$Q$46,Q5),0.5)+Scoring!$B$8*IFERROR(PERCENTRANK($N$2:$N$46,N5),0.5)+Scoring!$B$9*(1-IFERROR(PERCENTRANK($M$2:$M$46,M5),0.5))),0) | Z5: =IF(AND(Y5>=Scoring!$B$18,F5>=Scoring!$B$20,X5<>"Already takes broker loans"),"Tier 1",IF(Y5>=Scoring!$B$19,"Tier 2","Tier 3"))
A6: bank:34788 | B6: American Business Bank | C6: Los Angeles | D6: Los Angeles | E6: WWW.AMERICANBB.BANK | F6: 4417.375 | G6: 3938.208 | H6: 3124.695 | I6: 129.557 | J6: =IF(G6=0,"",H6/G6) | K6: 0.26868378 | L6: 0.1101037 | M6: =IF(H6=0,"",I6/H6) | N6: 1.7638141 | O6: 0.0170427 | P6: 0.079350544 | Q6: =IF(OR(O6="",P6=""),"",O6-P6) | X6: No HMDA mortgage reporting | Y6: =ROUND(100*(Scoring!$B$4*(1-IFERROR(PERCENTRANK($J$2:$J$46,J6),0.5))+Scoring!$B$5*IFERROR(PERCENTRANK($K$2:$K$46,K6),0.5)+Scoring!$B$6*IFERROR(PERCENTRANK($L$2:$L$46,L6),0.5)+Scoring!$B$7*IFERROR(PERCENTRANK($Q$2:$Q$46,Q6),0.5)+Scoring!$B$8*IFERROR(PERCENTRANK($N$2:$N$46,N6),0.5)+Scoring!$B$9*(1-IFERROR(PERCENTRANK($M$2:$M$46,M6),0.5))),0) | Z6: =IF(AND(Y6>=Scoring!$B$18,F6>=Scoring!$B$20,X6<>"Already takes broker loans"),"Tier 1",IF(Y6>=Scoring!$B$19,"Tier 2","Tier 3"))
A7: bank:58816 | B7: Royal Business Bank | C7: Los Angeles | D7: Los Angeles | E7: www.royalbusinessbankusa.com | F7: 4267.264 | G7: 3477.95 | H7: 3309.459 | I7: 1775.441 | J7: =IF(G7=0,"",H7/G7) | K7: 0.16276706 | L7: 0.1254492 | M7: =IF(H7=0,"",I7/H7) | N7: 2.3122035 | O7: 0.067696557 | P7: 0.023113153 | Q7: =IF(OR(O7="",P7=""),"",O7-P7) | R7: 607 | S7: 401.965 | T7: 0.93904448 | U7: 7 | V7: 70 | W7: 0.42833608 | X7: Already takes broker loans | Y7: =ROUND(100*(Scoring!$B$4*(1-IFERROR(PERCENTRANK($J$2:$J$46,J7),0.5))+Scoring!$B$5*IFERROR(PERCENTRANK($K$2:$K$46,K7),0.5)+Scoring!$B$6*IFERROR(PERCENTRANK($L$2:$L$46,L7),0.5)+Scoring!$B$7*IFERROR(PERCENTRANK($Q$2:$Q$46,Q7),0.5)+Scoring!$B$8*IFERROR(PERCENTRANK($N$2:$N$46,N7),0.5)+Scoring!$B$9*(1-IFERROR(PERCENTRANK($M$2:$M$46,M7),0.5))),0) | Z7: =IF(AND(Y7>=Scoring!$B$18,F7>=Scoring!$B$20,X7<>"Already takes broker loans"),"Tier 1",IF(Y7>=Scoring!$B$19,"Tier 2","Tier 3"))
A8: bank:57417 | B8: Commercial Bank of California | C8: Irvine | D8: Orange | E8: http://www.cbcal.com | F8: 3979.541 | G8: 3455.518 | H8: 2780.09 | I8: 97.685 | J8: =IF(G8=0,"",H8/G8) | K8: 0.27150217 | L8: 0.092734303 | M8: =IF(H8=0,"",I8/H8) | N8: 4.6996867 | O8: 0.13247625 | P8: 0.061884471 | Q8: =IF(OR(O8="",P8=""),"",O8-P8) | X8: No HMDA mortgage reporting | Y8: =ROUND(100*(Scoring!$B$4*(1-IFERROR(PERCENTRANK($J$2:$J$46,J8),0.5))+Scoring!$B$5*IFERROR(PERCENTRANK($K$2:$K$46,K8),0.5)+Scoring!$B$6*IFERROR(PERCENTRANK($L$2:$L$46,L8),0.5)+Scoring!$B$7*IFERROR(PERCENTRANK($Q$2:$Q$46,Q8),0.5)+Scoring!$B$8*IFERROR(PERCENTRANK($N$2:$N$46,N8),0.5)+Scoring!$B$9*(1-IFERROR(PERCENTRANK($M$2:$M$46,M8),0.5))),0) | Z8: =IF(AND(Y8>=Scoring!$B$18,F8>=Scoring!$B$20,X8<>"Already takes broker loans"),"Tier 1",IF(Y8>=Scoring!$B$19,"Tier 2","Tier 3"))
A9: bank:57463 | B9: PCB Bank | C9: Los Angeles | D9: Los Angeles | E9: www.mypcbbank.com | F9: 3469.065 | G9: 2933.655 | H9: 2934.956 | I9: 450.321 | J9: =IF(G9=0,"",H9/G9) | K9: 0.12957814 | L9: 0.11544222 | M9: =IF(H9=0,"",I9/H9) | N9: 3.0353608 | O9: 0.035753954 | P9: 0.046911618 | Q9: =IF(OR(O9="",P9=""),"",O9-P9) | R9: 120 | S9: 78.15 | T9: 1 | V9: 38 | X9: Unknown (small filer, channel not reported) | Y9: =ROUND(100*(Scoring!$B$4*(1-IFERROR(PERCENTRANK($J$2:$J$46,J9),0.5))+Scoring!$B$5*IFERROR(PERCENTRANK($K$2:$K$46,K9),0.5)+Scoring!$B$6*IFERROR(PERCENTRANK($L$2:$L$46,L9),0.5)+Scoring!$B$7*IFERROR(PERCENTRANK($Q$2:$Q$46,Q9),0.5)+Scoring!$B$8*IFERROR(PERCENTRANK($N$2:$N$46,N9),0.5)+Scoring!$B$9*(1-IFERROR(PERCENTRANK($M$2:$M$46,M9),0.5))),0) | Z9: =IF(AND(Y9>=Scoring!$B$18,F9>=Scoring!$B$20,X9<>"Already takes broker loans"),"Tier 1",IF(Y9>=Scoring!$B$19,"Tier 2","Tier 3"))
A10: bank:57944 | B10: Open Bank | C10: Los Angeles | D10: Los Angeles | E10: www.myopenbank.com | F10: 2745.961 | G10: 2369.409 | H10: 2280.366 | I10: 643.706 | J10: =IF(G10=0,"",H10/G10) | K10: 0.13891093 | L10: 0.10147272 | M10: =IF(H10=0,"",I10/H10) | N10: 2.5475621 | O10: 0.049818097 | P10: 0.090251655 | Q10: =IF(OR(O10="",P10=""),"",O10-P10) | R10: 18 | S10: 15.29 | T10: 1 | U10: 0 | V10: 2 | W10: 0.055555556 | X10: Mostly retail, a few broker loans | Y10: =ROUND(100*(Scoring!$B$4*(1-IFERROR(PERCENTRANK($J$2:$J$46,J10),0.5))+Scoring!$B$5*IFERROR(PERCENTRANK($K$2:$K$46,K10),0.5)+Scoring!$B$6*IFERROR(PERCENTRANK($L$2:$L$46,L10),0.5)+Scoring!$B$7*IFERROR(PERCENTRANK($Q$2:$Q$46,Q10),0.5)+Scoring!$B$8*IFERROR(PERCENTRANK($N$2:$N$46,N10),0.5)+Scoring!$B$9*(1-IFERROR(PERCENTRANK($M$2:$M$46,M10),0.5))),0) | Z10: =IF(AND(Y10>=Scoring!$B$18,F10>=Scoring!$B$20,X10<>"Already takes broker loans"),"Tier 1",IF(Y10>=Scoring!$B$19,"Tier 2","Tier 3"))
A11: bank:57873 | B11: Commonwealth Business Bank | C11: Los Angeles | D11: Los Angeles | E11: www.cbb-bank.com | F11: 1966.224 | G11: 1664.464 | H11: 1524.027 | I11: 98.659 | J11: =IF(G11=0,"",H11/G11) | K11: 0.20880988 | L11: 0.13932885 | M11: =IF(H11=0,"",I11/H11) | N11: 2.592328 | O11: 0.091110518 | P11: 0.042353406 | Q11: =IF(OR(O11="",P11=""),"",O11-P11) | X11: No HMDA mortgage reporting | Y11: =ROUND(100*(Scoring!$B$4*(1-IFERROR(PERCENTRANK($J$2:$J$46,J11),0.5))+Scoring!$B$5*IFERROR(PERCENTRANK($K$2:$K$46,K11),0.5)+Scoring!$B$6*IFERROR(PERCENTRANK($L$2:$L$46,L11),0.5)+Scoring!$B$7*IFERROR(PERCENTRANK($Q$2:$Q$46,Q11),0.5)+Scoring!$B$8*IFERROR(PERCENTRANK($N$2:$N$46,N11),0.5)+Scoring!$B$9*(1-IFERROR(PERCENTRANK($M$2:$M$46,M11),0.5))),0) | Z11: =IF(AND(Y11>=Scoring!$B$18,F11>=Scoring!$B$20,X11<>"Already takes broker loans"),"Tier 1",IF(Y11>=Scoring!$B$19,"Tier 2","Tier 3"))
A12: bank:58310 | B12: US Metro Bank | C12: Garden Grove | D12: Orange | E12: http://WWW.USMETROBANK.COM | F12: 1640.896 | G12: 1437.567 | H12: 1371.367 | I12: 195.945 | J12: =IF(G12=0,"",H12/G12) | K12: 0.14955427 | L12: 0.10416449 | M12: =IF(H12=0,"",I12/H12) | N12: 3.929876 | O12: 0.12227943 | P12: 0.11532515 | Q12: =IF(OR(O12="",P12=""),"",O12-P12) | X12: No HMDA mortgage reporting | Y12: =ROUND(100*(Scoring!$B$4*(1-IFERROR(PERCENTRANK($J$2:$J$46,J12),0.5))+Scoring!$B$5*IFERROR(PERCENTRANK($K$2:$K$46,K12),0.5)+Scoring!$B$6*IFERROR(PERCENTRANK($L$2:$L$46,L12),0.5)+Scoring!$B$7*IFERROR(PERCENTRANK($Q$2:$Q$46,Q12),0.5)+Scoring!$B$8*IFERROR(PERCENTRANK($N$2:$N$46,N12),0.5)+Scoring!$B$9*(1-IFERROR(PERCENTRANK($M$2:$M$46,M12),0.5))),0) | Z12: =IF(AND(Y12>=Scoring!$B$18,F12>=Scoring!$B$20,X12<>"Already takes broker loans"),"Tier 1",IF(Y12>=Scoring!$B$19,"Tier 2","Tier 3"))
A13: bank:32282 | B13: Malaga Bank F.S.B. | C13: Palos Verdes Peninsula | D13: Los Angeles | E13: www.malagabank.com | F13: 1448.853 | G13: 942.08 | H13: 1242.053 | I13: 78.919 | J13: =IF(G13=0,"",H13/G13) | K13: 0.12318848 | L13: 0.16759083 | M13: =IF(H13=0,"",I13/H13) | N13: 4.7280573 | O13: 0.015512742 | P13: 0.027197236 | Q13: =IF(OR(O13="",P13=""),"",O13-P13) | R13: 5 | S13: 4.175 | T13: 1 | V13: 5 | X13: Unknown (small filer, channel not reported) | Y13: =ROUND(100*(Scoring!$B$4*(1-IFERROR(PERCENTRANK($J$2:$J$46,J13),0.5))+Scoring!$B$5*IFERROR(PERCENTRANK($K$2:$K$46,K13),0.5)+Scoring!$B$6*IFERROR(PERCENTRANK($L$2:$L$46,L13),0.5)+Scoring!$B$7*IFERROR(PERCENTRANK($Q$2:$Q$46,Q13),0.5)+Scoring!$B$8*IFERROR(PERCENTRANK($N$2:$N$46,N13),0.5)+Scoring!$B$9*(1-IFERROR(PERCENTRANK($M$2:$M$46,M13),0.5))),0) | Z13: =IF(AND(Y13>=Scoring!$B$18,F13>=Scoring!$B$20,X13<>"Already takes broker loans"),"Tier 1",IF(Y13>=Scoring!$B$19,"Tier 2","Tier 3"))
A14: bank:23998 | B14: State Bank of India (California) | C14: Los Angeles | D14: Los Angeles | E14: www.sbical.com | F14: 1382.642 | G14: 1181.334 | H14: 1182.876 | I14: 0 | J14: =IF(G14=0,"",H14/G14) | K14: 0.13513983 | L14: 0.14048502 | M14: =IF(H14=0,"",I14/H14) | N14: 2.7561624 | O14: 0.059487626 | P14: 0.039424961 | Q14: =IF(OR(O14="",P14=""),"",O14-P14) | X14: No HMDA mortgage reporting | Y14: =ROUND(100*(Scoring!$B$4*(1-IFERROR(PERCENTRANK($J$2:$J$46,J14),0.5))+Scoring!$B$5*IFERROR(PERCENTRANK($K$2:$K$46,K14),0.5)+Scoring!$B$6*IFERROR(PERCENTRANK($L$2:$L$46,L14),0.5)+Scoring!$B$7*IFERROR(PERCENTRANK($Q$2:$Q$46,Q14),0.5)+Scoring!$B$8*IFERROR(PERCENTRANK($N$2:$N$46,N14),0.5)+Scoring!$B$9*(1-IFERROR(PERCENTRANK($M$2:$M$46,M14),0.5))),0) | Z14: =IF(AND(Y14>=Scoring!$B$18,F14>=Scoring!$B$20,X14<>"Already takes broker loans"),"Tier 1",IF(Y14>=Scoring!$B$19,"Tier 2","Tier 3"))
A15: bank:30879 | B15: Provident Savings Bank, F.S.B. | C15: Riverside | D15: Riverside | E15: www.myprovident.com | F15: 1208.112 | G15: 916.825 | H15: 1038.532 | I15: 573.27 | J15: =IF(G15=0,"",H15/G15) | K15: 0.11652479 | L15: 0.10295675 | M15: =IF(H15=0,"",I15/H15) | N15: 3.5398463 | O15: 0.024184071 | P15: -0.012960846 | Q15: =IF(OR(O15="",P15=""),"",O15-P15) | R15: 110 | S15: 93.43 | T15: 0.92727273 | U15: 0 | V15: 1 | W15: 0.98181818 | X15: Already takes broker loans | Y15: =ROUND(100*(Scoring!$B$4*(1-IFERROR(PERCENTRANK($J$2:$J$46,J15),0.5))+Scoring!$B$5*IFERROR(PERCENTRANK($K$2:$K$46,K15),0.5)+Scoring!$B$6*IFERROR(PERCENTRANK($L$2:$L$46,L15),0.5)+Scoring!$B$7*IFERROR(PERCENTRANK($Q$2:$Q$46,Q15),0.5)+Scoring!$B$8*IFERROR(PERCENTRANK($N$2:$N$46,N15),0.5)+Scoring!$B$9*(1-IFERROR(PERCENTRANK($M$2:$M$46,M15),0.5))),0) | Z15: =IF(AND(Y15>=Scoring!$B$18,F15>=Scoring!$B$20,X15<>"Already takes broker loans"),"Tier 1",IF(Y15>=Scoring!$B$19,"Tier 2","Tier 3"))
A16: bank:57176 | B16: Commerce West Bank | C16: Irvine | D16: Orange | E16: www.cwbk.com | F16: 1196.315 | G16: 1055.805 | H16: 779.651 | I16: 167.387 | J16: =IF(G16=0,"",H16/G16) | K16: 0.32811258 | L16: 0.11144714 | M16: =IF(H16=0,"",I16/H16) | N16: 2.0639533 | O16: 0.021381383 | P16: -0.038779196 | Q16: =IF(OR(O16="",P16=""),"",O16-P16) | X16: No HMDA mortgage reporting | Y16: =ROUND(100*(Scoring!$B$4*(1-IFERROR(PERCENTRANK($J$2:$J$46,J16),0.5))+Scoring!$B$5*IFERROR(PERCENTRANK($K$2:$K$46,K16),0.5)+Scoring!$B$6*IFERROR(PERCENTRANK($L$2:$L$46,L16),0.5)+Scoring!$B$7*IFERROR(PERCENTRANK($Q$2:$Q$46,Q16),0.5)+Scoring!$B$8*IFERROR(PERCENTRANK($N$2:$N$46,N16),0.5)+Scoring!$B$9*(1-IFERROR(PERCENTRANK($M$2:$M$46,M16),0.5))),0) | Z16: =IF(AND(Y16>=Scoring!$B$18,F16>=Scoring!$B$20,X16<>"Already takes broker loans"),"Tier 1",IF(Y16>=Scoring!$B$19,"Tier 2","Tier 3"))
A17: bank:58060 | B17: First General Bank | C17: Rowland Heights | D17: Los Angeles | E17: http://www.firstgeneralbank.com | F17: 1174.806 | G17: 837.772 | H17: 944.215 | I17: 34.645 | J17: =IF(G17=0,"",H17/G17) | K17: 0.17093205 | L17: 0.2629498 | M17: =IF(H17=0,"",I17/H17) | N17: 2.064006 | O17: 0.016675344 | P17: 0.015459649 | Q17: =IF(OR(O17="",P17=""),"",O17-P17) | X17: No HMDA mortgage reporting | Y17: =ROUND(100*(Scoring!$B$4*(1-IFERROR(PERCENTRANK($J$2:$J$46,J17),0.5))+Scoring!$B$5*IFERROR(PERCENTRANK($K$2:$K$46,K17),0.5)+Scoring!$B$6*IFERROR(PERCENTRANK($L$2:$L$46,L17),0.5)+Scoring!$B$7*IFERROR(PERCENTRANK($Q$2:$Q$46,Q17),0.5)+Scoring!$B$8*IFERROR(PERCENTRANK($N$2:$N$46,N17),0.5)+Scoring!$B$9*(1-IFERROR(PERCENTRANK($M$2:$M$46,M17),0.5))),0) | Z17: =IF(AND(Y17>=Scoring!$B$18,F17>=Scoring!$B$20,X17<>"Already takes broker loans"),"Tier 1",IF(Y17>=Scoring!$B$19,"Tier 2","Tier 3"))
A18: bank:34010 | B18: EverTrust Bank | C18: City Of Industry | D18: Los Angeles | E18: http://www.evertrustbank.com | F18: 1125.37 | G18: 848.571 | H18: 817.04 | I18: 88.018 | J18: =IF(G18=0,"",H18/G18) | K18: 0.19982939 | L18: 0.21707859 | M18: =IF(H18=0,"",I18/H18) | N18: 2.1096786 | O18: 0.15129787 | P18: 0.023730079 | Q18: =IF(OR(O18="",P18=""),"",O18-P18) | X18: No HMDA mortgage reporting | Y18: =ROUND(100*(Scoring!$B$4*(1-IFERROR(PERCENTRANK($J$2:$J$46,J18),0.5))+Scoring!$B$5*IFERROR(PERCENTRANK($K$2:$K$46,K18),0.5)+Scoring!$B$6*IFERROR(PERCENTRANK($L$2:$L$46,L18),0.5)+Scoring!$B$7*IFERROR(PERCENTRANK($Q$2:$Q$46,Q18),0.5)+Scoring!$B$8*IFERROR(PERCENTRANK($N$2:$N$46,N18),0.5)+Scoring!$B$9*(1-IFERROR(PERCENTRANK($M$2:$M$46,M18),0.5))),0) | Z18: =IF(AND(Y18>=Scoring!$B$18,F18>=Scoring!$B$20,X18<>"Already takes broker loans"),"Tier 1",IF(Y18>=Scoring!$B$19,"Tier 2","Tier 3"))
A19: bank:57585 | B19: Golden State Bank | C19: Glendale | D19: Los Angeles | E19: www.goldenstatebank.com | F19: 1000.102 | G19: 856.56 | H19: 858.061 | I19: 32.826 | J19: =IF(G19=0,"",H19/G19) | K19: 0.1323335 | L19: 0.11035294 | M19: =IF(H19=0,"",I19/H19) | N19: 4.2035583 | O19: 0.085793892 | P19: 0.092673243 | Q19: =IF(OR(O19="",P19=""),"",O19-P19) | X19: No HMDA mortgage reporting | Y19: =ROUND(100*(Scoring!$B$4*(1-IFERROR(PERCENTRANK($J$2:$J$46,J19),0.5))+Scoring!$B$5*IFERROR(PERCENTRANK($K$2:$K$46,K19),0.5)+Scoring!$B$6*IFERROR(PERCENTRANK($L$2:$L$46,L19),0.5)+Scoring!$B$7*IFERROR(PERCENTRANK($Q$2:$Q$46,Q19),0.5)+Scoring!$B$8*IFERROR(PERCENTRANK($N$2:$N$46,N19),0.5)+Scoring!$B$9*(1-IFERROR(PERCENTRANK($M$2:$M$46,M19),0.5))),0) | Z19: =IF(AND(Y19>=Scoring!$B$18,F19>=Scoring!$B$20,X19<>"Already takes broker loans"),"Tier 1",IF(Y19>=Scoring!$B$19,"Tier 2","Tier 3"))
A20: bank:21606 | B20: HCN Bank | C20: Riverside | D20: Riverside | E20: http://www.hcnbank.com | F20: 998.433 | G20: 846.287 | H20: 786.742 | I20: 1.203 | J20: =IF(G20=0,"",H20/G20) | K20: 0.19168036 | L20: 0.11704536 | M20: =IF(H20=0,"",I20/H20) | N20: 6.1106836 | O20: 0.0037479526 | P20: 0.08928564 | Q20: =IF(OR(O20="",P20=""),"",O20-P20) | X20: No HMDA mortgage reporting | Y20: =ROUND(100*(Scoring!$B$4*(1-IFERROR(PERCENTRANK($J$2:$J$46,J20),0.5))+Scoring!$B$5*IFERROR(PERCENTRANK($K$2:$K$46,K20),0.5)+Scoring!$B$6*IFERROR(PERCENTRANK($L$2:$L$46,L20),0.5)+Scoring!$B$7*IFERROR(PERCENTRANK($Q$2:$Q$46,Q20),0.5)+Scoring!$B$8*IFERROR(PERCENTRANK($N$2:$N$46,N20),0.5)+Scoring!$B$9*(1-IFERROR(PERCENTRANK($M$2:$M$46,M20),0.5))),0) | Z20: =IF(AND(Y20>=Scoring!$B$18,F20>=Scoring!$B$20,X20<>"Already takes broker loans"),"Tier 1",IF(Y20>=Scoring!$B$19,"Tier 2","Tier 3"))
A21: bank:58469 | B21: American Plus Bank, N.A. | C21: Arcadia | D21: Los Angeles | E21: www.bankaplus.com | F21: 935.046 | G21: 747.993 | H21: 804.179 | I21: 37.578 | J21: =IF(G21=0,"",H21/G21) | K21: 0.051047756 | L21: 0.16464303 | M21: =IF(H21=0,"",I21/H21) | N21: 4.5492027 | O21: 0.041981957 | P21: 0.046647439 | Q21: =IF(OR(O21="",P21=""),"",O21-P21) | X21: No HMDA mortgage reporting | Y21: =ROUND(100*(Scoring!$B$4*(1-IFERROR(PERCENTRANK($J$2:$J$46,J21),0.5))+Scoring!$B$5*IFERROR(PERCENTRANK($K$2:$K$46,K21),0.5)+Scoring!$B$6*IFERROR(PERCENTRANK($L$2:$L$46,L21),0.5)+Scoring!$B$7*IFERROR(PERCENTRANK($Q$2:$Q$46,Q21),0.5)+Scoring!$B$8*IFERROR(PERCENTRANK($N$2:$N$46,N21),0.5)+Scoring!$B$9*(1-IFERROR(PERCENTRANK($M$2:$M$46,M21),0.5))),0) | Z21: =IF(AND(Y21>=Scoring!$B$18,F21>=Scoring!$B$20,X21<>"Already takes broker loans"),"Tier 1",IF(Y21>=Scoring!$B$19,"Tier 2","Tier 3"))
A22: bank:34496 | B22: First Commercial Bank (USA) | C22: Alhambra | D22: Los Angeles | E22: bankfcb.com | F22: 849.866 | G22: 646.751 | H22: 732.112 | I22: 228.306 | J22: =IF(G22=0,"",H22/G22) | K22: 0.12530917 | L22: 0.23268476 | M22: =IF(H22=0,"",I22/H22) | N22: 1.625512 | O22: 0.042076125 | P22: 0.064315838 | Q22: =IF(OR(O22="",P22=""),"",O22-P22) | R22: 47 | S22: 33.125 | T22: 0.91489362 | V22: 13 | X22: Unknown (small filer, channel not reported) | Y22: =ROUND(100*(Scoring!$B$4*(1-IFERROR(PERCENTRANK($J$2:$J$46,J22),0.5))+Scoring!$B$5*IFERROR(PERCENTRANK($K$2:$K$46,K22),0.5)+Scoring!$B$6*IFERROR(PERCENTRANK($L$2:$L$46,L22),0.5)+Scoring!$B$7*IFERROR(PERCENTRANK($Q$2:$Q$46,Q22),0.5)+Scoring!$B$8*IFERROR(PERCENTRANK($N$2:$N$46,N22),0.5)+Scoring!$B$9*(1-IFERROR(PERCENTRANK($M$2:$M$46,M22),0.5))),0) | Z22: =IF(AND(Y22>=Scoring!$B$18,F22>=Scoring!$B$20,X22<>"Already takes broker loans"),"Tier 1",IF(Y22>=Scoring!$B$19,"Tier 2","Tier 3"))
A23: bank:57101 | B23: Mission Valley Bank | C23: Sun Valley | D23: Los Angeles | E23: www.missionvalleybank.com | F23: 782.004 | G23: 615.31 | H23: 630.507 | I23: 10.562 | J23: =IF(G23=0,"",H23/G23) | K23: 0.14292638 | L23: 0.10995416 | M23: =IF(H23=0,"",I23/H23) | N23: 2.2548803 | O23: 0.026258994 | P23: 0.057276767 | Q23: =IF(OR(O23="",P23=""),"",O23-P23) | X23: No HMDA mortgage reporting | Y23: =ROUND(100*(Scoring!$B$4*(1-IFERROR(PERCENTRANK($J$2:$J$46,J23),0.5))+Scoring!$B$5*IFERROR(PERCENTRANK($K$2:$K$46,K23),0.5)+Scoring!$B$6*IFERROR(PERCENTRANK($L$2:$L$46,L23),0.5)+Scoring!$B$7*IFERROR(PERCENTRANK($Q$2:$Q$46,Q23),0.5)+Scoring!$B$8*IFERROR(PERCENTRANK($N$2:$N$46,N23),0.5)+Scoring!$B$9*(1-IFERROR(PERCENTRANK($M$2:$M$46,M23),0.5))),0) | Z23: =IF(AND(Y23>=Scoring!$B$18,F23>=Scoring!$B$20,X23<>"Already takes broker loans"),"Tier 1",IF(Y23>=Scoring!$B$19,"Tier 2","Tier 3"))
A24: bank:22366 | B24: GBC International Bank | C24: Los Angeles | D24: Los Angeles | E24: http://www.gbcib.com | F24: 658.463 | G24: 504.604 | H24: 456.915 | I24: 2.133 | J24: =IF(G24=0,"",H24/G24) | K24: 0.28676934 | L24: 0.15943555 | M24: =IF(H24=0,"",I24/H24) | N24: 2.6863223 | O24: -0.015892642 | P24: 0.023759217 | Q24: =IF(OR(O24="",P24=""),"",O24-P24) | X24: No HMDA mortgage reporting | Y24: =ROUND(100*(Scoring!$B$4*(1-IFERROR(PERCENTRANK($J$2:$J$46,J24),0.5))+Scoring!$B$5*IFERROR(PERCENTRANK($K$2:$K$46,K24),0.5)+Scoring!$B$6*IFERROR(PERCENTRANK($L$2:$L$46,L24),0.5)+Scoring!$B$7*IFERROR(PERCENTRANK($Q$2:$Q$46,Q24),0.5)+Scoring!$B$8*IFERROR(PERCENTRANK($N$2:$N$46,N24),0.5)+Scoring!$B$9*(1-IFERROR(PERCENTRANK($M$2:$M$46,M24),0.5))),0) | Z24: =IF(AND(Y24>=Scoring!$B$18,F24>=Scoring!$B$20,X24<>"Already takes broker loans"),"Tier 1",IF(Y24>=Scoring!$B$19,"Tier 2","Tier 3"))
A25: bank:58588 | B25: Partners Bank of California | C25: Mission Viejo | D25: Orange | E25: www.partnersbankca.com | F25: 602.153 | G25: 508.991 | H25: 505.82 | I25: 64.001 | J25: =IF(G25=0,"",H25/G25) | K25: 0.15813755 | L25: 0.1167327 | M25: =IF(H25=0,"",I25/H25) | N25: 3.6500739 | O25: -0.11906505 | P25: 0.20725662 | Q25: =IF(OR(O25="",P25=""),"",O25-P25) | X25: No HMDA mortgage reporting | Y25: =ROUND(100*(Scoring!$B$4*(1-IFERROR(PERCENTRANK($J$2:$J$46,J25),0.5))+Scoring!$B$5*IFERROR(PERCENTRANK($K$2:$K$46,K25),0.5)+Scoring!$B$6*IFERROR(PERCENTRANK($L$2:$L$46,L25),0.5)+Scoring!$B$7*IFERROR(PERCENTRANK($Q$2:$Q$46,Q25),0.5)+Scoring!$B$8*IFERROR(PERCENTRANK($N$2:$N$46,N25),0.5)+Scoring!$B$9*(1-IFERROR(PERCENTRANK($M$2:$M$46,M25),0.5))),0) | Z25: =IF(AND(Y25>=Scoring!$B$18,F25>=Scoring!$B$20,X25<>"Already takes broker loans"),"Tier 1",IF(Y25>=Scoring!$B$19,"Tier 2","Tier 3"))
A26: bank:23086 | B26: New OMNI Bank, National Association | C26: Alhambra | D26: Los Angeles | E26: WWW.NEWOMNIBANK.COM | F26: 517.936 | G26: 373.759 | H26: 384.558 | I26: 165.411 | J26: =IF(G26=0,"",H26/G26) | K26: 0.21833393 | L26: 0.27114538 | M26: =IF(H26=0,"",I26/H26) | N26: 1.2977626 | O26: -2.4079108e-05 | P26: 0.077151036 | Q26: =IF(OR(O26="",P26=""),"",O26-P26) | X26: No HMDA mortgage reporting | Y26: =ROUND(100*(Scoring!$B$4*(1-IFERROR(PERCENTRANK($J$2:$J$46,J26),0.5))+Scoring!$B$5*IFERROR(PERCENTRANK($K$2:$K$46,K26),0.5)+Scoring!$B$6*IFERROR(PERCENTRANK($L$2:$L$46,L26),0.5)+Scoring!$B$7*IFERROR(PERCENTRANK($Q$2:$Q$46,Q26),0.5)+Scoring!$B$8*IFERROR(PERCENTRANK($N$2:$N$46,N26),0.5)+Scoring!$B$9*(1-IFERROR(PERCENTRANK($M$2:$M$46,M26),0.5))),0) | Z26: =IF(AND(Y26>=Scoring!$B$18,F26>=Scoring!$B$20,X26<>"Already takes broker loans"),"Tier 1",IF(Y26>=Scoring!$B$19,"Tier 2","Tier 3"))
A27: bank:35366 | B27: Chino Commercial Bank, N.A. | C27: Chino | D27: San Bernardino | E27: www.chinocommercialbank.com | F27: 516.688 | G27: 397.231 | H27: 239.264 | I27: 18.446 | J27: =IF(G27=0,"",H27/G27) | K27: 0.4973814 | L27: 0.12510506 | M27: =IF(H27=0,"",I27/H27) | N27: 2.1297831 | O27: 0.048664588 | P27: 0.16290395 | Q27: =IF(OR(O27="",P27=""),"",O27-P27) | X27: No HMDA mortgage reporting | Y27: =ROUND(100*(Scoring!$B$4*(1-IFERROR(PERCENTRANK($J$2:$J$46,J27),0.5))+Scoring!$B$5*IFERROR(PERCENTRANK($K$2:$K$46,K27),0.5)+Scoring!$B$6*IFERROR(PERCENTRANK($L$2:$L$46,L27),0.5)+Scoring!$B$7*IFERROR(PERCENTRANK($Q$2:$Q$46,Q27),0.5)+Scoring!$B$8*IFERROR(PERCENTRANK($N$2:$N$46,N27),0.5)+Scoring!$B$9*(1-IFERROR(PERCENTRANK($M$2:$M$46,M27),0.5))),0) | Z27: =IF(AND(Y27>=Scoring!$B$18,F27>=Scoring!$B$20,X27<>"Already takes broker loans"),"Tier 1",IF(Y27>=Scoring!$B$19,"Tier 2","Tier 3"))
A28: bank:24332 | B28: First Credit Bank | C28: Los Angeles | D28: Los Angeles | F28: 515.839 | G28: 265.294 | H28: 408.96 | I28: 40.919 | J28: =IF(G28=0,"",H28/G28) | K28: 0.13735681 | L28: 0.47614441 | M28: =IF(H28=0,"",I28/H28) | N28: 1.101237 | O28: -0.060423934 | P28: -0.047690015 | Q28: =IF(OR(O28="",P28=""),"",O28-P28) | X28: No HMDA mortgage reporting | Y28: =ROUND(100*(Scoring!$B$4*(1-IFERROR(PERCENTRANK($J$2:$J$46,J28),0.5))+Scoring!$B$5*IFERROR(PERCENTRANK($K$2:$K$46,K28),0.5)+Scoring!$B$6*IFERROR(PERCENTRANK($L$2:$L$46,L28),0.5)+Scoring!$B$7*IFERROR(PERCENTRANK($Q$2:$Q$46,Q28),0.5)+Scoring!$B$8*IFERROR(PERCENTRANK($N$2:$N$46,N28),0.5)+Scoring!$B$9*(1-IFERROR(PERCENTRANK($M$2:$M$46,M28),0.5))),0) | Z28: =IF(AND(Y28>=Scoring!$B$18,F28>=Scoring!$B$20,X28<>"Already takes broker loans"),"Tier 1",IF(Y28>=Scoring!$B$19,"Tier 2","Tier 3"))
A29: bank:58218 | B29: First Pacific Bank | C29: Whittier | D29: Los Angeles | E29: www.firstpacbank.com | F29: 514.36 | G29: 420.102 | H29: 352.887 | I29: 86.647 | J29: =IF(G29=0,"",H29/G29) | K29: 0.19979975 | L29: 0.092481904 | M29: =IF(H29=0,"",I29/H29) | N29: 2.4319579 | O29: 0.11084904 | P29: 0.13145061 | Q29: =IF(OR(O29="",P29=""),"",O29-P29) | X29: No HMDA mortgage reporting | Y29: =ROUND(100*(Scoring!$B$4*(1-IFERROR(PERCENTRANK($J$2:$J$46,J29),0.5))+Scoring!$B$5*IFERROR(PERCENTRANK($K$2:$K$46,K29),0.5)+Scoring!$B$6*IFERROR(PERCENTRANK($L$2:$L$46,L29),0.5)+Scoring!$B$7*IFERROR(PERCENTRANK($Q$2:$Q$46,Q29),0.5)+Scoring!$B$8*IFERROR(PERCENTRANK($N$2:$N$46,N29),0.5)+Scoring!$B$9*(1-IFERROR(PERCENTRANK($M$2:$M$46,M29),0.5))),0) | Z29: =IF(AND(Y29>=Scoring!$B$18,F29>=Scoring!$B$20,X29<>"Already takes broker loans"),"Tier 1",IF(Y29>=Scoring!$B$19,"Tier 2","Tier 3"))
A30: bank:58401 | B30: Mega Bank | C30: San Gabriel | D30: Los Angeles | E30: https://www.megabankusa.com | F30: 506.664 | G30: 426.08 | H30: 433.1 | I30: 23.392 | J30: =IF(G30=0,"",H30/G30) | K30: 0.10523147 | L30: 0.14433342 | M30: =IF(H30=0,"",I30/H30) | N30: 3.7250416 | O30: -0.019554602 | P30: 0.049234817 | Q30: =IF(OR(O30="",P30=""),"",O30-P30) | X30: No HMDA mortgage reporting | Y30: =ROUND(100*(Scoring!$B$4*(1-IFERROR(PERCENTRANK($J$2:$J$46,J30),0.5))+Scoring!$B$5*IFERROR(PERCENTRANK($K$2:$K$46,K30),0.5)+Scoring!$B$6*IFERROR(PERCENTRANK($L$2:$L$46,L30),0.5)+Scoring!$B$7*IFERROR(PERCENTRANK($Q$2:$Q$46,Q30),0.5)+Scoring!$B$8*IFERROR(PERCENTRANK($N$2:$N$46,N30),0.5)+Scoring!$B$9*(1-IFERROR(PERCENTRANK($M$2:$M$46,M30),0.5))),0) | Z30: =IF(AND(Y30>=Scoring!$B$18,F30>=Scoring!$B$20,X30<>"Already takes broker loans"),"Tier 1",IF(Y30>=Scoring!$B$19,"Tier 2","Tier 3"))
A31: bank:58234 | B31: Pacific Alliance Bank | C31: San Gabriel | D31: Los Angeles | E31: www.pacificalliancebank.com | F31: 454.372 | G31: 369.168 | H31: 347.994 | I31: 44.68 | J31: =IF(G31=0,"",H31/G31) | K31: 0.1800199 | L31: 0.13370668 | M31: =IF(H31=0,"",I31/H31) | N31: 4.0690387 | O31: 0.060681285 | P31: 0.002879004 | Q31: =IF(OR(O31="",P31=""),"",O31-P31) | X31: No HMDA mortgage reporting | Y31: =ROUND(100*(Scoring!$B$4*(1-IFERROR(PERCENTRANK($J$2:$J$46,J31),0.5))+Scoring!$B$5*IFERROR(PERCENTRANK($K$2:$K$46,K31),0.5)+Scoring!$B$6*IFERROR(PERCENTRANK($L$2:$L$46,L31),0.5)+Scoring!$B$7*IFERROR(PERCENTRANK($Q$2:$Q$46,Q31),0.5)+Scoring!$B$8*IFERROR(PERCENTRANK($N$2:$N$46,N31),0.5)+Scoring!$B$9*(1-IFERROR(PERCENTRANK($M$2:$M$46,M31),0.5))),0) | Z31: =IF(AND(Y31>=Scoring!$B$18,F31>=Scoring!$B$20,X31<>"Already takes broker loans"),"Tier 1",IF(Y31>=Scoring!$B$19,"Tier 2","Tier 3"))
A32: bank:26363 | B32: Community Commerce Bank | C32: Claremont | D32: Los Angeles | E32: www.ccombank.com | F32: 422.736 | G32: 317.509 | H32: 317.747 | I32: 11.126 | J32: =IF(G32=0,"",H32/G32) | K32: 0.14999196 | L32: 0.15253258 | M32: =IF(H32=0,"",I32/H32) | N32: 2.2491112 | O32: 0.063760143 | P32: 0.081169273 | Q32: =IF(OR(O32="",P32=""),"",O32-P32) | X32: No HMDA mortgage reporting | Y32: =ROUND(100*(Scoring!$B$4*(1-IFERROR(PERCENTRANK($J$2:$J$46,J32),0.5))+Scoring!$B$5*IFERROR(PERCENTRANK($K$2:$K$46,K32),0.5)+Scoring!$B$6*IFERROR(PERCENTRANK($L$2:$L$46,L32),0.5)+Scoring!$B$7*IFERROR(PERCENTRANK($Q$2:$Q$46,Q32),0.5)+Scoring!$B$8*IFERROR(PERCENTRANK($N$2:$N$46,N32),0.5)+Scoring!$B$9*(1-IFERROR(PERCENTRANK($M$2:$M$46,M32),0.5))),0) | Z32: =IF(AND(Y32>=Scoring!$B$18,F32>=Scoring!$B$20,X32<>"Already takes broker loans"),"Tier 1",IF(Y32>=Scoring!$B$19,"Tier 2","Tier 3"))
A33: bank:35331 | B33: Liberty Bank, National Association | C33: Irvine | D33: Orange | E33: www.libertybk.com | F33: 399.182 | G33: 336.266 | H33: 329.379 | I33: 22.579 | J33: =IF(G33=0,"",H33/G33) | K33: 0.15291521 | L33: 0.14442363 | M33: =IF(H33=0,"",I33/H33) | N33: 4.8011194 | O33: 0.026330809 | P33: -0.12647553 | Q33: =IF(OR(O33="",P33=""),"",O33-P33) | X33: No HMDA mortgage reporting | Y33: =ROUND(100*(Scoring!$B$4*(1-IFERROR(PERCENTRANK($J$2:$J$46,J33),0.5))+Scoring!$B$5*IFERROR(PERCENTRANK($K$2:$K$46,K33),0.5)+Scoring!$B$6*IFERROR(PERCENTRANK($L$2:$L$46,L33),0.5)+Scoring!$B$7*IFERROR(PERCENTRANK($Q$2:$Q$46,Q33),0.5)+Scoring!$B$8*IFERROR(PERCENTRANK($N$2:$N$46,N33),0.5)+Scoring!$B$9*(1-IFERROR(PERCENTRANK($M$2:$M$46,M33),0.5))),0) | Z33: =IF(AND(Y33>=Scoring!$B$18,F33>=Scoring!$B$20,X33<>"Already takes broker loans"),"Tier 1",IF(Y33>=Scoring!$B$19,"Tier 2","Tier 3"))
A34: bank:30722 | B34: Universal Bank | C34: West Covina | D34: Los Angeles | E34: https://www.universalbank.com | F34: 388.009 | G34: 275.101 | H34: 261.579 | I34: 8.969 | J34: =IF(G34=0,"",H34/G34) | K34: 0.26760977 | L34: 0.17801088 | M34: =IF(H34=0,"",I34/H34) | N34: 3.4724771 | O34: 0.033825629 | P34: -0.067241724 | Q34: =IF(OR(O34="",P34=""),"",O34-P34) | X34: No HMDA mortgage reporting | Y34: =ROUND(100*(Scoring!$B$4*(1-IFERROR(PERCENTRANK($J$2:$J$46,J34),0.5))+Scoring!$B$5*IFERROR(PERCENTRANK($K$2:$K$46,K34),0.5)+Scoring!$B$6*IFERROR(PERCENTRANK($L$2:$L$46,L34),0.5)+Scoring!$B$7*IFERROR(PERCENTRANK($Q$2:$Q$46,Q34),0.5)+Scoring!$B$8*IFERROR(PERCENTRANK($N$2:$N$46,N34),0.5)+Scoring!$B$9*(1-IFERROR(PERCENTRANK($M$2:$M$46,M34),0.5))),0) | Z34: =IF(AND(Y34>=Scoring!$B$18,F34>=Scoring!$B$20,X34<>"Already takes broker loans"),"Tier 1",IF(Y34>=Scoring!$B$19,"Tier 2","Tier 3"))
A35: bank:57444 | B35: American Continental Bank | C35: City Of Industry | D35: Los Angeles | E35: http://www.americancontinentalbank.com | F35: 385.265 | G35: 316.728 | H35: 287.221 | I35: 114.266 | J35: =IF(G35=0,"",H35/G35) | K35: 0.22694509 | L35: 0.16233157 | M35: =IF(H35=0,"",I35/H35) | N35: 1.9563891 | O35: 0.072149593 | P35: 0.013100206 | Q35: =IF(OR(O35="",P35=""),"",O35-P35) | R35: 42 | S35: 47.29 | T35: 1 | V35: 21 | X35: Unknown (small filer, channel not reported) | Y35: =ROUND(100*(Scoring!$B$4*(1-IFERROR(PERCENTRANK($J$2:$J$46,J35),0.5))+Scoring!$B$5*IFERROR(PERCENTRANK($K$2:$K$46,K35),0.5)+Scoring!$B$6*IFERROR(PERCENTRANK($L$2:$L$46,L35),0.5)+Scoring!$B$7*IFERROR(PERCENTRANK($Q$2:$Q$46,Q35),0.5)+Scoring!$B$8*IFERROR(PERCENTRANK($N$2:$N$46,N35),0.5)+Scoring!$B$9*(1-IFERROR(PERCENTRANK($M$2:$M$46,M35),0.5))),0) | Z35: =IF(AND(Y35>=Scoring!$B$18,F35>=Scoring!$B$20,X35<>"Already takes broker loans"),"Tier 1",IF(Y35>=Scoring!$B$19,"Tier 2","Tier 3"))
A36: bank:59098 | B36: Infinity Bank | C36: Santa Ana | D36: Orange | E36: www.infinity.bank | F36: 359.51 | G36: 310.467 | H36: 255.149 | I36: 54.112 | J36: =IF(G36=0,"",H36/G36) | K36: 0.28521877 | L36: 0.13031808 | M36: =IF(H36=0,"",I36/H36) | N36: 1.1329208 | O36: 0.064621325 | P36: 0.15268441 | Q36: =IF(OR(O36="",P36=""),"",O36-P36) | X36: No HMDA mortgage reporting | Y36: =ROUND(100*(Scoring!$B$4*(1-IFERROR(PERCENTRANK($J$2:$J$46,J36),0.5))+Scoring!$B$5*IFERROR(PERCENTRANK($K$2:$K$46,K36),0.5)+Scoring!$B$6*IFERROR(PERCENTRANK($L$2:$L$46,L36),0.5)+Scoring!$B$7*IFERROR(PERCENTRANK($Q$2:$Q$46,Q36),0.5)+Scoring!$B$8*IFERROR(PERCENTRANK($N$2:$N$46,N36),0.5)+Scoring!$B$9*(1-IFERROR(PERCENTRANK($M$2:$M$46,M36),0.5))),0) | Z36: =IF(AND(Y36>=Scoring!$B$18,F36>=Scoring!$B$20,X36<>"Already takes broker loans"),"Tier 1",IF(Y36>=Scoring!$B$19,"Tier 2","Tier 3"))
A37: bank:59245 | B37: Genesis Bank | C37: Newport Beach | D37: Orange | E37: www.mygenesisbank.com | F37: 340.254 | G37: 292.418 | H37: 260.819 | I37: 12.279 | J37: =IF(G37=0,"",H37/G37) | K37: 0.19721149 | L37: 0.11012386 | M37: =IF(H37=0,"",I37/H37) | N37: 4.4157387 | O37: -0.31935506 | P37: -0.13564254 | Q37: =IF(OR(O37="",P37=""),"",O37-P37) | X37: No HMDA mortgage reporting | Y37: =ROUND(100*(Scoring!$B$4*(1-IFERROR(PERCENTRANK($J$2:$J$46,J37),0.5))+Scoring!$B$5*IFERROR(PERCENTRANK($K$2:$K$46,K37),0.5)+Scoring!$B$6*IFERROR(PERCENTRANK($L$2:$L$46,L37),0.5)+Scoring!$B$7*IFERROR(PERCENTRANK($Q$2:$Q$46,Q37),0.5)+Scoring!$B$8*IFERROR(PERCENTRANK($N$2:$N$46,N37),0.5)+Scoring!$B$9*(1-IFERROR(PERCENTRANK($M$2:$M$46,M37),0.5))),0) | Z37: =IF(AND(Y37>=Scoring!$B$18,F37>=Scoring!$B$20,X37<>"Already takes broker loans"),"Tier 1",IF(Y37>=Scoring!$B$19,"Tier 2","Tier 3"))
A38: bank:59296 | B38: Bank Irvine | C38: Irvine | D38: Orange | E38: www.bankirvine.com | F38: 305.639 | G38: 234.749 | H38: 238.563 | I38: 144.099 | J38: =IF(G38=0,"",H38/G38) | K38: 0.21738718 | L38: 0.22762777 | M38: =IF(H38=0,"",I38/H38) | N38: 0.81365145 | O38: 0.4293656 | P38: 0.26441905 | Q38: =IF(OR(O38="",P38=""),"",O38-P38) | X38: No HMDA mortgage reporting | Y38: =ROUND(100*(Scoring!$B$4*(1-IFERROR(PERCENTRANK($J$2:$J$46,J38),0.5))+Scoring!$B$5*IFERROR(PERCENTRANK($K$2:$K$46,K38),0.5)+Scoring!$B$6*IFERROR(PERCENTRANK($L$2:$L$46,L38),0.5)+Scoring!$B$7*IFERROR(PERCENTRANK($Q$2:$Q$46,Q38),0.5)+Scoring!$B$8*IFERROR(PERCENTRANK($N$2:$N$46,N38),0.5)+Scoring!$B$9*(1-IFERROR(PERCENTRANK($M$2:$M$46,M38),0.5))),0) | Z38: =IF(AND(Y38>=Scoring!$B$18,F38>=Scoring!$B$20,X38<>"Already takes broker loans"),"Tier 1",IF(Y38>=Scoring!$B$19,"Tier 2","Tier 3"))
A39: bank:23805 | B39: United Pacific Bank | C39: City Of Industry | D39: Los Angeles | E39: www.upbnet.com | F39: 191.036 | G39: 156.802 | H39: 154.49 | I39: 0.018 | J39: =IF(G39=0,"",H39/G39) | K39: 0.18208086 | L39: 0.17394254 | M39: =IF(H39=0,"",I39/H39) | N39: 3.745342 | O39: 0.099624113 | P39: 0.18621293 | Q39: =IF(OR(O39="",P39=""),"",O39-P39) | X39: No HMDA mortgage reporting | Y39: =ROUND(100*(Scoring!$B$4*(1-IFERROR(PERCENTRANK($J$2:$J$46,J39),0.5))+Scoring!$B$5*IFERROR(PERCENTRANK($K$2:$K$46,K39),0.5)+Scoring!$B$6*IFERROR(PERCENTRANK($L$2:$L$46,L39),0.5)+Scoring!$B$7*IFERROR(PERCENTRANK($Q$2:$Q$46,Q39),0.5)+Scoring!$B$8*IFERROR(PERCENTRANK($N$2:$N$46,N39),0.5)+Scoring!$B$9*(1-IFERROR(PERCENTRANK($M$2:$M$46,M39),0.5))),0) | Z39: =IF(AND(Y39>=Scoring!$B$18,F39>=Scoring!$B$20,X39<>"Already takes broker loans"),"Tier 1",IF(Y39>=Scoring!$B$19,"Tier 2","Tier 3"))
A40: bank:59290 | B40: Beach Cities Commercial Bank | C40: Irvine | D40: Orange | E40: www.beachcitiescb.com | F40: 188.867 | G40: 139.556 | H40: 153.508 | I40: 17.493 | J40: =IF(G40=0,"",H40/G40) | K40: 0.17608158 | L40: 0.098080575 | M40: =IF(H40=0,"",I40/H40) | N40: 2.733293 | O40: 0.048985636 | P40: 0.16881891 | Q40: =IF(OR(O40="",P40=""),"",O40-P40) | X40: No HMDA mortgage reporting | Y40: =ROUND(100*(Scoring!$B$4*(1-IFERROR(PERCENTRANK($J$2:$J$46,J40),0.5))+Scoring!$B$5*IFERROR(PERCENTRANK($K$2:$K$46,K40),0.5)+Scoring!$B$6*IFERROR(PERCENTRANK($L$2:$L$46,L40),0.5)+Scoring!$B$7*IFERROR(PERCENTRANK($Q$2:$Q$46,Q40),0.5)+Scoring!$B$8*IFERROR(PERCENTRANK($N$2:$N$46,N40),0.5)+Scoring!$B$9*(1-IFERROR(PERCENTRANK($M$2:$M$46,M40),0.5))),0) | Z40: =IF(AND(Y40>=Scoring!$B$18,F40>=Scoring!$B$20,X40<>"Already takes broker loans"),"Tier 1",IF(Y40>=Scoring!$B$19,"Tier 2","Tier 3"))
A41: bank:59314 | B41: Icon Business Bank | C41: Riverside | D41: Riverside | E41: www.iconbusinessbank.com | F41: 155.506 | G41: 129.187 | H41: 122.746 | I41: 0 | J41: =IF(G41=0,"",H41/G41) | K41: 0.16883593 | L41: 0.11943511 | M41: =IF(H41=0,"",I41/H41) | N41: 0.78492657 | O41: -0.064187819 | P41: 0.13814942 | Q41: =IF(OR(O41="",P41=""),"",O41-P41) | X41: No HMDA mortgage reporting | Y41: =ROUND(100*(Scoring!$B$4*(1-IFERROR(PERCENTRANK($J$2:$J$46,J41),0.5))+Scoring!$B$5*IFERROR(PERCENTRANK($K$2:$K$46,K41),0.5)+Scoring!$B$6*IFERROR(PERCENTRANK($L$2:$L$46,L41),0.5)+Scoring!$B$7*IFERROR(PERCENTRANK($Q$2:$Q$46,Q41),0.5)+Scoring!$B$8*IFERROR(PERCENTRANK($N$2:$N$46,N41),0.5)+Scoring!$B$9*(1-IFERROR(PERCENTRANK($M$2:$M$46,M41),0.5))),0) | Z41: =IF(AND(Y41>=Scoring!$B$18,F41>=Scoring!$B$20,X41<>"Already takes broker loans"),"Tier 1",IF(Y41>=Scoring!$B$19,"Tier 2","Tier 3"))
A42: bank:24211 | B42: Bank of Whittier, National Association | C42: Whittier | D42: Los Angeles | E42: http://www.whittierbank.com | F42: 152.608 | G42: 125.183 | H42: 86.68 | I42: 27.306 | J42: =IF(G42=0,"",H42/G42) | K42: 0.40868762 | L42: 0.16376902 | M42: =IF(H42=0,"",I42/H42) | N42: 1.069689 | O42: -0.15370574 | P42: 0.0020809249 | Q42: =IF(OR(O42="",P42=""),"",O42-P42) | R42: 74 | S42: 30.41 | T42: 0.094594595 | U42: 0 | V42: 19 | W42: 0 | X42: Retail only | Y42: =ROUND(100*(Scoring!$B$4*(1-IFERROR(PERCENTRANK($J$2:$J$46,J42),0.5))+Scoring!$B$5*IFERROR(PERCENTRANK($K$2:$K$46,K42),0.5)+Scoring!$B$6*IFERROR(PERCENTRANK($L$2:$L$46,L42),0.5)+Scoring!$B$7*IFERROR(PERCENTRANK($Q$2:$Q$46,Q42),0.5)+Scoring!$B$8*IFERROR(PERCENTRANK($N$2:$N$46,N42),0.5)+Scoring!$B$9*(1-IFERROR(PERCENTRANK($M$2:$M$46,M42),0.5))),0) | Z42: =IF(AND(Y42>=Scoring!$B$18,F42>=Scoring!$B$20,X42<>"Already takes broker loans"),"Tier 1",IF(Y42>=Scoring!$B$19,"Tier 2","Tier 3"))
A43: bank:58037 | B43: California Business Bank | C43: Irvine | D43: Orange | E43: http://www.californiabusinessbank.com | F43: 130.475 | G43: 108.427 | H43: 94.354 | I43: 0.182 | J43: =IF(G43=0,"",H43/G43) | K43: 0.15707224 | L43: 0.14460874 | M43: =IF(H43=0,"",I43/H43) | N43: 1.1861089 | O43: 0.15015063 | P43: 0.041411889 | Q43: =IF(OR(O43="",P43=""),"",O43-P43) | X43: No HMDA mortgage reporting | Y43: =ROUND(100*(Scoring!$B$4*(1-IFERROR(PERCENTRANK($J$2:$J$46,J43),0.5))+Scoring!$B$5*IFERROR(PERCENTRANK($K$2:$K$46,K43),0.5)+Scoring!$B$6*IFERROR(PERCENTRANK($L$2:$L$46,L43),0.5)+Scoring!$B$7*IFERROR(PERCENTRANK($Q$2:$Q$46,Q43),0.5)+Scoring!$B$8*IFERROR(PERCENTRANK($N$2:$N$46,N43),0.5)+Scoring!$B$9*(1-IFERROR(PERCENTRANK($M$2:$M$46,M43),0.5))),0) | Z43: =IF(AND(Y43>=Scoring!$B$18,F43>=Scoring!$B$20,X43<>"Already takes broker loans"),"Tier 1",IF(Y43>=Scoring!$B$19,"Tier 2","Tier 3"))
A44: bank:32277 | B44: Eastern International Bank | C44: Los Angeles | D44: Los Angeles | E44: https://www.eibankca.com | F44: 125.822 | G44: 88.117 | H44: 97.996 | I44: 0 | J44: =IF(G44=0,"",H44/G44) | K44: 0.21065473 | L44: 0.18272822 | M44: =IF(H44=0,"",I44/H44) | N44: 3.6484345 | O44: -0.0389473 | P44: 0.17915458 | Q44: =IF(OR(O44="",P44=""),"",O44-P44) | X44: No HMDA mortgage reporting | Y44: =ROUND(100*(Scoring!$B$4*(1-IFERROR(PERCENTRANK($J$2:$J$46,J44),0.5))+Scoring!$B$5*IFERROR(PERCENTRANK($K$2:$K$46,K44),0.5)+Scoring!$B$6*IFERROR(PERCENTRANK($L$2:$L$46,L44),0.5)+Scoring!$B$7*IFERROR(PERCENTRANK($Q$2:$Q$46,Q44),0.5)+Scoring!$B$8*IFERROR(PERCENTRANK($N$2:$N$46,N44),0.5)+Scoring!$B$9*(1-IFERROR(PERCENTRANK($M$2:$M$46,M44),0.5))),0) | Z44: =IF(AND(Y44>=Scoring!$B$18,F44>=Scoring!$B$20,X44<>"Already takes broker loans"),"Tier 1",IF(Y44>=Scoring!$B$19,"Tier 2","Tier 3"))
A45: bank:57974 | B45: California International Bank, N.A. | C45: Westminster | D45: Orange | E45: www.cali.bank | F45: 120.902 | G45: 105.911 | H45: 83.635 | I45: 1.888 | J45: =IF(G45=0,"",H45/G45) | K45: 0.27488379 | L45: 0.13514018 | M45: =IF(H45=0,"",I45/H45) | N45: 1.5112629 | O45: 0.68715253 | P45: 0.38150614 | Q45: =IF(OR(O45="",P45=""),"",O45-P45) | X45: No HMDA mortgage reporting | Y45: =ROUND(100*(Scoring!$B$4*(1-IFERROR(PERCENTRANK($J$2:$J$46,J45),0.5))+Scoring!$B$5*IFERROR(PERCENTRANK($K$2:$K$46,K45),0.5)+Scoring!$B$6*IFERROR(PERCENTRANK($L$2:$L$46,L45),0.5)+Scoring!$B$7*IFERROR(PERCENTRANK($Q$2:$Q$46,Q45),0.5)+Scoring!$B$8*IFERROR(PERCENTRANK($N$2:$N$46,N45),0.5)+Scoring!$B$9*(1-IFERROR(PERCENTRANK($M$2:$M$46,M45),0.5))),0) | Z45: =IF(AND(Y45>=Scoring!$B$18,F45>=Scoring!$B$20,X45<>"Already takes broker loans"),"Tier 1",IF(Y45>=Scoring!$B$19,"Tier 2","Tier 3"))
A46: bank:59204 | B46: Legacy Bank | C46: Murrieta | D46: Riverside | E46: https://www.legacybankca.com | F46: 112.785 | G46: 101.597 | H46: 76.995 | I46: 0 | J46: =IF(G46=0,"",H46/G46) | K46: 0.19176309 | L46: 0.082923348 | M46: =IF(H46=0,"",I46/H46) | N46: 1.2658059 | O46: 0.39702162 | P46: 0.082545976 | Q46: =IF(OR(O46="",P46=""),"",O46-P46) | X46: No HMDA mortgage reporting | Y46: =ROUND(100*(Scoring!$B$4*(1-IFERROR(PERCENTRANK($J$2:$J$46,J46),0.5))+Scoring!$B$5*IFERROR(PERCENTRANK($K$2:$K$46,K46),0.5)+Scoring!$B$6*IFERROR(PERCENTRANK($L$2:$L$46,L46),0.5)+Scoring!$B$7*IFERROR(PERCENTRANK($Q$2:$Q$46,Q46),0.5)+Scoring!$B$8*IFERROR(PERCENTRANK($N$2:$N$46,N46),0.5)+Scoring!$B$9*(1-IFERROR(PERCENTRANK($M$2:$M$46,M46),0.5))),0) | Z46: =IF(AND(Y46>=Scoring!$B$18,F46>=Scoring!$B$20,X46<>"Already takes broker loans"),"Tier 1",IF(Y46>=Scoring!$B$19,"Tier 2","Tier 3"))

Sheet Credit Unions
A1: Key | B1: Institution | C1: City | D1: County | E1: Total assets ($M) | F1: Shares/deposits ($M) | G1: Total loans ($M) | H1: 1st-lien 1-4 family loans ($M) | I1: Loan-to-share | J1: Liquidity (cash+inv / assets) | K1: Net worth ratio | L1: 1st mtg % of loans | M1: 1st mtg originated YTD ($M) | N1: Annualized originations / assets | O1: 1st mtg sold YTD ($M) | P1: Share growth YoY | Q1: Loan growth YoY | R1: Funding gap (share g - loan g) | S1: HMDA 2025 originations (#) | T1: HMDA 2025 volume ($M) | U1: % kept in portfolio | V1: Non-QM-feature loans (IO/balloon/non-amort.) | W1: Investor / business-purpose loans | X1: Broker-channel share | Y1: Wholesale status | Z1: Capacity score | AA1: Tier | AB1: CEO / contact (fill in) | AC1: Notes (fill in)
A2: cu:1999 | B2: Logix CU | C2: Valencia | D2: Los Angeles | E2: 9687.8049 | F2: 8130.6756 | G2: 7759.7516 | H2: 3850.703 | I2: =IF(F2=0,"",G2/F2) | J2: 0.17708249 | K2: 0.1567 | L2: =IF(G2=0,"",H2/G2) | M2: 181.59677 | N2: =IF(E2=0,"",2*M2/E2) | O2: 17.745831 | P2: 0.035645613 | Q2: 0.0093343985 | R2: =IF(OR(P2="",Q2=""),"",P2-Q2) | S2: 900 | T2: 304.05 | U2: 0.9 | V2: 44 | W2: 65 | X2: 0 | Y2: Retail only | Z2: =ROUND(100*(Scoring!$B$11*(1-IFERROR(PERCENTRANK($I$2:$I$67,I2),0.5))+Scoring!$B$12*IFERROR(PERCENTRANK($J$2:$J$67,J2),0.5)+Scoring!$B$13*IFERROR(PERCENTRANK($K$2:$K$67,K2),0.5)+Scoring!$B$14*IFERROR(PERCENTRANK($R$2:$R$67,R2),0.5)+Scoring!$B$15*(1-IFERROR(PERCENTRANK($N$2:$N$67,N2),0.5))+Scoring!$B$16*(1-IFERROR(PERCENTRANK($L$2:$L$67,L2),0.5))),0) | AA2: =IF(AND(Z2>=Scoring!$B$18,E2>=Scoring!$B$20,Y2<>"Already takes broker loans"),"Tier 1",IF(Z2>=Scoring!$B$19,"Tier 2","Tier 3"))
A3: cu:4142 | B3: Kinecta CU | C3: Manhattan Beach | D3: Los Angeles | E3: 6770.4256 | F3: 5652.3562 | G3: 5345.3247 | H3: 3170.2609 | I3: =IF(F3=0,"",G3/F3) | J3: 0.15501279 | K3: 0.0868 | L3: =IF(G3=0,"",H3/G3) | M3: 145.68577 | N3: =IF(E3=0,"",2*M3/E3) | O3: 15.897076 | P3: 0.049661799 | Q3: -0.020851918 | R3: =IF(OR(P3="",Q3=""),"",P3-Q3) | S3: 238 | T3: 108.67 | U3: 0.99579832 | V3: 0 | W3: 6 | X3: 0 | Y3: Retail only | Z3: =ROUND(100*(Scoring!$B$11*(1-IFERROR(PERCENTRANK($I$2:$I$67,I3),0.5))+Scoring!$B$12*IFERROR(PERCENTRANK($J$2:$J$67,J3),0.5)+Scoring!$B$13*IFERROR(PERCENTRANK($K$2:$K$67,K3),0.5)+Scoring!$B$14*IFERROR(PERCENTRANK($R$2:$R$67,R3),0.5)+Scoring!$B$15*(1-IFERROR(PERCENTRANK($N$2:$N$67,N3),0.5))+Scoring!$B$16*(1-IFERROR(PERCENTRANK($L$2:$L$67,L3),0.5))),0) | AA3: =IF(AND(Z3>=Scoring!$B$18,E3>=Scoring!$B$20,Y3<>"Already takes broker loans"),"Tier 1",IF(Z3>=Scoring!$B$19,"Tier 2","Tier 3"))
A4: cu:66703 | B4: Wescom Central CU | C4: Pasadena | D4: Los Angeles | E4: 6600.2649 | F4: 4346.904 | G4: 3507.5016 | H4: 1769.1062 | I4: =IF(F4=0,"",G4/F4) | J4: 0.40220541 | K4: 0.079 | L4: =IF(G4=0,"",H4/G4) | M4: 56.547598 | N4: =IF(E4=0,"",2*M4/E4) | O4: 7.8082 | P4: -0.042322537 | Q4: 0.032633791 | R4: =IF(OR(P4="",Q4=""),"",P4-Q4) | S4: 188 | T4: 114.85 | U4: 0.78191489 | V4: 0 | W4: 28 | X4: 0.0053191489 | Y4: Mostly retail, a few broker loans | Z4: =ROUND(100*(Scoring!$B$11*(1-IFERROR(PERCENTRANK($I$2:$I$67,I4),0.5))+Scoring!$B$12*IFERROR(PERCENTRANK($J$2:$J$67,J4),0.5)+Scoring!$B$13*IFERROR(PERCENTRANK($K$2:$K$67,K4),0.5)+Scoring!$B$14*IFERROR(PERCENTRANK($R$2:$R$67,R4),0.5)+Scoring!$B$15*(1-IFERROR(PERCENTRANK($N$2:$N$67,N4),0.5))+Scoring!$B$16*(1-IFERROR(PERCENTRANK($L$2:$L$67,L4),0.5))),0) | AA4: =IF(AND(Z4>=Scoring!$B$18,E4>=Scoring!$B$20,Y4<>"Already takes broker loans"),"Tier 1",IF(Z4>=Scoring!$B$19,"Tier 2","Tier 3"))
A5: cu:24980 | B5: California CU | C5: Glendale | D5: Los Angeles | E5: 5426.1619 | F5: 4865.2693 | G5: 3550.6202 | H5: 2056.3453 | I5: =IF(F5=0,"",G5/F5) | J5: 0.29575893 | K5: 0.0941 | L5: =IF(G5=0,"",H5/G5) | M5: 274.24487 | N5: =IF(E5=0,"",2*M5/E5) | O5: 0 | R5: =IF(OR(P5="",Q5=""),"",P5-Q5) | S5: 669 | T5: 505.565 | U5: 0.93721973 | V5: 1 | W5: 14 | X5: 0 | Y5: Retail only | Z5: =ROUND(100*(Scoring!$B$11*(1-IFERROR(PERCENTRANK($I$2:$I$67,I5),0.5))+Scoring!$B$12*IFERROR(PERCENTRANK($J$2:$J$67,J5),0.5)+Scoring!$B$13*IFERROR(PERCENTRANK($K$2:$K$67,K5),0.5)+Scoring!$B$14*IFERROR(PERCENTRANK($R$2:$R$67,R5),0.5)+Scoring!$B$15*(1-IFERROR(PERCENTRANK($N$2:$N$67,N5),0.5))+Scoring!$B$16*(1-IFERROR(PERCENTRANK($L$2:$L$67,L5),0.5))),0) | AA5: =IF(AND(Z5>=Scoring!$B$18,E5>=Scoring!$B$20,Y5<>"Already takes broker loans"),"Tier 1",IF(Z5>=Scoring!$B$19,"Tier 2","Tier 3"))
A6: cu:24983 | B6: Credit Union of Southern California | C6: Anaheim | D6: Orange | E6: 4006.0962 | F6: 3062.5438 | G6: 2136.434 | H6: 793.71909 | I6: =IF(F6=0,"",G6/F6) | J6: 0.42885477 | K6: 0.113 | L6: =IF(G6=0,"",H6/G6) | M6: 46.973572 | N6: =IF(E6=0,"",2*M6/E6) | O6: 0.35 | R6: =IF(OR(P6="",Q6=""),"",P6-Q6) | S6: 322 | T6: 161.93 | U6: 0.99689441 | V6: 97 | W6: 52 | X6: 0 | Y6: Retail only | Z6: =ROUND(100*(Scoring!$B$11*(1-IFERROR(PERCENTRANK($I$2:$I$67,I6),0.5))+Scoring!$B$12*IFERROR(PERCENTRANK($J$2:$J$67,J6),0.5)+Scoring!$B$13*IFERROR(PERCENTRANK($K$2:$K$67,K6),0.5)+Scoring!$B$14*IFERROR(PERCENTRANK($R$2:$R$67,R6),0.5)+Scoring!$B$15*(1-IFERROR(PERCENTRANK($N$2:$N$67,N6),0.5))+Scoring!$B$16*(1-IFERROR(PERCENTRANK($L$2:$L$67,L6),0.5))),0) | AA6: =IF(AND(Z6>=Scoring!$B$18,E6>=Scoring!$B$20,Y6<>"Already takes broker loans"),"Tier 1",IF(Z6>=Scoring!$B$19,"Tier 2","Tier 3"))
A7: cu:566 | B7: Nuvision CU | C7: Huntington Beac | D7: Orange | E7: 3968.5928 | F7: 3326.9566 | G7: 3133.4856 | H7: 1309.7692 | I7: =IF(F7=0,"",G7/F7) | J7: 0.173854 | K7: 0.1203 | L7: =IF(G7=0,"",H7/G7) | M7: 138.88196 | N7: =IF(E7=0,"",2*M7/E7) | O7: 15.661999 | P7: 0.02904111 | Q7: 0.019737285 | R7: =IF(OR(P7="",Q7=""),"",P7-Q7) | S7: 403 | T7: 256.425 | U7: 0.81141439 | V7: 33 | W7: 30 | X7: 0.16129032 | Y7: Already takes broker loans | Z7: =ROUND(100*(Scoring!$B$11*(1-IFERROR(PERCENTRANK($I$2:$I$67,I7),0.5))+Scoring!$B$12*IFERROR(PERCENTRANK($J$2:$J$67,J7),0.5)+Scoring!$B$13*IFERROR(PERCENTRANK($K$2:$K$67,K7),0.5)+Scoring!$B$14*IFERROR(PERCENTRANK($R$2:$R$67,R7),0.5)+Scoring!$B$15*(1-IFERROR(PERCENTRANK($N$2:$N$67,N7),0.5))+Scoring!$B$16*(1-IFERROR(PERCENTRANK($L$2:$L$67,L7),0.5))),0) | AA7: =IF(AND(Z7>=Scoring!$B$18,E7>=Scoring!$B$20,Y7<>"Already takes broker loans"),"Tier 1",IF(Z7>=Scoring!$B$19,"Tier 2","Tier 3"))
A8: cu:68428 | B8: Premier America CU | C8: Chatsworth | D8: Los Angeles | E8: 3319.448 | F8: 2996.4645 | G8: 2610.5221 | H8: 1674.9993 | I8: =IF(F8=0,"",G8/F8) | J8: 0.18932101 | K8: 0.0949 | L8: =IF(G8=0,"",H8/G8) | M8: 64.864361 | N8: =IF(E8=0,"",2*M8/E8) | O8: 0.815333 | P8: 0.015769041 | Q8: -0.052090211 | R8: =IF(OR(P8="",Q8=""),"",P8-Q8) | S8: 146 | T8: 49.14 | U8: 1 | V8: 0 | W8: 9 | X8: 0 | Y8: Retail only | Z8: =ROUND(100*(Scoring!$B$11*(1-IFERROR(PERCENTRANK($I$2:$I$67,I8),0.5))+Scoring!$B$12*IFERROR(PERCENTRANK($J$2:$J$67,J8),0.5)+Scoring!$B$13*IFERROR(PERCENTRANK($K$2:$K$67,K8),0.5)+Scoring!$B$14*IFERROR(PERCENTRANK($R$2:$R$67,R8),0.5)+Scoring!$B$15*(1-IFERROR(PERCENTRANK($N$2:$N$67,N8),0.5))+Scoring!$B$16*(1-IFERROR(PERCENTRANK($L$2:$L$67,L8),0.5))),0) | AA8: =IF(AND(Z8>=Scoring!$B$18,E8>=Scoring!$B$20,Y8<>"Already takes broker loans"),"Tier 1",IF(Z8>=Scoring!$B$19,"Tier 2","Tier 3"))
A9: cu:1493 | B9: F&A CU | C9: Monterey Park | D9: Los Angeles | E9: 3153.7764 | F9: 2062.8378 | G9: 1229.4468 | H9: 673.22855 | I9: =IF(F9=0,"",G9/F9) | J9: 0.57533297 | K9: 0.1259 | L9: =IF(G9=0,"",H9/G9) | M9: 71.934805 | N9: =IF(E9=0,"",2*M9/E9) | O9: 0 | P9: 0.060422778 | Q9: 0.052758074 | R9: =IF(OR(P9="",Q9=""),"",P9-Q9) | S9: 290 | T9: 100.11 | U9: 1 | V9: 8 | W9: 13 | X9: 0 | Y9: Retail only | Z9: =ROUND(100*(Scoring!$B$11*(1-IFERROR(PERCENTRANK($I$2:$I$67,I9),0.5))+Scoring!$B$12*IFERROR(PERCENTRANK($J$2:$J$67,J9),0.5)+Scoring!$B$13*IFERROR(PERCENTRANK($K$2:$K$67,K9),0.5)+Scoring!$B$14*IFERROR(PERCENTRANK($R$2:$R$67,R9),0.5)+Scoring!$B$15*(1-IFERROR(PERCENTRANK($N$2:$N$67,N9),0.5))+Scoring!$B$16*(1-IFERROR(PERCENTRANK($L$2:$L$67,L9),0.5))),0) | AA9: =IF(AND(Z9>=Scoring!$B$18,E9>=Scoring!$B$20,Y9<>"Already takes broker loans"),"Tier 1",IF(Z9>=Scoring!$B$19,"Tier 2","Tier 3"))
A10: cu:24981 | B10: Orange County's CU | C10: Santa Ana | D10: Orange | E10: 3079.7965 | F10: 2553.7535 | G10: 2416.9868 | H10: 759.28859 | I10: =IF(F10=0,"",G10/F10) | J10: 0.180252 | K10: 0.1066 | L10: =IF(G10=0,"",H10/G10) | M10: 52.881296 | N10: =IF(E10=0,"",2*M10/E10) | O10: 5.258023 | R10: =IF(OR(P10="",Q10=""),"",P10-Q10) | S10: 575 | T10: 153.615 | U10: 0.96 | V10: 11 | W10: 16 | X10: 0 | Y10: Retail only | Z10: =ROUND(100*(Scoring!$B$11*(1-IFERROR(PERCENTRANK($I$2:$I$67,I10),0.5))+Scoring!$B$12*IFERROR(PERCENTRANK($J$2:$J$67,J10),0.5)+Scoring!$B$13*IFERROR(PERCENTRANK($K$2:$K$67,K10),0.5)+Scoring!$B$14*IFERROR(PERCENTRANK($R$2:$R$67,R10),0.5)+Scoring!$B$15*(1-IFERROR(PERCENTRANK($N$2:$N$67,N10),0.5))+Scoring!$B$16*(1-IFERROR(PERCENTRANK($L$2:$L$67,L10),0.5))),0) | AA10: =IF(AND(Z10>=Scoring!$B$18,E10>=Scoring!$B$20,Y10<>"Already takes broker loans"),"Tier 1",IF(Z10>=Scoring!$B$19,"Tier 2","Tier 3"))
A11: cu:24973 | B11: Arrowhead CU | C11: Rancho Cucamong | D11: San Bernardino | E11: 2925.6418 | F11: 2421.8463 | G11: 1448.33 | H11: 150.15081 | I11: =IF(F11=0,"",G11/F11) | J11: 0.46173316 | K11: 0.1136 | L11: =IF(G11=0,"",H11/G11) | M11: 27.459588 | N11: =IF(E11=0,"",2*M11/E11) | O11: 0.0785 | P11: 0.079813288 | Q11: 0.018314174 | R11: =IF(OR(P11="",Q11=""),"",P11-Q11) | S11: 458 | T11: 74.53 | U11: 0.73362445 | V11: 1 | W11: 13 | X11: 0.26637555 | Y11: Already takes broker loans | Z11: =ROUND(100*(Scoring!$B$11*(1-IFERROR(PERCENTRANK($I$2:$I$67,I11),0.5))+Scoring!$B$12*IFERROR(PERCENTRANK($J$2:$J$67,J11),0.5)+Scoring!$B$13*IFERROR(PERCENTRANK($K$2:$K$67,K11),0.5)+Scoring!$B$14*IFERROR(PERCENTRANK($R$2:$R$67,R11),0.5)+Scoring!$B$15*(1-IFERROR(PERCENTRANK($N$2:$N$67,N11),0.5))+Scoring!$B$16*(1-IFERROR(PERCENTRANK($L$2:$L$67,L11),0.5))),0) | AA11: =IF(AND(Z11>=Scoring!$B$18,E11>=Scoring!$B$20,Y11<>"Already takes broker loans"),"Tier 1",IF(Z11>=Scoring!$B$19,"Tier 2","Tier 3"))
A12: cu:18708 | B12: Partners CU | C12: Burbank | D12: Los Angeles | E12: 2766.0478 | F12: 2411.907 | G12: 2203.2951 | H12: 1163.7877 | I12: =IF(F12=0,"",G12/F12) | J12: 0.18542849 | K12: 0.1174 | L12: =IF(G12=0,"",H12/G12) | M12: 106.52806 | N12: =IF(E12=0,"",2*M12/E12) | O12: 0 | P12: 0.038377893 | Q12: 0.038672136 | R12: =IF(OR(P12="",Q12=""),"",P12-Q12) | Y12: No HMDA mortgage reporting | Z12: =ROUND(100*(Scoring!$B$11*(1-IFERROR(PERCENTRANK($I$2:$I$67,I12),0.5))+Scoring!$B$12*IFERROR(PERCENTRANK($J$2:$J$67,J12),0.5)+Scoring!$B$13*IFERROR(PERCENTRANK($K$2:$K$67,K12),0.5)+Scoring!$B$14*IFERROR(PERCENTRANK($R$2:$R$67,R12),0.5)+Scoring!$B$15*(1-IFERROR(PERCENTRANK($N$2:$N$67,N12),0.5))+Scoring!$B$16*(1-IFERROR(PERCENTRANK($L$2:$L$67,L12),0.5))),0) | AA12: =IF(AND(Z12>=Scoring!$B$18,E12>=Scoring!$B$20,Y12<>"Already takes broker loans"),"Tier 1",IF(Z12>=Scoring!$B$19,"Tier 2","Tier 3"))
A13: cu:24969 | B13: Altura CU | C13: Riverside | D13: Riverside | E13: 2645.8924 | F13: 2365.623 | G13: 1775.3253 | H13: 555.63 | I13: =IF(F13=0,"",G13/F13) | J13: 0.28453986 | K13: 0.1117 | L13: =IF(G13=0,"",H13/G13) | M13: 73.392449 | N13: =IF(E13=0,"",2*M13/E13) | O13: 1.376115 | P13: 0.035970594 | Q13: 0.038505645 | R13: =IF(OR(P13="",Q13=""),"",P13-Q13) | S13: 234 | T13: 74.37 | U13: 0.9957265 | V13: 3 | W13: 13 | X13: 0.042735043 | Y13: Mostly retail, a few broker loans | Z13: =ROUND(100*(Scoring!$B$11*(1-IFERROR(PERCENTRANK($I$2:$I$67,I13),0.5))+Scoring!$B$12*IFERROR(PERCENTRANK($J$2:$J$67,J13),0.5)+Scoring!$B$13*IFERROR(PERCENTRANK($K$2:$K$67,K13),0.5)+Scoring!$B$14*IFERROR(PERCENTRANK($R$2:$R$67,R13),0.5)+Scoring!$B$15*(1-IFERROR(PERCENTRANK($N$2:$N$67,N13),0.5))+Scoring!$B$16*(1-IFERROR(PERCENTRANK($L$2:$L$67,L13),0.5))),0) | AA13: =IF(AND(Z13>=Scoring!$B$18,E13>=Scoring!$B$20,Y13<>"Already takes broker loans"),"Tier 1",IF(Z13>=Scoring!$B$19,"Tier 2","Tier 3"))
A14: cu:24877 | B14: Firefighters First CU | C14: Los Angeles | D14: Los Angeles | E14: 2479.2055 | F14: 2219.0329 | G14: 2107.6732 | H14: 927.70816 | I14: =IF(F14=0,"",G14/F14) | J14: 0.10776005 | K14: 0.0939 | L14: =IF(G14=0,"",H14/G14) | M14: 129.49644 | N14: =IF(E14=0,"",2*M14/E14) | O14: 8.67295 | P14: 0.063398931 | Q14: 0.11469309 | R14: =IF(OR(P14="",Q14=""),"",P14-Q14) | S14: 443 | T14: 175.735 | U14: 1 | V14: 68 | W14: 66 | X14: 0 | Y14: Retail only | Z14: =ROUND(100*(Scoring!$B$11*(1-IFERROR(PERCENTRANK($I$2:$I$67,I14),0.5))+Scoring!$B$12*IFERROR(PERCENTRANK($J$2:$J$67,J14),0.5)+Scoring!$B$13*IFERROR(PERCENTRANK($K$2:$K$67,K14),0.5)+Scoring!$B$14*IFERROR(PERCENTRANK($R$2:$R$67,R14),0.5)+Scoring!$B$15*(1-IFERROR(PERCENTRANK($N$2:$N$67,N14),0.5))+Scoring!$B$16*(1-IFERROR(PERCENTRANK($L$2:$L$67,L14),0.5))),0) | AA14: =IF(AND(Z14>=Scoring!$B$18,E14>=Scoring!$B$20,Y14<>"Already takes broker loans"),"Tier 1",IF(Z14>=Scoring!$B$19,"Tier 2","Tier 3"))
A15: cu:68460 | B15: LBS Financial CU | C15: Long Beach | D15: Orange | E15: 2208.2406 | F15: 1907.0225 | G15: 1173.7313 | H15: 290.54828 | I15: =IF(F15=0,"",G15/F15) | J15: 0.41851672 | K15: 0.1311 | L15: =IF(G15=0,"",H15/G15) | M15: 26.480856 | N15: =IF(E15=0,"",2*M15/E15) | O15: 1.7625 | P15: 0.047395351 | Q15: 0.05280734 | R15: =IF(OR(P15="",Q15=""),"",P15-Q15) | S15: 177 | T15: 74.565 | U15: 0.93220339 | V15: 0 | W15: 0 | X15: 0 | Y15: Retail only | Z15: =ROUND(100*(Scoring!$B$11*(1-IFERROR(PERCENTRANK($I$2:$I$67,I15),0.5))+Scoring!$B$12*IFERROR(PERCENTRANK($J$2:$J$67,J15),0.5)+Scoring!$B$13*IFERROR(PERCENTRANK($K$2:$K$67,K15),0.5)+Scoring!$B$14*IFERROR(PERCENTRANK($R$2:$R$67,R15),0.5)+Scoring!$B$15*(1-IFERROR(PERCENTRANK($N$2:$N$67,N15),0.5))+Scoring!$B$16*(1-IFERROR(PERCENTRANK($L$2:$L$67,L15),0.5))),0) | AA15: =IF(AND(Z15>=Scoring!$B$18,E15>=Scoring!$B$20,Y15<>"Already takes broker loans"),"Tier 1",IF(Z15>=Scoring!$B$19,"Tier 2","Tier 3"))
A16: cu:68457 | B16: Financial Partners CU | C16: Downey | D16: Los Angeles | E16: 2190.4659 | F16: 1757.6551 | G16: 1582.1998 | H16: 709.55503 | I16: =IF(F16=0,"",G16/F16) | J16: 0.17309325 | K16: 0.095 | L16: =IF(G16=0,"",H16/G16) | M16: 51.37125 | N16: =IF(E16=0,"",2*M16/E16) | O16: 16.9649 | P16: -0.019150339 | Q16: -0.098161301 | R16: =IF(OR(P16="",Q16=""),"",P16-Q16) | S16: 209 | T16: 97.095 | U16: 0.70813397 | V16: 2 | W16: 20 | X16: 0 | Y16: Retail only | Z16: =ROUND(100*(Scoring!$B$11*(1-IFERROR(PERCENTRANK($I$2:$I$67,I16),0.5))+Scoring!$B$12*IFERROR(PERCENTRANK($J$2:$J$67,J16),0.5)+Scoring!$B$13*IFERROR(PERCENTRANK($K$2:$K$67,K16),0.5)+Scoring!$B$14*IFERROR(PERCENTRANK($R$2:$R$67,R16),0.5)+Scoring!$B$15*(1-IFERROR(PERCENTRANK($N$2:$N$67,N16),0.5))+Scoring!$B$16*(1-IFERROR(PERCENTRANK($L$2:$L$67,L16),0.5))),0) | AA16: =IF(AND(Z16>=Scoring!$B$18,E16>=Scoring!$B$20,Y16<>"Already takes broker loans"),"Tier 1",IF(Z16>=Scoring!$B$19,"Tier 2","Tier 3"))
A17: cu:68373 | B17: First Entertainment CU | C17: Hollywood | D17: Los Angeles | E17: 2114.9809 | F17: 1744.1272 | G17: 1452.5349 | H17: 785.04386 | I17: =IF(F17=0,"",G17/F17) | J17: 0.27442777 | K17: 0.1014 | L17: =IF(G17=0,"",H17/G17) | M17: 49.880902 | N17: =IF(E17=0,"",2*M17/E17) | O17: 0 | P17: 0.010617269 | Q17: 0.0039905937 | R17: =IF(OR(P17="",Q17=""),"",P17-Q17) | S17: 196 | T17: 91.81 | U17: 0.98979592 | V17: 0 | W17: 7 | X17: 0 | Y17: Retail only | Z17: =ROUND(100*(Scoring!$B$11*(1-IFERROR(PERCENTRANK($I$2:$I$67,I17),0.5))+Scoring!$B$12*IFERROR(PERCENTRANK($J$2:$J$67,J17),0.5)+Scoring!$B$13*IFERROR(PERCENTRANK($K$2:$K$67,K17),0.5)+Scoring!$B$14*IFERROR(PERCENTRANK($R$2:$R$67,R17),0.5)+Scoring!$B$15*(1-IFERROR(PERCENTRANK($N$2:$N$67,N17),0.5))+Scoring!$B$16*(1-IFERROR(PERCENTRANK($L$2:$L$67,L17),0.5))),0) | AA17: =IF(AND(Z17>=Scoring!$B$18,E17>=Scoring!$B$20,Y17<>"Already takes broker loans"),"Tier 1",IF(Z17>=Scoring!$B$19,"Tier 2","Tier 3"))
A18: cu:6681 | B18: Caltech Employees CU | C18: La Canada | D18: Los Angeles | E18: 2096.4318 | F18: 1578.7824 | G18: 705.45033 | H18: 513.12925 | I18: =IF(F18=0,"",G18/F18) | J18: 0.64898528 | K18: 0.1008 | L18: =IF(G18=0,"",H18/G18) | M18: 73.012425 | N18: =IF(E18=0,"",2*M18/E18) | O18: 0 | P18: -0.019389788 | Q18: 0.14033643 | R18: =IF(OR(P18="",Q18=""),"",P18-Q18) | S18: 148 | T18: 96.42 | U18: 1 | V18: 0 | W18: 4 | X18: 0.013513514 | Y18: Mostly retail, a few broker loans | Z18: =ROUND(100*(Scoring!$B$11*(1-IFERROR(PERCENTRANK($I$2:$I$67,I18),0.5))+Scoring!$B$12*IFERROR(PERCENTRANK($J$2:$J$67,J18),0.5)+Scoring!$B$13*IFERROR(PERCENTRANK($K$2:$K$67,K18),0.5)+Scoring!$B$14*IFERROR(PERCENTRANK($R$2:$R$67,R18),0.5)+Scoring!$B$15*(1-IFERROR(PERCENTRANK($N$2:$N$67,N18),0.5))+Scoring!$B$16*(1-IFERROR(PERCENTRANK($L$2:$L$67,L18),0.5))),0) | AA18: =IF(AND(Z18>=Scoring!$B$18,E18>=Scoring!$B$20,Y18<>"Already takes broker loans"),"Tier 1",IF(Z18>=Scoring!$B$19,"Tier 2","Tier 3"))
A19: cu:24292 | B19: Northrop Grumman CU | C19: Gardena | D19: Los Angeles | E19: 1645.4088 | F19: 1483.8548 | G19: 827.90169 | H19: 236.29395 | I19: =IF(F19=0,"",G19/F19) | J19: 0.45294065 | K19: 0.0908 | L19: =IF(G19=0,"",H19/G19) | M19: 21.092204 | N19: =IF(E19=0,"",2*M19/E19) | O19: 17.012921 | P19: 0.029959639 | Q19: -0.012344803 | R19: =IF(OR(P19="",Q19=""),"",P19-Q19) | S19: 254 | T19: 69 | U19: 1 | V19: 0 | W19: 14 | X19: 0.0039370079 | Y19: Mostly retail, a few broker loans | Z19: =ROUND(100*(Scoring!$B$11*(1-IFERROR(PERCENTRANK($I$2:$I$67,I19),0.5))+Scoring!$B$12*IFERROR(PERCENTRANK($J$2:$J$67,J19),0.5)+Scoring!$B$13*IFERROR(PERCENTRANK($K$2:$K$67,K19),0.5)+Scoring!$B$14*IFERROR(PERCENTRANK($R$2:$R$67,R19),0.5)+Scoring!$B$15*(1-IFERROR(PERCENTRANK($N$2:$N$67,N19),0.5))+Scoring!$B$16*(1-IFERROR(PERCENTRANK($L$2:$L$67,L19),0.5))),0) | AA19: =IF(AND(Z19>=Scoring!$B$18,E19>=Scoring!$B$20,Y19<>"Already takes broker loans"),"Tier 1",IF(Z19>=Scoring!$B$19,"Tier 2","Tier 3"))
A20: cu:97068 | B20: Adelfi CU | C20: San Dimas | D20: Los Angeles | E20: 1421.3494 | F20: 1214.6277 | G20: 1027.2949 | H20: 256.98307 | I20: =IF(F20=0,"",G20/F20) | J20: 0.23548726 | K20: 0.1285 | L20: =IF(G20=0,"",H20/G20) | M20: 10.24934 | N20: =IF(E20=0,"",2*M20/E20) | O20: 0 | P20: 0.58180434 | Q20: 0.43351914 | R20: =IF(OR(P20="",Q20=""),"",P20-Q20) | Y20: No HMDA mortgage reporting | Z20: =ROUND(100*(Scoring!$B$11*(1-IFERROR(PERCENTRANK($I$2:$I$67,I20),0.5))+Scoring!$B$12*IFERROR(PERCENTRANK($J$2:$J$67,J20),0.5)+Scoring!$B$13*IFERROR(PERCENTRANK($K$2:$K$67,K20),0.5)+Scoring!$B$14*IFERROR(PERCENTRANK($R$2:$R$67,R20),0.5)+Scoring!$B$15*(1-IFERROR(PERCENTRANK($N$2:$N$67,N20),0.5))+Scoring!$B$16*(1-IFERROR(PERCENTRANK($L$2:$L$67,L20),0.5))),0) | AA20: =IF(AND(Z20>=Scoring!$B$18,E20>=Scoring!$B$20,Y20<>"Already takes broker loans"),"Tier 1",IF(Z20>=Scoring!$B$19,"Tier 2","Tier 3"))
A21: cu:24553 | B21: Los Angeles Police CU | C21: Van Nuys | D21: Los Angeles | E21: 1387.365 | F21: 1249.6244 | G21: 757.56982 | H21: 331.56854 | I21: =IF(F21=0,"",G21/F21) | J21: 0.42242033 | K21: 0.1132 | L21: =IF(G21=0,"",H21/G21) | M21: 9.645763 | N21: =IF(E21=0,"",2*M21/E21) | O21: 3.340436 | P21: 0.030138635 | Q21: -0.0012194139 | R21: =IF(OR(P21="",Q21=""),"",P21-Q21) | S21: 230 | T21: 44.51 | U21: 0.93043478 | W21: 19 | Y21: Unknown (small filer, channel not reported) | Z21: =ROUND(100*(Scoring!$B$11*(1-IFERROR(PERCENTRANK($I$2:$I$67,I21),0.5))+Scoring!$B$12*IFERROR(PERCENTRANK($J$2:$J$67,J21),0.5)+Scoring!$B$13*IFERROR(PERCENTRANK($K$2:$K$67,K21),0.5)+Scoring!$B$14*IFERROR(PERCENTRANK($R$2:$R$67,R21),0.5)+Scoring!$B$15*(1-IFERROR(PERCENTRANK($N$2:$N$67,N21),0.5))+Scoring!$B$16*(1-IFERROR(PERCENTRANK($L$2:$L$67,L21),0.5))),0) | AA21: =IF(AND(Z21>=Scoring!$B$18,E21>=Scoring!$B$20,Y21<>"Already takes broker loans"),"Tier 1",IF(Z21>=Scoring!$B$19,"Tier 2","Tier 3"))
A22: cu:68485 | B22: American First CU | C22: Brea | D22: Orange | E22: 1369.2155 | F22: 1181.119 | G22: 1164.0291 | H22: 124.30831 | I22: =IF(F22=0,"",G22/F22) | J22: 0.089528764 | K22: 0.1009 | L22: =IF(G22=0,"",H22/G22) | M22: 9.151005 | N22: =IF(E22=0,"",2*M22/E22) | O22: 1.428129 | P22: 0.27205061 | Q22: 0.37131845 | R22: =IF(OR(P22="",Q22=""),"",P22-Q22) | S22: 74 | T22: 10.8 | U22: 0.59459459 | V22: 3 | W22: 3 | X22: 0.013513514 | Y22: Mostly retail, a few broker loans | Z22: =ROUND(100*(Scoring!$B$11*(1-IFERROR(PERCENTRANK($I$2:$I$67,I22),0.5))+Scoring!$B$12*IFERROR(PERCENTRANK($J$2:$J$67,J22),0.5)+Scoring!$B$13*IFERROR(PERCENTRANK($K$2:$K$67,K22),0.5)+Scoring!$B$14*IFERROR(PERCENTRANK($R$2:$R$67,R22),0.5)+Scoring!$B$15*(1-IFERROR(PERCENTRANK($N$2:$N$67,N22),0.5))+Scoring!$B$16*(1-IFERROR(PERCENTRANK($L$2:$L$67,L22),0.5))),0) | AA22: =IF(AND(Z22>=Scoring!$B$18,E22>=Scoring!$B$20,Y22<>"Already takes broker loans"),"Tier 1",IF(Z22>=Scoring!$B$19,"Tier 2","Tier 3"))
A23: cu:1074 | B23: Farmers Insurance CU | C23: Los Angeles | D23: Los Angeles | E23: 1329.8904 | F23: 1140.8192 | G23: 1184.6883 | H23: 281.37474 | I23: =IF(F23=0,"",G23/F23) | J23: 0.092477157 | K23: 0.0986 | L23: =IF(G23=0,"",H23/G23) | M23: 36.880178 | N23: =IF(E23=0,"",2*M23/E23) | O23: 5.425564 | P23: -0.057857193 | Q23: -0.048851597 | R23: =IF(OR(P23="",Q23=""),"",P23-Q23) | S23: 309 | T23: 78.395 | U23: 0.9579288 | V23: 0 | W23: 6 | X23: 0 | Y23: Retail only | Z23: =ROUND(100*(Scoring!$B$11*(1-IFERROR(PERCENTRANK($I$2:$I$67,I23),0.5))+Scoring!$B$12*IFERROR(PERCENTRANK($J$2:$J$67,J23),0.5)+Scoring!$B$13*IFERROR(PERCENTRANK($K$2:$K$67,K23),0.5)+Scoring!$B$14*IFERROR(PERCENTRANK($R$2:$R$67,R23),0.5)+Scoring!$B$15*(1-IFERROR(PERCENTRANK($N$2:$N$67,N23),0.5))+Scoring!$B$16*(1-IFERROR(PERCENTRANK($L$2:$L$67,L23),0.5))),0) | AA23: =IF(AND(Z23>=Scoring!$B$18,E23>=Scoring!$B$20,Y23<>"Already takes broker loans"),"Tier 1",IF(Z23>=Scoring!$B$19,"Tier 2","Tier 3"))
A24: cu:68415 | B24: Southland CU | C24: Los Alamitos | D24: Orange | E24: 1308.174 | F24: 1051.5157 | G24: 869.67398 | H24: 308.58727 | I24: =IF(F24=0,"",G24/F24) | J24: 0.28082417 | K24: 0.0856 | L24: =IF(G24=0,"",H24/G24) | M24: 24.609307 | N24: =IF(E24=0,"",2*M24/E24) | O24: 1.0345 | P24: -0.040084173 | Q24: -0.029550575 | R24: =IF(OR(P24="",Q24=""),"",P24-Q24) | S24: 107 | T24: 79.075 | U24: 0.90654206 | V24: 1 | W24: 27 | X24: 0 | Y24: Retail only | Z24: =ROUND(100*(Scoring!$B$11*(1-IFERROR(PERCENTRANK($I$2:$I$67,I24),0.5))+Scoring!$B$12*IFERROR(PERCENTRANK($J$2:$J$67,J24),0.5)+Scoring!$B$13*IFERROR(PERCENTRANK($K$2:$K$67,K24),0.5)+Scoring!$B$14*IFERROR(PERCENTRANK($R$2:$R$67,R24),0.5)+Scoring!$B$15*(1-IFERROR(PERCENTRANK($N$2:$N$67,N24),0.5))+Scoring!$B$16*(1-IFERROR(PERCENTRANK($L$2:$L$67,L24),0.5))),0) | AA24: =IF(AND(Z24>=Scoring!$B$18,E24>=Scoring!$B$20,Y24<>"Already takes broker loans"),"Tier 1",IF(Z24>=Scoring!$B$19,"Tier 2","Tier 3"))
A25: cu:7835 | B25: Rize CU | C25: El Monte | D25: Los Angeles | E25: 1293.7268 | F25: 1055.1285 | G25: 1025.7935 | H25: 135.0799 | I25: =IF(F25=0,"",G25/F25) | J25: 0.16536636 | K25: 0.1039 | L25: =IF(G25=0,"",H25/G25) | M25: 20.614308 | N25: =IF(E25=0,"",2*M25/E25) | O25: 0 | P25: 0.033201383 | Q25: 0.1015216 | R25: =IF(OR(P25="",Q25=""),"",P25-Q25) | S25: 292 | T25: 45.62 | U25: 0.98630137 | W25: 15 | Y25: Unknown (small filer, channel not reported) | Z25: =ROUND(100*(Scoring!$B$11*(1-IFERROR(PERCENTRANK($I$2:$I$67,I25),0.5))+Scoring!$B$12*IFERROR(PERCENTRANK($J$2:$J$67,J25),0.5)+Scoring!$B$13*IFERROR(PERCENTRANK($K$2:$K$67,K25),0.5)+Scoring!$B$14*IFERROR(PERCENTRANK($R$2:$R$67,R25),0.5)+Scoring!$B$15*(1-IFERROR(PERCENTRANK($N$2:$N$67,N25),0.5))+Scoring!$B$16*(1-IFERROR(PERCENTRANK($L$2:$L$67,L25),0.5))),0) | AA25: =IF(AND(Z25>=Scoring!$B$18,E25>=Scoring!$B$20,Y25<>"Already takes broker loans"),"Tier 1",IF(Z25>=Scoring!$B$19,"Tier 2","Tier 3"))
A26: cu:1207 | B26: Los Angeles CU | C26: Glendale | D26: Los Angeles | E26: 1290.8072 | F26: 1147.0291 | G26: 911.79477 | H26: 268.49963 | I26: =IF(F26=0,"",G26/F26) | J26: 0.25662184 | K26: 0.114 | L26: =IF(G26=0,"",H26/G26) | M26: 6.75876 | N26: =IF(E26=0,"",2*M26/E26) | O26: 0 | P26: 0.035977527 | Q26: 0.031174847 | R26: =IF(OR(P26="",Q26=""),"",P26-Q26) | S26: 100 | T26: 27.57 | U26: 1 | V26: 0 | W26: 3 | X26: 0 | Y26: Retail only | Z26: =ROUND(100*(Scoring!$B$11*(1-IFERROR(PERCENTRANK($I$2:$I$67,I26),0.5))+Scoring!$B$12*IFERROR(PERCENTRANK($J$2:$J$67,J26),0.5)+Scoring!$B$13*IFERROR(PERCENTRANK($K$2:$K$67,K26),0.5)+Scoring!$B$14*IFERROR(PERCENTRANK($R$2:$R$67,R26),0.5)+Scoring!$B$15*(1-IFERROR(PERCENTRANK($N$2:$N$67,N26),0.5))+Scoring!$B$16*(1-IFERROR(PERCENTRANK($L$2:$L$67,L26),0.5))),0) | AA26: =IF(AND(Z26>=Scoring!$B$18,E26>=Scoring!$B$20,Y26<>"Already takes broker loans"),"Tier 1",IF(Z26>=Scoring!$B$19,"Tier 2","Tier 3"))
A27: cu:17623 | B27: Honda CU | C27: Torrance | D27: Los Angeles | E27: 1197.3891 | F27: 1035.2925 | G27: 931.54067 | H27: 435.76692 | I27: =IF(F27=0,"",G27/F27) | J27: 0.19783506 | K27: 0.0929 | L27: =IF(G27=0,"",H27/G27) | M27: 25.933699 | N27: =IF(E27=0,"",2*M27/E27) | O27: 0 | P27: 0.0034778364 | Q27: 0.042867636 | R27: =IF(OR(P27="",Q27=""),"",P27-Q27) | Y27: No HMDA mortgage reporting | Z27: =ROUND(100*(Scoring!$B$11*(1-IFERROR(PERCENTRANK($I$2:$I$67,I27),0.5))+Scoring!$B$12*IFERROR(PERCENTRANK($J$2:$J$67,J27),0.5)+Scoring!$B$13*IFERROR(PERCENTRANK($K$2:$K$67,K27),0.5)+Scoring!$B$14*IFERROR(PERCENTRANK($R$2:$R$67,R27),0.5)+Scoring!$B$15*(1-IFERROR(PERCENTRANK($N$2:$N$67,N27),0.5))+Scoring!$B$16*(1-IFERROR(PERCENTRANK($L$2:$L$67,L27),0.5))),0) | AA27: =IF(AND(Z27>=Scoring!$B$18,E27>=Scoring!$B$20,Y27<>"Already takes broker loans"),"Tier 1",IF(Z27>=Scoring!$B$19,"Tier 2","Tier 3"))
A28: cu:64171 | B28: University CU | C28: Los Angeles | D28: Los Angeles | E28: 1170.0948 | F28: 990.86221 | G28: 998.35661 | H28: 441.78243 | I28: =IF(F28=0,"",G28/F28) | J28: 0.083832776 | K28: 0.0873 | L28: =IF(G28=0,"",H28/G28) | M28: 19.629928 | N28: =IF(E28=0,"",2*M28/E28) | O28: 5.535767 | P28: 0.013633144 | Q28: 0.023174144 | R28: =IF(OR(P28="",Q28=""),"",P28-Q28) | S28: 58 | T28: 34.05 | U28: 0.60344828 | V28: 0 | W28: 5 | X28: 0 | Y28: Retail only | Z28: =ROUND(100*(Scoring!$B$11*(1-IFERROR(PERCENTRANK($I$2:$I$67,I28),0.5))+Scoring!$B$12*IFERROR(PERCENTRANK($J$2:$J$67,J28),0.5)+Scoring!$B$13*IFERROR(PERCENTRANK($K$2:$K$67,K28),0.5)+Scoring!$B$14*IFERROR(PERCENTRANK($R$2:$R$67,R28),0.5)+Scoring!$B$15*(1-IFERROR(PERCENTRANK($N$2:$N$67,N28),0.5))+Scoring!$B$16*(1-IFERROR(PERCENTRANK($L$2:$L$67,L28),0.5))),0) | AA28: =IF(AND(Z28>=Scoring!$B$18,E28>=Scoring!$B$20,Y28<>"Already takes broker loans"),"Tier 1",IF(Z28>=Scoring!$B$19,"Tier 2","Tier 3"))
A29: cu:68493 | B29: Water and Power Community CU | C29: Los Angeles | D29: Los Angeles | E29: 1020.4243 | F29: 826.15134 | G29: 692.69257 | H29: 373.4213 | I29: =IF(F29=0,"",G29/F29) | J29: 0.28212754 | K29: 0.1019 | L29: =IF(G29=0,"",H29/G29) | M29: 51.739756 | N29: =IF(E29=0,"",2*M29/E29) | O29: 0 | P29: 0.0044185261 | Q29: 0.0044348835 | R29: =IF(OR(P29="",Q29=""),"",P29-Q29) | S29: 182 | T29: 105 | U29: 0.0054945055 | V29: 1 | W29: 10 | X29: 0 | Y29: Retail only | Z29: =ROUND(100*(Scoring!$B$11*(1-IFERROR(PERCENTRANK($I$2:$I$67,I29),0.5))+Scoring!$B$12*IFERROR(PERCENTRANK($J$2:$J$67,J29),0.5)+Scoring!$B$13*IFERROR(PERCENTRANK($K$2:$K$67,K29),0.5)+Scoring!$B$14*IFERROR(PERCENTRANK($R$2:$R$67,R29),0.5)+Scoring!$B$15*(1-IFERROR(PERCENTRANK($N$2:$N$67,N29),0.5))+Scoring!$B$16*(1-IFERROR(PERCENTRANK($L$2:$L$67,L29),0.5))),0) | AA29: =IF(AND(Z29>=Scoring!$B$18,E29>=Scoring!$B$20,Y29<>"Already takes broker loans"),"Tier 1",IF(Z29>=Scoring!$B$19,"Tier 2","Tier 3"))
A30: cu:68503 | B30: First City CU | C30: Pasadena | D30: Los Angeles | E30: 948.50836 | F30: 816.1643 | G30: 465.11509 | H30: 204.43981 | I30: =IF(F30=0,"",G30/F30) | J30: 0.44591071 | K30: 0.1352 | L30: =IF(G30=0,"",H30/G30) | M30: 32.278876 | N30: =IF(E30=0,"",2*M30/E30) | O30: 0 | P30: 0.0086702847 | Q30: 0.11566033 | R30: =IF(OR(P30="",Q30=""),"",P30-Q30) | S30: 126 | T30: 25.65 | U30: 1 | V30: 0 | W30: 2 | X30: 0 | Y30: Retail only | Z30: =ROUND(100*(Scoring!$B$11*(1-IFERROR(PERCENTRANK($I$2:$I$67,I30),0.5))+Scoring!$B$12*IFERROR(PERCENTRANK($J$2:$J$67,J30),0.5)+Scoring!$B$13*IFERROR(PERCENTRANK($K$2:$K$67,K30),0.5)+Scoring!$B$14*IFERROR(PERCENTRANK($R$2:$R$67,R30),0.5)+Scoring!$B$15*(1-IFERROR(PERCENTRANK($N$2:$N$67,N30),0.5))+Scoring!$B$16*(1-IFERROR(PERCENTRANK($L$2:$L$67,L30),0.5))),0) | AA30: =IF(AND(Z30>=Scoring!$B$18,E30>=Scoring!$B$20,Y30<>"Already takes broker loans"),"Tier 1",IF(Z30>=Scoring!$B$19,"Tier 2","Tier 3"))
A31: cu:9230 | B31: Certified CU | C31: El Monte | D31: Los Angeles | E31: 925.32842 | F31: 723.91977 | G31: 585.35561 | H31: 285.90479 | I31: =IF(F31=0,"",G31/F31) | J31: 0.33639564 | K31: 0.2071 | L31: =IF(G31=0,"",H31/G31) | M31: 13.7596 | N31: =IF(E31=0,"",2*M31/E31) | O31: 0 | P31: 0.027244346 | Q31: 0.033059721 | R31: =IF(OR(P31="",Q31=""),"",P31-Q31) | S31: 101 | T31: 29.545 | U31: 1 | V31: 0 | W31: 0 | X31: 0 | Y31: Retail only | Z31: =ROUND(100*(Scoring!$B$11*(1-IFERROR(PERCENTRANK($I$2:$I$67,I31),0.5))+Scoring!$B$12*IFERROR(PERCENTRANK($J$2:$J$67,J31),0.5)+Scoring!$B$13*IFERROR(PERCENTRANK($K$2:$K$67,K31),0.5)+Scoring!$B$14*IFERROR(PERCENTRANK($R$2:$R$67,R31),0.5)+Scoring!$B$15*(1-IFERROR(PERCENTRANK($N$2:$N$67,N31),0.5))+Scoring!$B$16*(1-IFERROR(PERCENTRANK($L$2:$L$67,L31),0.5))),0) | AA31: =IF(AND(Z31>=Scoring!$B$18,E31>=Scoring!$B$20,Y31<>"Already takes broker loans"),"Tier 1",IF(Z31>=Scoring!$B$19,"Tier 2","Tier 3"))
A32: cu:6248 | B32: Skyone CU | C32: Hawthorne | D32: Los Angeles | E32: 863.33988 | F32: 732.2873 | G32: 622.35254 | H32: 139.89215 | I32: =IF(F32=0,"",G32/F32) | J32: 0.17573776 | K32: 0.0767 | L32: =IF(G32=0,"",H32/G32) | M32: 19.845086 | N32: =IF(E32=0,"",2*M32/E32) | O32: 0 | P32: 0.0037776056 | Q32: -0.019048551 | R32: =IF(OR(P32="",Q32=""),"",P32-Q32) | S32: 64 | T32: 20.36 | U32: 0.890625 | V32: 0 | W32: 2 | X32: 0 | Y32: Retail only | Z32: =ROUND(100*(Scoring!$B$11*(1-IFERROR(PERCENTRANK($I$2:$I$67,I32),0.5))+Scoring!$B$12*IFERROR(PERCENTRANK($J$2:$J$67,J32),0.5)+Scoring!$B$13*IFERROR(PERCENTRANK($K$2:$K$67,K32),0.5)+Scoring!$B$14*IFERROR(PERCENTRANK($R$2:$R$67,R32),0.5)+Scoring!$B$15*(1-IFERROR(PERCENTRANK($N$2:$N$67,N32),0.5))+Scoring!$B$16*(1-IFERROR(PERCENTRANK($L$2:$L$67,L32),0.5))),0) | AA32: =IF(AND(Z32>=Scoring!$B$18,E32>=Scoring!$B$20,Y32<>"Already takes broker loans"),"Tier 1",IF(Z32>=Scoring!$B$19,"Tier 2","Tier 3"))
A33: cu:68062 | B33: America's Christian CU | C33: Glendora | D33: Los Angeles | E33: 819.75482 | F33: 729.13023 | G33: 646.97423 | H33: 35.267901 | I33: =IF(F33=0,"",G33/F33) | J33: 0.12886973 | K33: 0.0889 | L33: =IF(G33=0,"",H33/G33) | M33: 1.162 | N33: =IF(E33=0,"",2*M33/E33) | O33: 0 | P33: 0.13980277 | Q33: 0.096317907 | R33: =IF(OR(P33="",Q33=""),"",P33-Q33) | Y33: No HMDA mortgage reporting | Z33: =ROUND(100*(Scoring!$B$11*(1-IFERROR(PERCENTRANK($I$2:$I$67,I33),0.5))+Scoring!$B$12*IFERROR(PERCENTRANK($J$2:$J$67,J33),0.5)+Scoring!$B$13*IFERROR(PERCENTRANK($K$2:$K$67,K33),0.5)+Scoring!$B$14*IFERROR(PERCENTRANK($R$2:$R$67,R33),0.5)+Scoring!$B$15*(1-IFERROR(PERCENTRANK($N$2:$N$67,N33),0.5))+Scoring!$B$16*(1-IFERROR(PERCENTRANK($L$2:$L$67,L33),0.5))),0) | AA33: =IF(AND(Z33>=Scoring!$B$18,E33>=Scoring!$B$20,Y33<>"Already takes broker loans"),"Tier 1",IF(Z33>=Scoring!$B$19,"Tier 2","Tier 3"))
A34: cu:12425 | B34: Foothill CU | C34: Arcadia | D34: Los Angeles | E34: 778.60253 | F34: 654.68288 | G34: 565.70649 | H34: 211.23607 | I34: =IF(F34=0,"",G34/F34) | J34: 0.20090375 | K34: 0.1229 | L34: =IF(G34=0,"",H34/G34) | M34: 25.01422 | N34: =IF(E34=0,"",2*M34/E34) | O34: 0 | P34: 0.017158104 | Q34: 0.098865355 | R34: =IF(OR(P34="",Q34=""),"",P34-Q34) | S34: 140 | T34: 47.19 | U34: 0.0071428571 | V34: 1 | W34: 3 | X34: 0 | Y34: Retail only | Z34: =ROUND(100*(Scoring!$B$11*(1-IFERROR(PERCENTRANK($I$2:$I$67,I34),0.5))+Scoring!$B$12*IFERROR(PERCENTRANK($J$2:$J$67,J34),0.5)+Scoring!$B$13*IFERROR(PERCENTRANK($K$2:$K$67,K34),0.5)+Scoring!$B$14*IFERROR(PERCENTRANK($R$2:$R$67,R34),0.5)+Scoring!$B$15*(1-IFERROR(PERCENTRANK($N$2:$N$67,N34),0.5))+Scoring!$B$16*(1-IFERROR(PERCENTRANK($L$2:$L$67,L34),0.5))),0) | AA34: =IF(AND(Z34>=Scoring!$B$18,E34>=Scoring!$B$20,Y34<>"Already takes broker loans"),"Tier 1",IF(Z34>=Scoring!$B$19,"Tier 2","Tier 3"))
A35: cu:24875 | B35: The First Financial CU | C35: Pasadena | D35: Los Angeles | E35: 748.27475 | F35: 726.826 | G35: 398.68515 | H35: 97.790016 | I35: =IF(F35=0,"",G35/F35) | J35: 0.33789193 | K35: 0.0704 | L35: =IF(G35=0,"",H35/G35) | M35: 0.3502 | N35: =IF(E35=0,"",2*M35/E35) | O35: 0 | P35: 0.013607556 | Q35: -0.0062578922 | R35: =IF(OR(P35="",Q35=""),"",P35-Q35) | S35: 323 | T35: 34.425 | U35: 1 | V35: 0 | W35: 0 | X35: 0.0030959752 | Y35: Mostly retail, a few broker loans | Z35: =ROUND(100*(Scoring!$B$11*(1-IFERROR(PERCENTRANK($I$2:$I$67,I35),0.5))+Scoring!$B$12*IFERROR(PERCENTRANK($J$2:$J$67,J35),0.5)+Scoring!$B$13*IFERROR(PERCENTRANK($K$2:$K$67,K35),0.5)+Scoring!$B$14*IFERROR(PERCENTRANK($R$2:$R$67,R35),0.5)+Scoring!$B$15*(1-IFERROR(PERCENTRANK($N$2:$N$67,N35),0.5))+Scoring!$B$16*(1-IFERROR(PERCENTRANK($L$2:$L$67,L35),0.5))),0) | AA35: =IF(AND(Z35>=Scoring!$B$18,E35>=Scoring!$B$20,Y35<>"Already takes broker loans"),"Tier 1",IF(Z35>=Scoring!$B$19,"Tier 2","Tier 3"))
A36: cu:68459 | B36: USC CU | C36: Los Angeles | D36: Los Angeles | E36: 741.13355 | F36: 638.26166 | G36: 602.69829 | H36: 263.28755 | I36: =IF(F36=0,"",G36/F36) | J36: 0.15823839 | K36: 0.1028 | L36: =IF(G36=0,"",H36/G36) | M36: 36.591773 | N36: =IF(E36=0,"",2*M36/E36) | O36: 2.0449 | P36: 0.031391385 | Q36: 0.12109389 | R36: =IF(OR(P36="",Q36=""),"",P36-Q36) | S36: 144 | T36: 55.84 | U36: 0.92361111 | V36: 0 | W36: 0 | X36: 0 | Y36: Retail only | Z36: =ROUND(100*(Scoring!$B$11*(1-IFERROR(PERCENTRANK($I$2:$I$67,I36),0.5))+Scoring!$B$12*IFERROR(PERCENTRANK($J$2:$J$67,J36),0.5)+Scoring!$B$13*IFERROR(PERCENTRANK($K$2:$K$67,K36),0.5)+Scoring!$B$14*IFERROR(PERCENTRANK($R$2:$R$67,R36),0.5)+Scoring!$B$15*(1-IFERROR(PERCENTRANK($N$2:$N$67,N36),0.5))+Scoring!$B$16*(1-IFERROR(PERCENTRANK($L$2:$L$67,L36),0.5))),0) | AA36: =IF(AND(Z36>=Scoring!$B$18,E36>=Scoring!$B$20,Y36<>"Already takes broker loans"),"Tier 1",IF(Z36>=Scoring!$B$19,"Tier 2","Tier 3"))
A37: cu:24916 | B37: ILWU CU | C37: Long Beach | D37: Los Angeles | E37: 607.53536 | F37: 550.22778 | G37: 407.52832 | H37: 124.66119 | I37: =IF(F37=0,"",G37/F37) | J37: 0.2916398 | K37: 0.0994 | L37: =IF(G37=0,"",H37/G37) | M37: 4.962 | N37: =IF(E37=0,"",2*M37/E37) | O37: 0 | P37: 0.16024355 | Q37: 0.11592476 | R37: =IF(OR(P37="",Q37=""),"",P37-Q37) | S37: 58 | T37: 11.05 | U37: 1 | V37: 1 | W37: 5 | X37: 0 | Y37: Retail only | Z37: =ROUND(100*(Scoring!$B$11*(1-IFERROR(PERCENTRANK($I$2:$I$67,I37),0.5))+Scoring!$B$12*IFERROR(PERCENTRANK($J$2:$J$67,J37),0.5)+Scoring!$B$13*IFERROR(PERCENTRANK($K$2:$K$67,K37),0.5)+Scoring!$B$14*IFERROR(PERCENTRANK($R$2:$R$67,R37),0.5)+Scoring!$B$15*(1-IFERROR(PERCENTRANK($N$2:$N$67,N37),0.5))+Scoring!$B$16*(1-IFERROR(PERCENTRANK($L$2:$L$67,L37),0.5))),0) | AA37: =IF(AND(Z37>=Scoring!$B$18,E37>=Scoring!$B$20,Y37<>"Already takes broker loans"),"Tier 1",IF(Z37>=Scoring!$B$19,"Tier 2","Tier 3"))
A38: cu:3943 | B38: Gain CU | C38: Burbank | D38: Los Angeles | E38: 453.99633 | F38: 424.12415 | G38: 241.76364 | H38: 123.93259 | I38: =IF(F38=0,"",G38/F38) | J38: 0.42196663 | K38: 0.0814 | L38: =IF(G38=0,"",H38/G38) | M38: 3.559 | N38: =IF(E38=0,"",2*M38/E38) | O38: 0.55 | P38: 0.046075801 | Q38: 0.025584826 | R38: =IF(OR(P38="",Q38=""),"",P38-Q38) | S38: 7 | T38: 1.295 | U38: 0.42857143 | V38: 0 | W38: 1 | X38: 0 | Y38: Retail only | Z38: =ROUND(100*(Scoring!$B$11*(1-IFERROR(PERCENTRANK($I$2:$I$67,I38),0.5))+Scoring!$B$12*IFERROR(PERCENTRANK($J$2:$J$67,J38),0.5)+Scoring!$B$13*IFERROR(PERCENTRANK($K$2:$K$67,K38),0.5)+Scoring!$B$14*IFERROR(PERCENTRANK($R$2:$R$67,R38),0.5)+Scoring!$B$15*(1-IFERROR(PERCENTRANK($N$2:$N$67,N38),0.5))+Scoring!$B$16*(1-IFERROR(PERCENTRANK($L$2:$L$67,L38),0.5))),0) | AA38: =IF(AND(Z38>=Scoring!$B$18,E38>=Scoring!$B$20,Y38<>"Already takes broker loans"),"Tier 1",IF(Z38>=Scoring!$B$19,"Tier 2","Tier 3"))
A39: cu:14723 | B39: Aerospace CU | C39: Los Angeles | D39: Los Angeles | E39: 445.6964 | F39: 325.536 | G39: 154.10346 | H39: 67.376777 | I39: =IF(F39=0,"",G39/F39) | J39: 0.61127965 | K39: 0.0947 | L39: =IF(G39=0,"",H39/G39) | M39: 0.359 | N39: =IF(E39=0,"",2*M39/E39) | O39: 0 | P39: -0.016353798 | Q39: -0.063261831 | R39: =IF(OR(P39="",Q39=""),"",P39-Q39) | Y39: No HMDA mortgage reporting | Z39: =ROUND(100*(Scoring!$B$11*(1-IFERROR(PERCENTRANK($I$2:$I$67,I39),0.5))+Scoring!$B$12*IFERROR(PERCENTRANK($J$2:$J$67,J39),0.5)+Scoring!$B$13*IFERROR(PERCENTRANK($K$2:$K$67,K39),0.5)+Scoring!$B$14*IFERROR(PERCENTRANK($R$2:$R$67,R39),0.5)+Scoring!$B$15*(1-IFERROR(PERCENTRANK($N$2:$N$67,N39),0.5))+Scoring!$B$16*(1-IFERROR(PERCENTRANK($L$2:$L$67,L39),0.5))),0) | AA39: =IF(AND(Z39>=Scoring!$B$18,E39>=Scoring!$B$20,Y39<>"Already takes broker loans"),"Tier 1",IF(Z39>=Scoring!$B$19,"Tier 2","Tier 3"))
A40: cu:97101 | B40: Glendale Area Schools CU | C40: Glendale | D40: Los Angeles | E40: 422.09023 | F40: 364.43303 | G40: 127.57817 | H40: 30.377588 | I40: =IF(F40=0,"",G40/F40) | J40: 0.69401525 | K40: 0.1309 | L40: =IF(G40=0,"",H40/G40) | M40: 2.526 | N40: =IF(E40=0,"",2*M40/E40) | O40: 0 | P40: -0.017666251 | Q40: -0.059082015 | R40: =IF(OR(P40="",Q40=""),"",P40-Q40) | Y40: No HMDA mortgage reporting | Z40: =ROUND(100*(Scoring!$B$11*(1-IFERROR(PERCENTRANK($I$2:$I$67,I40),0.5))+Scoring!$B$12*IFERROR(PERCENTRANK($J$2:$J$67,J40),0.5)+Scoring!$B$13*IFERROR(PERCENTRANK($K$2:$K$67,K40),0.5)+Scoring!$B$14*IFERROR(PERCENTRANK($R$2:$R$67,R40),0.5)+Scoring!$B$15*(1-IFERROR(PERCENTRANK($N$2:$N$67,N40),0.5))+Scoring!$B$16*(1-IFERROR(PERCENTRANK($L$2:$L$67,L40),0.5))),0) | AA40: =IF(AND(Z40>=Scoring!$B$18,E40>=Scoring!$B$20,Y40<>"Already takes broker loans"),"Tier 1",IF(Z40>=Scoring!$B$19,"Tier 2","Tier 3"))
A41: cu:66847 | B41: Eagle Community CU | C41: Lake Forest | D41: Orange | E41: 409.21621 | F41: 362.67259 | G41: 337.15389 | H41: 3.315754 | I41: =IF(F41=0,"",G41/F41) | J41: 0.12349004 | K41: 0.0991 | L41: =IF(G41=0,"",H41/G41) | M41: 0 | N41: =IF(E41=0,"",2*M41/E41) | O41: 0 | P41: 0.1610401 | Q41: 0.1597078 | R41: =IF(OR(P41="",Q41=""),"",P41-Q41) | S41: 480 | T41: 76.51 | U41: 1 | V41: 0 | W41: 0 | X41: 0 | Y41: Retail only | Z41: =ROUND(100*(Scoring!$B$11*(1-IFERROR(PERCENTRANK($I$2:$I$67,I41),0.5))+Scoring!$B$12*IFERROR(PERCENTRANK($J$2:$J$67,J41),0.5)+Scoring!$B$13*IFERROR(PERCENTRANK($K$2:$K$67,K41),0.5)+Scoring!$B$14*IFERROR(PERCENTRANK($R$2:$R$67,R41),0.5)+Scoring!$B$15*(1-IFERROR(PERCENTRANK($N$2:$N$67,N41),0.5))+Scoring!$B$16*(1-IFERROR(PERCENTRANK($L$2:$L$67,L41),0.5))),0) | AA41: =IF(AND(Z41>=Scoring!$B$18,E41>=Scoring!$B$20,Y41<>"Already takes broker loans"),"Tier 1",IF(Z41>=Scoring!$B$19,"Tier 2","Tier 3"))
A42: cu:23004 | B42: POPA CU | C42: Cerritos | D42: Los Angeles | E42: 404.54464 | F42: 358.23878 | G42: 246.35718 | H42: 55.514287 | I42: =IF(F42=0,"",G42/F42) | J42: 0.35734017 | K42: 0.1184 | L42: =IF(G42=0,"",H42/G42) | M42: 7.023082 | N42: =IF(E42=0,"",2*M42/E42) | O42: 0 | P42: 0.022398144 | Q42: -0.0054361996 | R42: =IF(OR(P42="",Q42=""),"",P42-Q42) | S42: 80 | T42: 12.14 | U42: 1 | V42: 0 | W42: 0 | X42: 0 | Y42: Retail only | Z42: =ROUND(100*(Scoring!$B$11*(1-IFERROR(PERCENTRANK($I$2:$I$67,I42),0.5))+Scoring!$B$12*IFERROR(PERCENTRANK($J$2:$J$67,J42),0.5)+Scoring!$B$13*IFERROR(PERCENTRANK($K$2:$K$67,K42),0.5)+Scoring!$B$14*IFERROR(PERCENTRANK($R$2:$R$67,R42),0.5)+Scoring!$B$15*(1-IFERROR(PERCENTRANK($N$2:$N$67,N42),0.5))+Scoring!$B$16*(1-IFERROR(PERCENTRANK($L$2:$L$67,L42),0.5))),0) | AA42: =IF(AND(Z42>=Scoring!$B$18,E42>=Scoring!$B$20,Y42<>"Already takes broker loans"),"Tier 1",IF(Z42>=Scoring!$B$19,"Tier 2","Tier 3"))
A43: cu:594 | B43: Pasadena CU | C43: Monrovia | D43: Los Angeles | E43: 374.96614 | F43: 322.89518 | G43: 223.56059 | H43: 99.492174 | I43: =IF(F43=0,"",G43/F43) | J43: 0.2854996 | K43: 0.111 | L43: =IF(G43=0,"",H43/G43) | M43: 10.703 | N43: =IF(E43=0,"",2*M43/E43) | O43: 0 | P43: -0.020649874 | Q43: 0.1147036 | R43: =IF(OR(P43="",Q43=""),"",P43-Q43) | S43: 75 | T43: 14.795 | U43: 1 | V43: 0 | W43: 0 | X43: 0.053333333 | Y43: Mostly retail, a few broker loans | Z43: =ROUND(100*(Scoring!$B$11*(1-IFERROR(PERCENTRANK($I$2:$I$67,I43),0.5))+Scoring!$B$12*IFERROR(PERCENTRANK($J$2:$J$67,J43),0.5)+Scoring!$B$13*IFERROR(PERCENTRANK($K$2:$K$67,K43),0.5)+Scoring!$B$14*IFERROR(PERCENTRANK($R$2:$R$67,R43),0.5)+Scoring!$B$15*(1-IFERROR(PERCENTRANK($N$2:$N$67,N43),0.5))+Scoring!$B$16*(1-IFERROR(PERCENTRANK($L$2:$L$67,L43),0.5))),0) | AA43: =IF(AND(Z43>=Scoring!$B$18,E43>=Scoring!$B$20,Y43<>"Already takes broker loans"),"Tier 1",IF(Z43>=Scoring!$B$19,"Tier 2","Tier 3"))
A44: cu:68483 | B44: Matadors Community CU | C44: Northridge | D44: Los Angeles | E44: 356.09364 | F44: 312.77016 | G44: 281.26608 | H44: 70.52468 | I44: =IF(F44=0,"",G44/F44) | J44: 0.12114313 | K44: 0.1167 | L44: =IF(G44=0,"",H44/G44) | M44: 4.612 | N44: =IF(E44=0,"",2*M44/E44) | O44: 0 | P44: -0.035241335 | Q44: 0.0060934982 | R44: =IF(OR(P44="",Q44=""),"",P44-Q44) | Y44: No HMDA mortgage reporting | Z44: =ROUND(100*(Scoring!$B$11*(1-IFERROR(PERCENTRANK($I$2:$I$67,I44),0.5))+Scoring!$B$12*IFERROR(PERCENTRANK($J$2:$J$67,J44),0.5)+Scoring!$B$13*IFERROR(PERCENTRANK($K$2:$K$67,K44),0.5)+Scoring!$B$14*IFERROR(PERCENTRANK($R$2:$R$67,R44),0.5)+Scoring!$B$15*(1-IFERROR(PERCENTRANK($N$2:$N$67,N44),0.5))+Scoring!$B$16*(1-IFERROR(PERCENTRANK($L$2:$L$67,L44),0.5))),0) | AA44: =IF(AND(Z44>=Scoring!$B$18,E44>=Scoring!$B$20,Y44<>"Already takes broker loans"),"Tier 1",IF(Z44>=Scoring!$B$19,"Tier 2","Tier 3"))
A45: cu:15317 | B45: SAG-AFTRA CU | C45: Burbank | D45: Los Angeles | E45: 335.61489 | F45: 287.06696 | G45: 163.50784 | H45: 71.545874 | I45: =IF(F45=0,"",G45/F45) | J45: 0.45314369 | K45: 0.1313 | L45: =IF(G45=0,"",H45/G45) | M45: 10.450394 | N45: =IF(E45=0,"",2*M45/E45) | O45: 0 | P45: -0.060097638 | Q45: 0.0063385705 | R45: =IF(OR(P45="",Q45=""),"",P45-Q45) | Y45: No HMDA mortgage reporting | Z45: =ROUND(100*(Scoring!$B$11*(1-IFERROR(PERCENTRANK($I$2:$I$67,I45),0.5))+Scoring!$B$12*IFERROR(PERCENTRANK($J$2:$J$67,J45),0.5)+Scoring!$B$13*IFERROR(PERCENTRANK($K$2:$K$67,K45),0.5)+Scoring!$B$14*IFERROR(PERCENTRANK($R$2:$R$67,R45),0.5)+Scoring!$B$15*(1-IFERROR(PERCENTRANK($N$2:$N$67,N45),0.5))+Scoring!$B$16*(1-IFERROR(PERCENTRANK($L$2:$L$67,L45),0.5))),0) | AA45: =IF(AND(Z45>=Scoring!$B$18,E45>=Scoring!$B$20,Y45<>"Already takes broker loans"),"Tier 1",IF(Z45>=Scoring!$B$19,"Tier 2","Tier 3"))
A46: cu:11870 | B46: Downey CU | C46: Downey | D46: Los Angeles | E46: 327.91265 | F46: 267.94149 | G46: 173.96629 | H46: 38.912538 | I46: =IF(F46=0,"",G46/F46) | J46: 0.39290478 | K46: 0.088 | L46: =IF(G46=0,"",H46/G46) | M46: 5.041597 | N46: =IF(E46=0,"",2*M46/E46) | O46: 0 | P46: 0.029034662 | Q46: -0.060902483 | R46: =IF(OR(P46="",Q46=""),"",P46-Q46) | S46: 10 | T46: 0.95 | U46: 1 | V46: 0 | W46: 2 | X46: 0 | Y46: Retail only | Z46: =ROUND(100*(Scoring!$B$11*(1-IFERROR(PERCENTRANK($I$2:$I$67,I46),0.5))+Scoring!$B$12*IFERROR(PERCENTRANK($J$2:$J$67,J46),0.5)+Scoring!$B$13*IFERROR(PERCENTRANK($K$2:$K$67,K46),0.5)+Scoring!$B$14*IFERROR(PERCENTRANK($R$2:$R$67,R46),0.5)+Scoring!$B$15*(1-IFERROR(PERCENTRANK($N$2:$N$67,N46),0.5))+Scoring!$B$16*(1-IFERROR(PERCENTRANK($L$2:$L$67,L46),0.5))),0) | AA46: =IF(AND(Z46>=Scoring!$B$18,E46>=Scoring!$B$20,Y46<>"Already takes broker loans"),"Tier 1",IF(Z46>=Scoring!$B$19,"Tier 2","Tier 3"))
A47: cu:3945 | B47: UMe CU | C47: Burbank | D47: Los Angeles | E47: 327.85711 | F47: 296.65711 | G47: 168.31056 | H47: 87.919045 | I47: =IF(F47=0,"",G47/F47) | J47: 0.45261937 | K47: 0.0986 | L47: =IF(G47=0,"",H47/G47) | M47: 9.381 | N47: =IF(E47=0,"",2*M47/E47) | O47: 0 | P47: -0.034110385 | Q47: 0.041470375 | R47: =IF(OR(P47="",Q47=""),"",P47-Q47) | S47: 15 | T47: 11.045 | U47: 1 | V47: 0 | W47: 0 | X47: 0 | Y47: Retail only | Z47: =ROUND(100*(Scoring!$B$11*(1-IFERROR(PERCENTRANK($I$2:$I$67,I47),0.5))+Scoring!$B$12*IFERROR(PERCENTRANK($J$2:$J$67,J47),0.5)+Scoring!$B$13*IFERROR(PERCENTRANK($K$2:$K$67,K47),0.5)+Scoring!$B$14*IFERROR(PERCENTRANK($R$2:$R$67,R47),0.5)+Scoring!$B$15*(1-IFERROR(PERCENTRANK($N$2:$N$67,N47),0.5))+Scoring!$B$16*(1-IFERROR(PERCENTRANK($L$2:$L$67,L47),0.5))),0) | AA47: =IF(AND(Z47>=Scoring!$B$18,E47>=Scoring!$B$20,Y47<>"Already takes broker loans"),"Tier 1",IF(Z47>=Scoring!$B$19,"Tier 2","Tier 3"))
A48: cu:1438 | B48: Long Beach City Employees CU | C48: Signal Hill | D48: Los Angeles | E48: 270.62513 | F48: 233.97745 | G48: 121.83694 | H48: 81.924686 | I48: =IF(F48=0,"",G48/F48) | J48: 0.45313077 | K48: 0.1385 | L48: =IF(G48=0,"",H48/G48) | M48: 9.60469 | N48: =IF(E48=0,"",2*M48/E48) | O48: 0 | P48: -0.014325601 | Q48: 0.027319666 | R48: =IF(OR(P48="",Q48=""),"",P48-Q48) | S48: 37 | T48: 9.075 | U48: 0 | V48: 0 | W48: 0 | X48: 1 | Y48: Already takes broker loans | Z48: =ROUND(100*(Scoring!$B$11*(1-IFERROR(PERCENTRANK($I$2:$I$67,I48),0.5))+Scoring!$B$12*IFERROR(PERCENTRANK($J$2:$J$67,J48),0.5)+Scoring!$B$13*IFERROR(PERCENTRANK($K$2:$K$67,K48),0.5)+Scoring!$B$14*IFERROR(PERCENTRANK($R$2:$R$67,R48),0.5)+Scoring!$B$15*(1-IFERROR(PERCENTRANK($N$2:$N$67,N48),0.5))+Scoring!$B$16*(1-IFERROR(PERCENTRANK($L$2:$L$67,L48),0.5))),0) | AA48: =IF(AND(Z48>=Scoring!$B$18,E48>=Scoring!$B$20,Y48<>"Already takes broker loans"),"Tier 1",IF(Z48>=Scoring!$B$19,"Tier 2","Tier 3"))
A49: cu:16030 | B49: Chaffey CU | C49: Upland | D49: San Bernardino | E49: 230.38104 | F49: 202.66887 | G49: 118.656 | H49: 36.145492 | I49: =IF(F49=0,"",G49/F49) | J49: 0.43632384 | K49: 0.0774 | L49: =IF(G49=0,"",H49/G49) | M49: 0 | N49: =IF(E49=0,"",2*M49/E49) | O49: 0 | P49: 0.0059423147 | Q49: -0.025772887 | R49: =IF(OR(P49="",Q49=""),"",P49-Q49) | Y49: No HMDA mortgage reporting | Z49: =ROUND(100*(Scoring!$B$11*(1-IFERROR(PERCENTRANK($I$2:$I$67,I49),0.5))+Scoring!$B$12*IFERROR(PERCENTRANK($J$2:$J$67,J49),0.5)+Scoring!$B$13*IFERROR(PERCENTRANK($K$2:$K$67,K49),0.5)+Scoring!$B$14*IFERROR(PERCENTRANK($R$2:$R$67,R49),0.5)+Scoring!$B$15*(1-IFERROR(PERCENTRANK($N$2:$N$67,N49),0.5))+Scoring!$B$16*(1-IFERROR(PERCENTRANK($L$2:$L$67,L49),0.5))),0) | AA49: =IF(AND(Z49>=Scoring!$B$18,E49>=Scoring!$B$20,Y49<>"Already takes broker loans"),"Tier 1",IF(Z49>=Scoring!$B$19,"Tier 2","Tier 3"))
A50: cu:9556 | B50: Clearpath CU | C50: Burbank | D50: Los Angeles | E50: 228.6342 | F50: 204.16793 | G50: 194.41698 | H50: 12.898533 | I50: =IF(F50=0,"",G50/F50) | J50: 0.097089809 | K50: 0.0846 | L50: =IF(G50=0,"",H50/G50) | M50: 0.005938 | N50: =IF(E50=0,"",2*M50/E50) | O50: 0 | P50: 0.030776291 | Q50: 0.24845392 | R50: =IF(OR(P50="",Q50=""),"",P50-Q50) | Y50: No HMDA mortgage reporting | Z50: =ROUND(100*(Scoring!$B$11*(1-IFERROR(PERCENTRANK($I$2:$I$67,I50),0.5))+Scoring!$B$12*IFERROR(PERCENTRANK($J$2:$J$67,J50),0.5)+Scoring!$B$13*IFERROR(PERCENTRANK($K$2:$K$67,K50),0.5)+Scoring!$B$14*IFERROR(PERCENTRANK($R$2:$R$67,R50),0.5)+Scoring!$B$15*(1-IFERROR(PERCENTRANK($N$2:$N$67,N50),0.5))+Scoring!$B$16*(1-IFERROR(PERCENTRANK($L$2:$L$67,L50),0.5))),0) | AA50: =IF(AND(Z50>=Scoring!$B$18,E50>=Scoring!$B$20,Y50<>"Already takes broker loans"),"Tier 1",IF(Z50>=Scoring!$B$19,"Tier 2","Tier 3"))
A51: cu:64531 | B51: Alta Vista CU | C51: Redlands | D51: San Bernardino | E51: 208.55416 | F51: 188.40319 | G51: 129.06131 | H51: 76.389747 | I51: =IF(F51=0,"",G51/F51) | J51: 0.29675491 | K51: 0.0889 | L51: =IF(G51=0,"",H51/G51) | M51: 4.87485 | N51: =IF(E51=0,"",2*M51/E51) | O51: 0 | P51: -0.034674149 | Q51: -0.067030753 | R51: =IF(OR(P51="",Q51=""),"",P51-Q51) | S51: 24 | T51: 11.87 | U51: 0 | V51: 21 | W51: 3 | X51: 0 | Y51: Retail only | Z51: =ROUND(100*(Scoring!$B$11*(1-IFERROR(PERCENTRANK($I$2:$I$67,I51),0.5))+Scoring!$B$12*IFERROR(PERCENTRANK($J$2:$J$67,J51),0.5)+Scoring!$B$13*IFERROR(PERCENTRANK($K$2:$K$67,K51),0.5)+Scoring!$B$14*IFERROR(PERCENTRANK($R$2:$R$67,R51),0.5)+Scoring!$B$15*(1-IFERROR(PERCENTRANK($N$2:$N$67,N51),0.5))+Scoring!$B$16*(1-IFERROR(PERCENTRANK($L$2:$L$67,L51),0.5))),0) | AA51: =IF(AND(Z51>=Scoring!$B$18,E51>=Scoring!$B$20,Y51<>"Already takes broker loans"),"Tier 1",IF(Z51>=Scoring!$B$19,"Tier 2","Tier 3"))
A52: cu:60024 | B52: Priority One CU | C52: South Pasadena | D52: Los Angeles | E52: 205.88525 | F52: 178.59397 | G52: 95.974905 | H52: 37.338533 | I52: =IF(F52=0,"",G52/F52) | J52: 0.4836554 | K52: 0.1395 | L52: =IF(G52=0,"",H52/G52) | M52: 0.331 | N52: =IF(E52=0,"",2*M52/E52) | O52: 0 | P52: 0.015290934 | Q52: -0.021741487 | R52: =IF(OR(P52="",Q52=""),"",P52-Q52) | S52: 19 | T52: 1.325 | U52: 1 | V52: 1 | W52: 0 | X52: 0 | Y52: Retail only | Z52: =ROUND(100*(Scoring!$B$11*(1-IFERROR(PERCENTRANK($I$2:$I$67,I52),0.5))+Scoring!$B$12*IFERROR(PERCENTRANK($J$2:$J$67,J52),0.5)+Scoring!$B$13*IFERROR(PERCENTRANK($K$2:$K$67,K52),0.5)+Scoring!$B$14*IFERROR(PERCENTRANK($R$2:$R$67,R52),0.5)+Scoring!$B$15*(1-IFERROR(PERCENTRANK($N$2:$N$67,N52),0.5))+Scoring!$B$16*(1-IFERROR(PERCENTRANK($L$2:$L$67,L52),0.5))),0) | AA52: =IF(AND(Z52>=Scoring!$B$18,E52>=Scoring!$B$20,Y52<>"Already takes broker loans"),"Tier 1",IF(Z52>=Scoring!$B$19,"Tier 2","Tier 3"))
A53: cu:67921 | B53: Long Beach Firemen's CU | C53: Long Beach | D53: Los Angeles | E53: 201.47866 | F53: 142.04903 | G53: 134.37336 | H53: 110.17416 | I53: =IF(F53=0,"",G53/F53) | J53: 0.33359135 | K53: 0.2943 | L53: =IF(G53=0,"",H53/G53) | M53: 1.539729 | N53: =IF(E53=0,"",2*M53/E53) | O53: 0 | P53: -0.02814352 | Q53: -0.055578529 | R53: =IF(OR(P53="",Q53=""),"",P53-Q53) | Y53: No HMDA mortgage reporting | Z53: =ROUND(100*(Scoring!$B$11*(1-IFERROR(PERCENTRANK($I$2:$I$67,I53),0.5))+Scoring!$B$12*IFERROR(PERCENTRANK($J$2:$J$67,J53),0.5)+Scoring!$B$13*IFERROR(PERCENTRANK($K$2:$K$67,K53),0.5)+Scoring!$B$14*IFERROR(PERCENTRANK($R$2:$R$67,R53),0.5)+Scoring!$B$15*(1-IFERROR(PERCENTRANK($N$2:$N$67,N53),0.5))+Scoring!$B$16*(1-IFERROR(PERCENTRANK($L$2:$L$67,L53),0.5))),0) | AA53: =IF(AND(Z53>=Scoring!$B$18,E53>=Scoring!$B$20,Y53<>"Already takes broker loans"),"Tier 1",IF(Z53>=Scoring!$B$19,"Tier 2","Tier 3"))
A54: cu:3526 | B54: Schools CU | C54: Torrance | D54: Los Angeles | E54: 195.70378 | F54: 170.45671 | G54: 93.588806 | H54: 29.657745 | I54: =IF(F54=0,"",G54/F54) | J54: 0.48663526 | K54: 0.1191 | L54: =IF(G54=0,"",H54/G54) | M54: 1.5425 | N54: =IF(E54=0,"",2*M54/E54) | O54: 0 | P54: 0.037284317 | Q54: 0.070408563 | R54: =IF(OR(P54="",Q54=""),"",P54-Q54) | Y54: No HMDA mortgage reporting | Z54: =ROUND(100*(Scoring!$B$11*(1-IFERROR(PERCENTRANK($I$2:$I$67,I54),0.5))+Scoring!$B$12*IFERROR(PERCENTRANK($J$2:$J$67,J54),0.5)+Scoring!$B$13*IFERROR(PERCENTRANK($K$2:$K$67,K54),0.5)+Scoring!$B$14*IFERROR(PERCENTRANK($R$2:$R$67,R54),0.5)+Scoring!$B$15*(1-IFERROR(PERCENTRANK($N$2:$N$67,N54),0.5))+Scoring!$B$16*(1-IFERROR(PERCENTRANK($L$2:$L$67,L54),0.5))),0) | AA54: =IF(AND(Z54>=Scoring!$B$18,E54>=Scoring!$B$20,Y54<>"Already takes broker loans"),"Tier 1",IF(Z54>=Scoring!$B$19,"Tier 2","Tier 3"))
A55: cu:4633 | B55: Camino CU | C55: Montebello | D55: Los Angeles | E55: 178.80111 | F55: 150.56705 | G55: 134.7112 | H55: 82.124553 | I55: =IF(F55=0,"",G55/F55) | J55: 0.16315377 | K55: 0.1225 | L55: =IF(G55=0,"",H55/G55) | M55: 6.611441 | N55: =IF(E55=0,"",2*M55/E55) | O55: 0 | P55: 0.022772941 | Q55: 0.026227625 | R55: =IF(OR(P55="",Q55=""),"",P55-Q55) | Y55: No HMDA mortgage reporting | Z55: =ROUND(100*(Scoring!$B$11*(1-IFERROR(PERCENTRANK($I$2:$I$67,I55),0.5))+Scoring!$B$12*IFERROR(PERCENTRANK($J$2:$J$67,J55),0.5)+Scoring!$B$13*IFERROR(PERCENTRANK($K$2:$K$67,K55),0.5)+Scoring!$B$14*IFERROR(PERCENTRANK($R$2:$R$67,R55),0.5)+Scoring!$B$15*(1-IFERROR(PERCENTRANK($N$2:$N$67,N55),0.5))+Scoring!$B$16*(1-IFERROR(PERCENTRANK($L$2:$L$67,L55),0.5))),0) | AA55: =IF(AND(Z55>=Scoring!$B$18,E55>=Scoring!$B$20,Y55<>"Already takes broker loans"),"Tier 1",IF(Z55>=Scoring!$B$19,"Tier 2","Tier 3"))
A56: cu:64834 | B56: California Lithuanian CU | C56: Santa Monica | D56: Los Angeles | E56: 175.12525 | F56: 142.99523 | G56: 129.86937 | H56: 55.165036 | I56: =IF(F56=0,"",G56/F56) | J56: 0.25124029 | K56: 0.174 | L56: =IF(G56=0,"",H56/G56) | M56: 5.021747 | N56: =IF(E56=0,"",2*M56/E56) | O56: 0 | P56: 0.23723967 | Q56: 0.26869132 | R56: =IF(OR(P56="",Q56=""),"",P56-Q56) | Y56: No HMDA mortgage reporting | Z56: =ROUND(100*(Scoring!$B$11*(1-IFERROR(PERCENTRANK($I$2:$I$67,I56),0.5))+Scoring!$B$12*IFERROR(PERCENTRANK($J$2:$J$67,J56),0.5)+Scoring!$B$13*IFERROR(PERCENTRANK($K$2:$K$67,K56),0.5)+Scoring!$B$14*IFERROR(PERCENTRANK($R$2:$R$67,R56),0.5)+Scoring!$B$15*(1-IFERROR(PERCENTRANK($N$2:$N$67,N56),0.5))+Scoring!$B$16*(1-IFERROR(PERCENTRANK($L$2:$L$67,L56),0.5))),0) | AA56: =IF(AND(Z56>=Scoring!$B$18,E56>=Scoring!$B$20,Y56<>"Already takes broker loans"),"Tier 1",IF(Z56>=Scoring!$B$19,"Tier 2","Tier 3"))
A57: cu:14542 | B57: Vida CU | C57: Ontario | D57: San Bernardino | E57: 174.60935 | F57: 150.41688 | G57: 88.771637 | H57: 33.400853 | I57: =IF(F57=0,"",G57/F57) | J57: 0.45538129 | K57: 0.1375 | L57: =IF(G57=0,"",H57/G57) | M57: 6.202191 | N57: =IF(E57=0,"",2*M57/E57) | O57: 0 | P57: 0.028128399 | Q57: 0.062105043 | R57: =IF(OR(P57="",Q57=""),"",P57-Q57) | Y57: No HMDA mortgage reporting | Z57: =ROUND(100*(Scoring!$B$11*(1-IFERROR(PERCENTRANK($I$2:$I$67,I57),0.5))+Scoring!$B$12*IFERROR(PERCENTRANK($J$2:$J$67,J57),0.5)+Scoring!$B$13*IFERROR(PERCENTRANK($K$2:$K$67,K57),0.5)+Scoring!$B$14*IFERROR(PERCENTRANK($R$2:$R$67,R57),0.5)+Scoring!$B$15*(1-IFERROR(PERCENTRANK($N$2:$N$67,N57),0.5))+Scoring!$B$16*(1-IFERROR(PERCENTRANK($L$2:$L$67,L57),0.5))),0) | AA57: =IF(AND(Z57>=Scoring!$B$18,E57>=Scoring!$B$20,Y57<>"Already takes broker loans"),"Tier 1",IF(Z57>=Scoring!$B$19,"Tier 2","Tier 3"))
A58: cu:62323 | B58: E-central CU | C58: Pasadena | D58: Los Angeles | E58: 173.53387 | F58: 130.72664 | G58: 110.53321 | H58: 23.520065 | I58: =IF(F58=0,"",G58/F58) | J58: 0.31368229 | K58: 0.2341 | L58: =IF(G58=0,"",H58/G58) | M58: 0 | N58: =IF(E58=0,"",2*M58/E58) | O58: 0 | P58: -0.022712585 | Q58: -0.070808081 | R58: =IF(OR(P58="",Q58=""),"",P58-Q58) | Y58: No HMDA mortgage reporting | Z58: =ROUND(100*(Scoring!$B$11*(1-IFERROR(PERCENTRANK($I$2:$I$67,I58),0.5))+Scoring!$B$12*IFERROR(PERCENTRANK($J$2:$J$67,J58),0.5)+Scoring!$B$13*IFERROR(PERCENTRANK($K$2:$K$67,K58),0.5)+Scoring!$B$14*IFERROR(PERCENTRANK($R$2:$R$67,R58),0.5)+Scoring!$B$15*(1-IFERROR(PERCENTRANK($N$2:$N$67,N58),0.5))+Scoring!$B$16*(1-IFERROR(PERCENTRANK($L$2:$L$67,L58),0.5))),0) | AA58: =IF(AND(Z58>=Scoring!$B$18,E58>=Scoring!$B$20,Y58<>"Already takes broker loans"),"Tier 1",IF(Z58>=Scoring!$B$19,"Tier 2","Tier 3"))
A59: cu:12543 | B59: Torrance Community CU | C59: Torrance | D59: Los Angeles | E59: 162.92793 | F59: 150.82525 | G59: 69.950032 | H59: 8.272762 | I59: =IF(F59=0,"",G59/F59) | J59: 0.51775692 | K59: 0.1015 | L59: =IF(G59=0,"",H59/G59) | M59: 0.4 | N59: =IF(E59=0,"",2*M59/E59) | O59: 0 | P59: 0.035791645 | Q59: 0.075556544 | R59: =IF(OR(P59="",Q59=""),"",P59-Q59) | Y59: No HMDA mortgage reporting | Z59: =ROUND(100*(Scoring!$B$11*(1-IFERROR(PERCENTRANK($I$2:$I$67,I59),0.5))+Scoring!$B$12*IFERROR(PERCENTRANK($J$2:$J$67,J59),0.5)+Scoring!$B$13*IFERROR(PERCENTRANK($K$2:$K$67,K59),0.5)+Scoring!$B$14*IFERROR(PERCENTRANK($R$2:$R$67,R59),0.5)+Scoring!$B$15*(1-IFERROR(PERCENTRANK($N$2:$N$67,N59),0.5))+Scoring!$B$16*(1-IFERROR(PERCENTRANK($L$2:$L$67,L59),0.5))),0) | AA59: =IF(AND(Z59>=Scoring!$B$18,E59>=Scoring!$B$20,Y59<>"Already takes broker loans"),"Tier 1",IF(Z59>=Scoring!$B$19,"Tier 2","Tier 3"))
A60: cu:95052 | B60: South Bay CU | C60: Redondo Beach | D60: Los Angeles | E60: 160.5741 | F60: 144.1394 | G60: 123.45765 | H60: 58.602203 | I60: =IF(F60=0,"",G60/F60) | J60: 0.13582465 | K60: 0.0941 | L60: =IF(G60=0,"",H60/G60) | M60: 3.812 | N60: =IF(E60=0,"",2*M60/E60) | O60: 0 | P60: 0.075953063 | Q60: 0.033626278 | R60: =IF(OR(P60="",Q60=""),"",P60-Q60) | Y60: No HMDA mortgage reporting | Z60: =ROUND(100*(Scoring!$B$11*(1-IFERROR(PERCENTRANK($I$2:$I$67,I60),0.5))+Scoring!$B$12*IFERROR(PERCENTRANK($J$2:$J$67,J60),0.5)+Scoring!$B$13*IFERROR(PERCENTRANK($K$2:$K$67,K60),0.5)+Scoring!$B$14*IFERROR(PERCENTRANK($R$2:$R$67,R60),0.5)+Scoring!$B$15*(1-IFERROR(PERCENTRANK($N$2:$N$67,N60),0.5))+Scoring!$B$16*(1-IFERROR(PERCENTRANK($L$2:$L$67,L60),0.5))),0) | AA60: =IF(AND(Z60>=Scoring!$B$18,E60>=Scoring!$B$20,Y60<>"Already takes broker loans"),"Tier 1",IF(Z60>=Scoring!$B$19,"Tier 2","Tier 3"))
A61: cu:5816 | B61: Interfaith CU | C61: Montclair | D61: San Bernardino | E61: 134.82976 | F61: 118.31485 | G61: 72.243147 | H61: 31.904412 | I61: =IF(F61=0,"",G61/F61) | J61: 0.43492977 | K61: 0.1187 | L61: =IF(G61=0,"",H61/G61) | M61: 0.625 | N61: =IF(E61=0,"",2*M61/E61) | O61: 0 | P61: 0.0098789266 | Q61: 0.0038803761 | R61: =IF(OR(P61="",Q61=""),"",P61-Q61) | Y61: No HMDA mortgage reporting | Z61: =ROUND(100*(Scoring!$B$11*(1-IFERROR(PERCENTRANK($I$2:$I$67,I61),0.5))+Scoring!$B$12*IFERROR(PERCENTRANK($J$2:$J$67,J61),0.5)+Scoring!$B$13*IFERROR(PERCENTRANK($K$2:$K$67,K61),0.5)+Scoring!$B$14*IFERROR(PERCENTRANK($R$2:$R$67,R61),0.5)+Scoring!$B$15*(1-IFERROR(PERCENTRANK($N$2:$N$67,N61),0.5))+Scoring!$B$16*(1-IFERROR(PERCENTRANK($L$2:$L$67,L61),0.5))),0) | AA61: =IF(AND(Z61>=Scoring!$B$18,E61>=Scoring!$B$20,Y61<>"Already takes broker loans"),"Tier 1",IF(Z61>=Scoring!$B$19,"Tier 2","Tier 3"))
A62: cu:7770 | B62: Thinkwise CU | C62: San Bernardino | D62: San Bernardino | E62: 122.80651 | F62: 109.56982 | G62: 56.068532 | H62: 6.514414 | I62: =IF(F62=0,"",G62/F62) | J62: 0.41040643 | K62: 0.0859 | L62: =IF(G62=0,"",H62/G62) | M62: 0 | N62: =IF(E62=0,"",2*M62/E62) | O62: 0 | P62: 0.035389125 | Q62: 0.0094286743 | R62: =IF(OR(P62="",Q62=""),"",P62-Q62) | Y62: No HMDA mortgage reporting | Z62: =ROUND(100*(Scoring!$B$11*(1-IFERROR(PERCENTRANK($I$2:$I$67,I62),0.5))+Scoring!$B$12*IFERROR(PERCENTRANK($J$2:$J$67,J62),0.5)+Scoring!$B$13*IFERROR(PERCENTRANK($K$2:$K$67,K62),0.5)+Scoring!$B$14*IFERROR(PERCENTRANK($R$2:$R$67,R62),0.5)+Scoring!$B$15*(1-IFERROR(PERCENTRANK($N$2:$N$67,N62),0.5))+Scoring!$B$16*(1-IFERROR(PERCENTRANK($L$2:$L$67,L62),0.5))),0) | AA62: =IF(AND(Z62>=Scoring!$B$18,E62>=Scoring!$B$20,Y62<>"Already takes broker loans"),"Tier 1",IF(Z62>=Scoring!$B$19,"Tier 2","Tier 3"))
A63: cu:7817 | B63: Sea Air CU | C63: Seal Beach | D63: Orange | E63: 118.82794 | F63: 90.814229 | G63: 45.076631 | H63: 8.268195 | I63: =IF(F63=0,"",G63/F63) | J63: 0.52745246 | K63: 0.2339 | L63: =IF(G63=0,"",H63/G63) | M63: 1.49 | N63: =IF(E63=0,"",2*M63/E63) | O63: 0 | P63: 0.0016779006 | Q63: -0.051763589 | R63: =IF(OR(P63="",Q63=""),"",P63-Q63) | Y63: No HMDA mortgage reporting | Z63: =ROUND(100*(Scoring!$B$11*(1-IFERROR(PERCENTRANK($I$2:$I$67,I63),0.5))+Scoring!$B$12*IFERROR(PERCENTRANK($J$2:$J$67,J63),0.5)+Scoring!$B$13*IFERROR(PERCENTRANK($K$2:$K$67,K63),0.5)+Scoring!$B$14*IFERROR(PERCENTRANK($R$2:$R$67,R63),0.5)+Scoring!$B$15*(1-IFERROR(PERCENTRANK($N$2:$N$67,N63),0.5))+Scoring!$B$16*(1-IFERROR(PERCENTRANK($L$2:$L$67,L63),0.5))),0) | AA63: =IF(AND(Z63>=Scoring!$B$18,E63>=Scoring!$B$20,Y63<>"Already takes broker loans"),"Tier 1",IF(Z63>=Scoring!$B$19,"Tier 2","Tier 3"))
A64: cu:10351 | B64: La Loma CU | C64: Loma Linda | D64: San Bernardino | E64: 116.6413 | F64: 110.45866 | G64: 73.869347 | H64: 21.835204 | I64: =IF(F64=0,"",G64/F64) | J64: 0.2839338 | K64: 0.0973 | L64: =IF(G64=0,"",H64/G64) | M64: 1.720555 | N64: =IF(E64=0,"",2*M64/E64) | O64: 0 | P64: 0.022001434 | Q64: 0.028203165 | R64: =IF(OR(P64="",Q64=""),"",P64-Q64) | Y64: No HMDA mortgage reporting | Z64: =ROUND(100*(Scoring!$B$11*(1-IFERROR(PERCENTRANK($I$2:$I$67,I64),0.5))+Scoring!$B$12*IFERROR(PERCENTRANK($J$2:$J$67,J64),0.5)+Scoring!$B$13*IFERROR(PERCENTRANK($K$2:$K$67,K64),0.5)+Scoring!$B$14*IFERROR(PERCENTRANK($R$2:$R$67,R64),0.5)+Scoring!$B$15*(1-IFERROR(PERCENTRANK($N$2:$N$67,N64),0.5))+Scoring!$B$16*(1-IFERROR(PERCENTRANK($L$2:$L$67,L64),0.5))),0) | AA64: =IF(AND(Z64>=Scoring!$B$18,E64>=Scoring!$B$20,Y64<>"Already takes broker loans"),"Tier 1",IF(Z64>=Scoring!$B$19,"Tier 2","Tier 3"))
... A67: cu:7557 | B67: Glendale CU | C67: Glendale | D67: Los Angeles | E67: 102.65985 | F67: 86.514506 | G67: 63.482508 | H67: 28.61782 | I67: =IF(F67=0,"",G67/F67) | J67: 0.29215283 | K67: 0.1258 | L67: =IF(G67=0,"",H67/G67) | M67: 5.4501 | N67: =IF(E67=0,"",2*M67/E67) | O67: 0 | P67: -0.016039271 | Q67: 0.071527799 | R67: =IF(OR(P67="",Q67=""),"",P67-Q67) | Y67: No HMDA mortgage reporting | Z67: =ROUND(100*(Scoring!$B$11*(1-IFERROR(PERCENTRANK($I$2:$I$67,I67),0.5))+Scoring!$B$12*IFERROR(PERCENTRANK($J$2:$J$67,J67),0.5)+Scoring!$B$13*IFERROR(PERCENTRANK($K$2:$K$67,K67),0.5)+Scoring!$B$14*IFERROR(PERCENTRANK($R$2:$R$67,R67),0.5)+Scoring!$B$15*(1-IFERROR(PERCENTRANK($N$2:$N$67,N67),0.5))+Scoring!$B$16*(1-IFERROR(PERCENTRANK($L$2:$L$67,L67),0.5))),0) | AA67: =IF(AND(Z67>=Scoring!$B$18,E67>=Scoring!$B$20,Y67<>"Already takes broker loans"),"Tier 1",IF(Z67>=Scoring!$B$19,"Tier 2","Tier 3"))
